Workbook

Sheet README
B1: J-REITオフィス系16法人 保有物件・収支比較データベース
A3: 【完成】全16法人・1,273行(物件1,203+期中譲渡等+法人一括16行)の投入・5段階検証を完了(2026/8/8) | B3: 1. 基本情報
A4: 16法人取得価格合計: 8,485,612百万円(約8.49兆円)。各法人とも最新決算期短信と照合済(鑑定評価額・NLA・テナント数は原則完全一致、取得・帳簿の物件別合算と合計欄の差は百万円未満切捨て/四捨五入(HLCのみ)の累積として全件注記済) | B4: 作成日 | C4: 2026年8月7日
A5: 開示水準の類型: ①費用内訳フル開示=MHR・NUD・HLC(46/67)・JRE(76/79)・MTR(18/20) ②収益のみ開示=NBF・GOR・DOI・ICG・JEI・JPR・SHR・HFR・KDX ③法人一括のみ=TRE・SKR。E列(開示区分)で判別可能 | B5: 築年数計算の基準日 | C5: 46241
A6: 原資料内の系統的丸め: 科目別切捨てによる内訳チェック(U列)1〜5千円・掲載損益との1千円差(多数法人)、KDXの3層切捨て構造(物件<用途小計<総合計)等はすべて備考に注記。数値は開示掲載値のまま転記(改変ゼロ) | B6: 目的 | C6: オフィス系J-REIT16法人の保有物件の基本情報と物件別収支（収入・費用・利益）を、法人をまたいで同一基準で比較できる形で管理する。
A7: 次回更新の目安: NBF第50期(2026/8中旬)→JEI 2026年6月期(8月下旬)→TRE第46期(9/14)→HLC第25期(10月中旬)→MTR第49期(10月下旬)→JRE第50期・SKR(11月・SKRは上場廃止の可能性)→KDX第43期・SHR第24期(12月中旬)→HFR第50期(2027/1)。SKRはTOB成立時に更新対象から除外検討 | B7: 対象決算期 | C7: 各法人の最新決算期（法人マスタ「最新決算期」列参照）。決算期は法人ごとに異なるため、比較の際は期間月数と年換算値を用いること。
B9: 2. シート構成
B10: 法人マスタ | C10: 16法人の基本情報（コード、タイプ、スポンサー、決算期、投入状況）
B11: 物件マスタ | C11: 物件の基本情報（1物件1行）：所在地、延床面積、階数、竣工年月、取得価格、鑑定評価額、稼働率ほか
B12: 物件収支 | C12: 物件別の期次損益（1物件×1決算期で1行）：賃貸事業収入・費用の内訳、賃貸事業損益、NOI、NCF
B13: 比較ビュー | C13: 物件マスタ・物件収支・法人マスタを自動連結し、年換算NOI利回り・月坪賃料収入・費用率などの法人横断比較指標を数式で算出（全列自動計算・入力不要）
B15: 3. 単位・表記ルール（比較可能性の担保）
B16: 金額 | C16: 物件収支シート＝千円 ／ 取得価格・帳簿価額・鑑定評価額＝百万円 ／ 比較ビューの年換算NOI＝百万円
B17: 面積 | C17: ㎡で入力。坪換算は 1㎡=0.3025坪 で比較ビューが自動計算
B18: 比率 | C18: 稼働率・利回り等は小数で入力（例：97.5% → 0.975）。セル書式が%表示に変換
B19: 竣工年月・取得年月 | C19: 日付として入力（例：2005/3/1）。表示は「2005年03月」形式
B20: 決算期の表記 | C20: 「YYYY年M月期（第N期）」で統一。法人マスタと物件収支で完全一致させること（比較ビューのSUMIFSが文字列一致で参照するため）
B22: 4. 色の凡例
B23: 青字 | C23: 原資料から転記した手入力データ
B24: 黒字 | C24: 数式（編集しないこと）
B25: 黄色セル | C25: 要確認・要入力の項目
B26: 薄橙の行 | C26: 架空物件による記入例（実データ投入後に削除すること）
B28: 5. データ出典ルール（優先順位）
B29: ① | C29: 各投資法人の直近期「有価証券報告書」内「個別不動産の収支状況」→ 物件別の収入・費用内訳の一次情報
B30: ② | C30: 各投資法人の「資産運用報告」「決算短信」「決算説明資料」→ 物件基本情報・稼働率・鑑定評価額
B31: ③ | C31: 各投資法人ウェブサイトのポートフォリオページ → 建物概要の補完
B32: 非開示の扱い | C32: テナント同意が得られない物件は収支が非開示・一部非開示となる。開示区分列に「非開示」「一部非開示」と記録し、空欄と区別する。非開示物件を含む法人平均・合計を扱う際は注記必須。
B34: 6. 検証プロセス（各法人のデータ投入ごとに5段階を実施し、実施日を法人マスタ備考に記録）
B35: 第1段階：転記照合 | C35: 原資料PDFと全セルを突合（金額は千円単位まで一致確認）
B36: 第2段階：内訳整合 | C36: 物件収支の「内訳チェック」列が全行0、または0でない場合は備考欄で原資料由来の丸め差等として説明済みであることを確認（例：GOR-ALL行の差3千円は開示数値の丸めに由来）
B37: 第3段階：法人合計照合 | C37: 物件収支の法人別合計を、当該法人の損益計算書の賃貸事業収入・費用と突合（差異は非開示物件・期中売買物件として説明できること）
B38: 第4段階：指標妥当性 | C38: 比較ビューでNOI利回りが概ね2〜7%のレンジ外、稼働率100%超、月坪賃料が市場相場と乖離する物件を抽出し原資料へ立ち返って精査
B39: 第5段階：再計算検証 | C39: 全数式の再計算とエラー0件の確認、無作為抽出3物件の手計算照合
B41: 7. 現在の投入状況
B42: 法人マスタ | C42: 16法人投入済（決算期・期数に「要確認」フラグ付きの項目あり。黄色セル参照）
B43: 物件マスタ・物件収支 | C43: GOR（グローバル・ワン）投入済：物件18行（期末16物件＋期中譲渡1＋第46期取得1）＋ポートフォリオ全体行。物件別収支は収益・稼働率・テナント数まで開示、費用内訳は法人一括のみ（GOR-ALL行参照）。他15法人は順次投入。
A45: 【環境認証シート】(2026/8/7調査)
A46: ・各法人のウェブサイト/ESGレポート/決算説明資料/適時開示の公表情報に基づき、ZEB(BELS含む)/DBJ/CASBEE/LEED/WELLの5分類で物件別に収録。
A47: ・1物件が複数認証を保有する場合は複数行。同一物件の事務所/住宅/店舗別認証も別行(認証名称に区分を付記)。
A48: ・本シートに記載のない物件は、各法人の開示上、上記5分類の認証取得の公表が確認できなかった物件(=開示ベースで認証なし)。
A49: ・出典時点は法人により異なる(2024/11末〜2026/6末)。詳細と法人別の注意事項は環境認証シート下部「法人別出典・注記」参照。
A50: ・5分類外の認証(東京都低炭素モデルビル、SMBCサステイナブルビルディング、JHEP、Fitwel、ResReal、東京都建築物省エネ性能評価書、優良特定地球温暖化対策事業所)は非収録(各法人注記に記載)。
A51: ・WELLは16法人の開示上、狭義のWELL認証(IWBI)の取得公表が確認できなかったため0件。CASBEEウェルネスオフィスはCASBEEに収録。
A52: ・出典URL: NBF esg.nbf-m.com / JRE jre-esg.com / GOR go-reit.co.jp / DOI daiwa-office.co.jp / ICG ichigo-office.co.jp / JEI excellent-reit.co.jp(ESGレポート) / MHR mori-hills-reit.co.jp / JPR jpr-reit.co.jp / TRE tokyu-reit.co.jp / HLC hulic-reit.co.jp / NUD nud-reit.co.jp / HFR heiwa-re.co.jp(ESGレポート2025) / SHR sekisuihouse-reit.co.jp / MTR mt-reit.jp / SKR s-reit.co.jp(適時開示・決算説明資料) / KDX kdx-reit.com
A53: ・物件マスタ末尾「環境認証数」列=当該物件の収録認証件数(COUNTIF)。
A55: 【環境認証シート 表記統一ルール(2026/8/8改訂)】
A56: ・認証名称は法人ごとの表記ゆれ(BELS評価/BELS認証/BELS等)を統一。ZEB=「BELS」、ZEB評価併記時のみ「BELS（ZEB Ready）」「BELS（ZEB Oriented）」。
A57: ・CASBEE=「CASBEE-不動産」「CASBEE-建築」「CASBEE-ウェルネスオフィス」。出典が評価ツールを特定していないものは「CASBEE-不動産／建築（区分不明）」。
... A454: ◆検証(5観点): ①絞込3種のselectが表示される ②並び替えが3ボタン ③3軸すべてで方向トグルが動作 ④利回り降順が実データ順と一致 ⑤絞込とソートの併用が正常。自動テスト15本すべてエラー0・要修正0、レイアウト検査も幅390/1280で文字重なり0件。

Sheet 法人マスタ
A1: 法人ID | B1: 証券コード | C1: 投資法人名 | D1: 運用タイプ | E1: オフィス比率の目安 | F1: 主要スポンサー | G1: 決算月 | H1: 最新決算期（本DB収録対象） | I1: 保有物件数（直近開示） | J1: 取得価格合計(百万円) | K1: 物件データ投入数 | L1: 確認ステータス | M1: 備考
A2: NBF | B2: 8951 | C2: 日本ビルファンド投資法人 | D2: オフィス特化型 | E2: ほぼ100% | F2: 三井不動産・住友生命ほか | G2: 6月・12月 | H2: 2025年12月期（第49期） | I2: 70 | J2: 1519039 | K2: =COUNTIF(物件マスタ!$B:$B,$A2) -> 71 | L2: 確認済（短信照合） | M2: 決算月6月/12月。第49期短信より投入し5段階検証実施(2026/8/7)。※2026年6月期(第50期)短信は2026/8中旬公表見込み→公表後に差替検討。J-REIT最大規模・オフィス特化。格付JCR AA+/R&I AA/S&P A+。期末LTV43.3%・長期固定比率83.9%。収益開示59物件・非開示11物件(残差8,862百万円=一括比18.3%、取得価格比率19.2%と符合し整合確認済)。原資料の丸め表示に伴う合計欄と個別合算の微差は物件マスタNBF-ALL行注記参照
A3: JRE | B3: 8952 | C3: ジャパンリアルエステイト投資法人 | D3: オフィス特化型 | E3: ほぼ100% | F3: 三菱地所ほか | G3: 3月・9月 | H3: 2026年3月期（第49期） | I3: 79 | J3: 1197029 | K3: =COUNTIF(物件マスタ!$B:$B,$A3) -> 80 | L3: 確認済（短信照合） | M3: 日本初のJ-REIT2銘柄の一つ(2001/9上場・オフィス特化)。物件別収支は費用内訳までフル開示(76/79物件・百万円単位)。取得価格は千円単位開示でDB中最高精度。竣工年月は短信非掲載のため未収録。※第50期(2026年9月期)短信は2026/11中旬公表見込
A4: GOR | B4: 8958 | C4: グローバル・ワン不動産投資法人 | D4: オフィス特化型 | E4: ほぼ100% | F4: 明治安田生命・近鉄グループHD・三菱UFJ信託ほか | G4: 3月・9月 | H4: 2026年3月期（第45期） | I4: 17 | J4: 232273 | K4: =COUNTIF(物件マスタ!$B:$B,$A4) -> 19 | L4: 確認済（短信照合） | M4: 物件数・取得価格は2026/4/24現在（公式サイト）。物件・収支データは第45期短信より投入し5段階検証実施（2026/8/7）。物件収支の費用内訳は法人一括開示のみ（GOR-ALL行に収録）
A5: DOI | B5: 8976 | C5: 大和証券オフィス投資法人 | D5: オフィス特化型 | E5: ほぼ100% | F5: 大和証券グループ本社 | G5: 5月・11月 | H5: 2026年5月期（第41期） | I5: 58 | J5: 487709 | K5: =COUNTIF(物件マスタ!$B:$B,$A5) -> 61 | L5: 確認済（短信照合） | M5: 決算月5月/11月。物件・収支は第41期短信より投入し5段階検証実施(2026/8/7)。物件別収益は千円単位開示だが7物件はテナント同意なく非開示。竣工年月・階数は短信開示(登記簿ベース)。2026/12/1効力で投資口1:4分割・自己投資口取得(上限15億円)を公表。個別物件収支データ(Excel)を別途公表しており物件別費用の将来拡充が可能
A6: ICG | B6: 8975 | C6: いちごオフィスリート投資法人 | D6: オフィス主体型 | E6: 高 | F6: いちご | G6: 4月・10月 | H6: 2026年4月期（第41期） | I6: 87 | J6: 222508 | K6: =COUNTIF(物件マスタ!$B:$B,$A6) -> 89 | L6: 確認済（短信照合） | M6: 決算月4月/10月。第41期短信より投入し5段階検証実施(2026/8/7)。中規模オフィス特化型・87物件は16法人中最多クラスの小口分散。物件別に当期総賃料収入(その他収入含む発生ベース)をフル開示し88行合算が一括と整合(切捨て差42千円のみ)=MHRに次ぐ開示水準。ICG独自の地域区分(品川区含む「都心6区」等)は物件備考に保存。格付JCR A+。期末有利子負債126,638百万円。期後2026/7/17に4物件一括譲渡(住友商事・売却益約59億円)。※2026年10月期(第42期)短信は2026/12中旬公表見込→公表後更新検討
A7: JEI | B7: 8987 | C7: ジャパンエクセレント投資法人 | D7: オフィス特化型 | E7: ほぼ100% | F7: 日鉄興和不動産・第一生命・積水ハウスほか | G7: 6月・12月 | H7: 2025年12月期（第39期） | I7: 33 | J7: 290534 | K7: =COUNTIF(物件マスタ!$B:$B,$A7) -> 35 | L7: 確認済（短信照合） | M7: 2026年6月期は2026年8月下旬公表見込み（公表後に収録対象期の更新を検討）。物件・収支データは第39期短信より投入し5段階検証実施（2026/8/7）。物件別収益は千円単位開示だが8物件はテナント同意なく非開示
A8: MHR | B8: 3234 | C8: 森ヒルズリート投資法人 | D8: 総合型（オフィス中心） | E8: 約9割 | F8: 森ビル | G8: 1月・7月 | H8: 2026年1月期（第39期） | I8: 11 | J8: 416049 | K8: =COUNTIF(物件マスタ!$B:$B,$A8) -> 12 | L8: 確認済（短信照合） | M8: 決算月1月/7月。第39期短信より投入し5段階検証実施(2026/8/7)。16法人中初の物件別費用フル開示(11物件全て)。主要テナント森ビル(固定型ML中心、賃貸面積66.4%)。期後: ラフォーレ原宿底地各5%を2026/7・12に追加譲渡予定、自己投資口取得(上限10億円)実施済
A9: JPR | B9: 8955 | C9: 日本プライムリアルティ投資法人 | D9: 複合型（オフィス＋商業） | E9: 高 | F9: 東京建物ほか | G9: 6月・12月 | H9: 2025年12月期（第48期） | I9: 67 | J9: 556828 | K9: =COUNTIF(物件マスタ!$B:$B,$A9) -> 69 | L9: 確認済（短信照合） | M9: 決算月6月/12月。第48期短信(2026/3/10訂正=実績数値への影響なし)より投入し5段階検証実施(2026/8/7)。オフィス・都市型商業複合型(ホテル2物件含む)。JPR独自の地域区分(品川区含む「東京都心」等)は物件備考に保存。格付JCR AA/R&I AA-/S&P A(長期)。期末LTV43.4%・長期固定比率86.7%。開示51物件・非開示16物件(残差検証済)。期中譲渡HDC神戸を含め68行収録。取得価格合計欄と個別合算の1百万円差(切捨て由来)は物件マスタJPR-ALL行注記参照。2025/7/1投資口1:4分割
A10: TRE | B10: 8957 | C10: 東急リアル・エステート投資法人 | D10: 複合型（オフィス＋商業） | E10: 高 | F10: 東急 | G10: 1月・7月 | H10: 2026年1月期（第45期） | I10: 28 | J10: 244261 | K10: =COUNTIF(物件マスタ!$B:$B,$A10) -> 29 | L10: 確認済（短信照合） | M10: 決算月1月/7月。第45期短信より投入し5段階検証実施(2026/8/7)。渋谷・東急沿線特化型(商業・オフィス・住宅・複合)。物件別は帳簿・算定価額・契約賃料・PMLを開示する一方、取得価格・発生ベース収支は非開示という16法人中特異な開示スタイル(物件マスタ20・21・25列と備考に収録)。帳簿・月額賃料の合計欄と個別合算の各13千円差(切捨て由来)は物件マスタTRE-ALL行注記参照。格付JCR AA-/R&I A+。期末有利子負債1,055億円・加重平均利率0.82%。※2026年7月期(第46期)短信は2026/9/14公表予定→公表後更新検討
A11: HLC | B11: 3295 | C11: ヒューリックリート投資法人 | D11: 複合型（東京コマーシャル＋次世代アセット） | E11: 高 | F11: ヒューリック | G11: 2月・8月 | H11: 2026年2月期（第24期） | I11: 67 | J11: 421530 | K11: =COUNTIF(物件マスタ!$B:$B,$A11) -> 70 | L11: 確認済（短信照合） | M11: 東京コマーシャル・プロパティ(オフィス・商業)重点+ホテル+次世代アセット。取得価格は百万円未満四捨五入。物件別収支フル開示46/67物件(費用内訳含む・NOIのみ22物件)。期後NC5物件譲渡→62物件。※第25期(2026年8月期)短信は2026/10中旬公表見込
A12: NUD | B12: 8956 | C12: NTT都市開発リート投資法人 | D12: 複合型（オフィス＋住宅） | E12: 中〜高 | F12: NTT都市開発 | G12: 4月・10月 | H12: 2026年4月期（第47期） | I12: 62 | J12: 295266 | K12: =COUNTIF(物件マスタ!$B:$B,$A12) -> 64 | L12: 確認済（短信照合） | M12: 決算月4月/10月。第47期短信+公式ポートフォリオ一覧より投入し5段階検証実施(2026/8/7)。オフィス25+レジデンス36+優先出資証券1(秋葉原UDX19%)の複合型。物件別に費用内訳を含む損益をフル開示(百万円単位)=MHRに次ぐ第3の費用開示法人(非開示6物件は損益・NOIのみ開示、この2値の列解釈は用途計との突合で検証確定済)。NTTグループがテナント上位を占める(上位10テナント中8社・面積22.8%)。格付JCR AA。期末有利子負債147,250百万円(長期比率94.6%)。※2026年10月期(第48期)短信は2026/12中旬公表見込→公表後更新検討
A13: HFR | B13: 8966 | C13: 平和不動産リート投資法人 | D13: 複合型（オフィス＋住宅） | E13: 中 | F13: 平和不動産 | G13: 5月・11月 | H13: 2026年5月期（第49期） | I13: 136 | J13: 265046 | K13: =COUNTIF(物件マスタ!$B:$B,$A13) -> 139 | L13: 確認済（短信照合） | M13: 決算月5月/11月。第49期短信より投入し5段階検証実施(2026/8/7)。中小型オフィス46+レジデンス90の136物件複合型。物件別に鑑定・帳簿・取得・NLA・稼働・テナント数・賃貸事業収入(千円)・PMLを開示(Of-40アーク森ビルの収入のみML同意なく非開示)。竣工年月は短信非掲載。個別物件収支データ(費用内訳含む)はxlsx別綴で公表=将来精緻化候補。2010/10にジャパン・シングルレジデンス投資法人と合併。5年連続で毎年6月に公募増資を実施する成長軌道(期後2026/6も11,762百万円調達・3物件取得で139物件→8/7現在141物件)。格付JCR AA-(安定的)。期末有利子負債138,680百万円(総資産LTV48.55%)。※2026年11月期(第50期)短信は2027/1中旬公表見込→公表後更新検討
... A17: KDX | B17: 8972 | C17: ＫＤＸ不動産投資法人 | D17: 総合型 | E17: 中 | F17: ケネディクス | G17: 4月・10月 | H17: 2026年4月期（第42期） | I17: 343 | J17: 1218978 | K17: =COUNTIF(物件マスタ!$B:$B,$A17) -> 346 | L17: 確認済（短信照合） | M17: 決算月4月/10月。2023/11の3リート合併(旧KDXオフィス8972+ケネディクス・レジデンシャル・ネクスト3278+ケネディクス商業リート3453)で誕生した国内最大級総合型。第42期短信より投入(2026/8/7)。343物件・取得1,218,978百万円=16法人中最大。物件別開示は取得・帳簿・鑑定・NLA・稼働・テナント数・総賃貸事業収入(百万円単位)。所在地・竣工年月は短信非掲載(個別物件データブックxlsx別綴)→エリア区分は短信の東京経済圏/地方経済圏2区分を収録。物流14・宿泊6・ヘルスケア42の収入とアーク森ビルは非開示。規模が最大のため3応答分割で全343物件+譲渡2の投入完了・5段階検証実施(2026/8/7)。※第43期(2026年10月期)短信は2026/12中旬公表見込→公表後更新検討
A18: CTR | B18: 3488 | C18: セントラル・リート投資法人（旧ザイマックス・リート投資法人） | D18: 総合型（オフィス・商業・ホテル） | E18: 約56%（取得価格ベース） | F18: 名鉄都市開発・ザイマックスグループ（2025年10月よりダブルスポンサー） | G18: 2月・8月 | H18: 第16期（2026年2月期） | I18: 20 | J18: 50591 | K18: 20 | L18: 確認済（公式サイト・有報） | M18: 2025年11月の投資主総会承認によりザイマックス・リート投資法人から名称変更。2026年3月30日にエニシオ名駅・上前津KDビルを取得し20物件。第16期末の法人合計は稼働率99.9%・総賃貸可能面積86,030.38㎡・NOI 1,291百万円（半期）。平均稼働率は2026年6月30日現在99.6%
A19: ORI | B19: 3290 | C19: Oneリート投資法人 | D19: 総合型（中小規模オフィス中心） | E19: 約74%（取得価格ベース） | F19: みずほ信託銀行（みずほフィナンシャルグループ） | G19: 2月・8月 | H19: 第25期（2026年2月期） | I19: 34 | J19: 151202 | K19: 34 | L19: 確認済（公式サイト・決算短信） | M19: 2013年10月にSIA不動産投資法人として上場、2017年6月に現名称へ。2025年5月に用途を限定しない総合型へ規約変更しホテルへの投資を開始。中小規模オフィス（延床概ね33,000㎡未満）を重点投資対象とする。第25期末は28物件だが、2026年3月19日にホテル5物件とONEST飯田橋スクエアを取得し34物件（うちONEST京都烏丸スクエアは東京建物へ4回に分割して譲渡中、2026年3月に10%譲渡済で残90%）

Sheet 投資法人戦略
A1: 法人ID | B1: 投資法人名 | C1: 戦略ポジション | D1: 戦略の軸 | E1: モデルの構造 | F1: 主要リスク | G1: ESG・管理の特徴 | H1: 物件数 | I1: 資産規模(兆円・鑑定評価額ベース) | J1: 1物件平均(百万円・鑑定評価額ベース) | K1: 上位5物件集中度(%・鑑定評価額ベース) | L1: 粗利回り中央値(%・鑑定評価額ベース) | M1: 築年中央値 | N1: 稼働率中央値(%) | O1: 賃貸面積中央値(㎡) | P1: 東京圏比率(%) | Q1: 都心5区比率(%) | R1: オフィス比率(%) | S1: 用途構成 | T1: エリア構成 | U1: 認証保有率(%) | V1: 資産規模の算定物件数 | W1: 取得価格の開示率(%) | X1: 参考:取得価格合計(兆円) | Y1: 粗利回りの算定物件数 | Z1: 稼働率の算定物件数
A2: NBF | B2: 日本ビルファンド投資法人 | C2: 超大型コア・オフィス特化型 | D2: 規模の優位で「都心の象徴的資産」を押さえる | E2: 1物件あたり平均254億円（鑑定評価額ベース）はMHR(460億円)に次ぐ規模。三井不動産の開発物件を継続取得し、都心5区44%・東京圏74%に集中。オフィス100%で用途分散を放棄する代わり、テナント信用力と立地で下方リスクを抑える設計。 | F2: オフィス市況の一方向リスクを丸ごと負う。上位5物件で32.5%を占め、大型1棟の稼働変動が全体に効く。 | G2: 認証保有率97.1%は全法人最高。ESG適格性を資金調達コストと出口価格に転嫁する戦略が最も徹底している。 | H2: 70 | I2: 1.78 | J2: 25403 | K2: 32.5 | L2: 6.25 | N2: 100 | O2: 12481 | P2: 74.3 | Q2: 44.3 | R2: 100 | S2: オフィス100% | T2: 都心5区44% / 他23区19% / 他3大都市圏14% | U2: 97.1 | V2: 70 | W2: 100 | X2: 1.52 | Y2: 54 | Z2: 69
A3: JRE | B3: ジャパンリアルエステイト投資法人 | C3: 大型コア・オフィス特化型（全国分散併用） | D3: 都心の質と地方中核都市の利回りを両建てする | E3: 都心5区49%と最も都心比率が高い一方、地方圏19%を明示的に組み込む。1物件平均183億円。三菱地所の開発力を背景に、丸の内型のプライム物件と地方中核都市のランドマークを組み合わせ、キャップレート差を収益源にする。 | F3: 地方物件は流動性が低く、出口が限られる。テナント集中度の管理が生命線。 | G3: 認証91.1%。管理は三菱地所プロパティマネジメントに集約するが、物件名を非開示とする情報統制型。 | H3: 79 | I3: 1.45 | J3: 18320 | K3: 29.5 | L3: 5.74 | N3: 100 | O3: 7880 | P3: 67.1 | Q3: 49.4 | R3: 100 | S3: オフィス100% | T3: 都心5区49% / 地方圏19% / 他3大都市圏14% | U3: 91.1 | V3: 79 | W3: 100 | X3: 1.2 | Y3: 73 | Z3: 78
A4: GOR | B4: グローバル・ワン不動産投資法人 | C4: 少数精鋭・大型オフィス型 | D4: 18物件に絞り、1棟あたりの質で勝負する | E4: 保有18物件で1物件平均158億円。上位5物件で48.9%と集中度が高い。複数スポンサー（明治安田生命・近鉄・農林中金・三菱UFJ信託）の物件供給を受ける独立系に近い構造。粗利回り4.60%（鑑定評価額ベース）はMHR(4.44%)に次ぐ16法人で2番目の低さで、価格の高い優良物件を保有していることを示す。 | F4: 物件数が少なく、1棟の退去がポートフォリオ全体の稼働に直結する。スポンサー単独の開発パイプラインに依存できない。 | G4: 認証77.8%。規模の制約を質で補う典型。 | H4: 18 | I4: 0.25 | J4: 15788 | K4: 48.9 | L4: 4.6 | M4: 16.7 | N4: 100 | O4: 8890 | P4: 55.6 | Q4: 22.2 | R4: 100 | S4: オフィス100% | T4: 他3大都市圏33% / 都心5区22% / 他23区17% | U4: 77.8 | V4: 16 | W4: 94.4 | X4: 0.23 | Y4: 15 | Z4: 16
A5: DOI | B5: 大和証券オフィス投資法人 | C5: 都心集中・中規模オフィス型 | D5: 都心5区に83%を集中させ、立地だけで選別する | E5: 都心5区82.8%・東京圏98.3%は16法人で突出。1物件平均108億円・賃貸面積中央値3,794㎡と中規模に振り、築年中央値28.7年の既存ビルを取得してバリューアップする発想。 | F5: 築古比率が高く、修繕・設備更新の資本的支出が構造的に重い。エリア分散が事実上ないため、都心オフィス需給の変調を直撃で受ける。 | G5: 認証63.8%は都心特化型として低め。築古ストックへの認証後付けが今後の課題。 | H5: 58 | I5: 0.63 | J5: 10828 | K5: 34.3 | L5: 5.2 | M5: 28.7 | N5: 100 | O5: 3794 | P5: 98.3 | Q5: 82.8 | R5: 100 | S5: オフィス100% | T5: 都心5区83% / 他23区12% / 東京圏3% | U5: 63.8 | V5: 58 | W5: 96.7 | X5: 0.49 | Y5: 50 | Z5: 58
A6: ICG | B6: いちごオフィスリート投資法人 | C6: 中小型ビルの再生（バリューアッド）型 | D6: 市場に埋もれた中小ビルを買い、手を入れて価値を上げる | E6: 87物件・1物件平均33億円・賃貸面積中央値2,765㎡と小型の部類（HFR 2,078㎡・SHR 2,306㎡に次ぐ小ささ）。都心5区41%だが他23区25%・地方20%と広く拾う。大型プライム市場では価格競争に勝てないため、競合の少ない中小ビル市場で「心築（再生）」により利回りを作る。 | F6: 物件数が多く1棟あたりが小さいため、管理オペレーションの効率が収益を左右する。テナントは中小企業中心で信用力が相対的に低い。 | G6: 認証21.8%は最低水準。中小ビルは認証取得の費用対効果が出にくく、ESG評価では構造的に不利。 | H6: 87 | I6: 0.29 | J6: 3319 | K6: 14.9 | L6: 5.64 | N6: 100 | O6: 2765 | P6: 75.9 | Q6: 41.4 | R6: 97.7 | S6: オフィス98% / 商業2% | T6: 都心5区41% / 他23区25% / 他3大都市圏20% | U6: 21.8 | V6: 87 | W6: 0 | Y6: 87 | Z6: 87
A7: JEI | B7: ジャパンエクセレント投資法人 | C7: 大型オフィス・準コア型 | D7: 東京圏の大型物件を軸に、地方中核都市で利回りを補完 | E7: 33物件・1物件平均107億円。都心5区39%に対し東京圏21%・地方18%と分散。粗利回り7.06%（鑑定評価額ベース）は16法人で最高水準で、価格に対して収益の厚い物件を選好していることを示す。 | F7: 高利回りは市場が求めたリスクプレミアムでもある。地方大型物件の出口戦略が問われる。 | G7: 認証78.8%。日鉄興和不動産系の開発物件を受け皿とする構造。 | H7: 33 | I7: 0.35 | J7: 10655 | K7: 40 | L7: 7.06 | N7: 100 | O7: 6634 | P7: 69.7 | Q7: 39.4 | R7: 100 | S7: オフィス100% | T7: 都心5区39% / 東京圏21% / 地方圏18% | U7: 78.8 | V7: 33 | W7: 97.1 | X7: 0.29 | Y7: 25 | Z7: 33
A8: MHR | B8: 森ヒルズリート投資法人 | C8: 都心プレミアム集中型（最も極端な集中戦略） | D8: 森ビルの都心大規模再開発に100%張る | E8: 11物件すべてが都心5区。1物件平均460億円は16法人で最大、上位5物件で79.9%を占める。六本木ヒルズ・虎ノ門ヒルズ・アーク森ビルといった街区型再開発の持分を保有し、オフィス73%に住宅18%・商業9%を混ぜた複合用途で単一用途リスクを緩和。 | F8: 集中度79.9%は16法人で最高。1物件の稼働・賃料改定が分配金に直結する。全物件が都心5区かつ森ビルの開発物件であり、単一デベロッパーへの依存度が最も高い部類。 | G8: 粗利回り4.44%（鑑定評価額ベース）は最低水準。市場が最も低いキャップレートで評価している＝資産価値が最も高く評価されている裏返し。 | H8: 11 | I8: 0.51 | J8: 46000 | K8: 79.9 | L8: 4.44 | M8: 25.5 | N8: 100 | O8: 16153 | P8: 100 | Q8: 100 | R8: 72.7 | S8: オフィス73% / 住宅18% / 商業9% | T8: 都心5区100% | U8: 72.7 | V8: 11 | W8: 100 | X8: 0.42 | Y8: 10 | Z8: 11
A9: JPR | B9: 日本プライムリアルティ投資法人 | C9: オフィス＋商業のバランス型 | D9: 用途と地域の二軸で分散し、変動を平準化する | E9: オフィス75%・商業22%。都心5区45%に東京圏21%を組み合わせ、上位5物件の集中度30.8%は低位。1物件平均100億円。東京建物の開発物件を軸にしつつ、特定用途・特定物件への依存を意図的に避けた設計。 | F9: 分散は変動を抑える一方で突出した成長も生みにくい。商業施設は個別のテナント業績に業績が連動する。 | G9: 築年中央値30.1年と築古。認証71.6%。計画修繕の巧拙が長期のNOIを決める帯にある。 | H9: 67 | I9: 0.67 | J9: 10015 | K9: 30.8 | L9: 6.12 | M9: 30.1 | N9: 100 | O9: 5185 | P9: 77.6 | Q9: 44.8 | R9: 74.6 | S9: オフィス75% / 商業22% / ホテル3% | T9: 都心5区45% / 東京圏21% / 他23区12% | U9: 71.6 | V9: 67 | W9: 98.5 | X9: 0.56 | Y9: 50 | Z9: 67
A10: TRE | B10: 東急リアル・エステート投資法人 | C10: 沿線集中・複合用途型 | D10: 東急沿線という「面」に投資し、街の成長を取り込む | E10: 28物件すべてが東京圏、都心5区71%。1物件平均117億円。オフィス64%・商業21%・住宅11%の複合。渋谷・二子玉川など東急が開発を主導するエリアに集中し、街づくりの果実を賃料成長として回収する構造。 | F10: 沿線集中は地域経済の変調に対する分散が効かない。築年中央値31.4年と築古で、更新投資の負担が重い。 | G10: LEED ND（まちづくり部門）を取得した二子玉川ライズを保有。街区単位でのESG評価という他法人にない資産を持つ。 | H10: 28 | I10: 0.33 | J10: 11676 | K10: 43.5 | M10: 31.4 | N10: 100 | O10: 4616 | P10: 100 | Q10: 71.4 | R10: 64.3 | S10: オフィス64% / 商業21% / 住宅11% | T10: 都心5区71% / 他23区21% / 東京圏7% | U10: 75 | V10: 28 | W10: 0 | Y10: 0 | Z10: 28
A11: HLC | B11: ヒューリックリート投資法人 | C11: 用途分散・駅前立地特化型 | D11: 駅前という立地条件を共通項に、用途を跨いで分散する | E11: オフィス51%・ヘルスケア21%・商業12%。東京圏92.5%だが他23区45%が都心5区40%を上回る。1物件平均73億円。ヒューリックの「駅前・駅近」戦略を継承し、用途ではなく立地で選別する点が他法人と決定的に異なる。ヘルスケア21%は高齢化を捉えた長期契約型キャッシュフロー。 | F11: ヘルスケアはオペレーター信用力に依存し、代替が難しい。用途分散はモニタリング負荷を高める。 | G11: 管理をヒューリックビルマネジメントに内製集約。グループ内で運営品質を統制する垂直統合型。 | H11: 67 | I11: 0.49 | J11: 7259 | K11: 34.6 | L11: 5.48 | M11: 21.2 | N11: 100 | O11: 3957 | P11: 92.5 | Q11: 40.3 | R11: 50.7 | S11: オフィス51% / ヘルスケア21% / 商業12% | T11: 他23区45% / 都心5区40% / 東京圏7% | U11: 41.8 | V11: 67 | W11: 97.1 | X11: 0.42 | Y11: 44 | Z11: 67
A12: NUD | B12: NTT都市開発リート投資法人 | C12: 住宅・オフィス二本柱型 | D12: 変動の大きいオフィスを、安定的な住宅で中和する | E12: 住宅58%・オフィス40%。都心5区56.5%と都心比率は高い。1物件平均55億円と中規模。オフィスの景気連動性を、賃料変動の小さい都心住宅で打ち消すポートフォリオ設計。 | F12: 住宅は個別の賃料上昇余地が限られ、成長エンジンにはなりにくい。稼働率中央値99.2%と既に高位で、稼働改善の余地が乏しい。 | G12: 認証71.0%。住宅系でのDBJ認証取得（23件）を積極化しており、オフィス偏重になりがちな認証取得を住宅にも広げている点が特徴。 | H12: 62 | I12: 0.34 | J12: 5497 | K12: 31.5 | L12: 5.3 | N12: 99.2 | P12: 88.7 | Q12: 56.5 | R12: 40.3 | S12: 住宅58% / オフィス40% / その他2% | T12: 都心5区56% / 他23区31% / 他3大都市圏8% | U12: 71 | V12: 61 | W12: 98.4 | X12: 0.3 | Y12: 52 | Z12: 61
A13: HFR | B13: 平和不動産リート投資法人 | C13: 小口分散・住宅主体型 | D13: 小さく多く持ち、1棟の失敗が効かない構造をつくる | E13: 136物件・1物件平均24億円は16法人で最小。上位5物件の集中度11.9%も最小で、極端な分散型。住宅66%・オフィス34%、他23区38%と都心外の実需エリアが中心。 | F13: 1棟あたりが小さいため管理コストの比率が上がりやすい。物件数の多さは運営負荷とデータ管理の難易度を高める。 | G13: 認証22.8%と低位。小規模物件は認証取得の採算が合わず、ESG面では構造的な制約を抱える。 | H13: 136 | I13: 0.33 | J13: 2436 | K13: 11.9 | L13: 5.41 | N13: 99.25 | O13: 2078 | P13: 70.6 | Q13: 22.8 | R13: 33.8 | S13: 住宅66% / オフィス34% | T13: 他23区38% / 都心5区23% / 他3大都市圏15% | U13: 22.8 | V13: 136 | W13: 98.6 | X13: 0.27 | Y13: 135 | Z13: 136
A14: SHR | B14: 積水ハウス・リート投資法人 | C14: 住宅特化・スポンサー開発直結型 | D14: 積水ハウスの開発供給を受け皿として安定成長する | E14: 住宅96%。他23区46%・都心5区18%と、都心よりも実需の厚いエリアに展開。1物件平均48億円。築年中央値16.8年と16法人で最も築浅で、スポンサーの新築供給を継続的に取得している証左。米国物件も保有し地理分散を試行。 | F14: 稼働率中央値96.4%は16法人で最低。住宅は入退去が常態で、稼働の底上げ余地が最大の改善テーマ。 | G14: 認証81.2%と住宅系では突出。CASBEE不動産103件・BELS★5×9件で、ZEH水準の新築供給がそのまま認証率に直結している。 | H14: 138 | I14: 0.67 | J14: 4823 | K14: 36.9 | L14: 4.83 | M14: 16.8 | N14: 96.4 | O14: 2306 | P14: 78.3 | Q14: 18.1 | R14: 3.6 | S14: 住宅96% / オフィス4% | T14: 他23区46% / 都心5区18% / 東京圏14% | U14: 81.2 | V14: 138 | W14: 92 | X14: 0.56 | Y14: 136 | Z14: 138
A15: MTR | B15: 森トラストリート投資法人 | C15: 大型・複合（オフィス＋ホテル）型 | D15: オフィスの安定とホテルの変動を意図的に組み合わせる | E15: 20物件・1物件平均268億円と大型。オフィス50%・ホテル30%・商業15%。上位5物件で57.3%と集中度が高い。森トラストの大型開発とホテル運営力を背景に、景気拡大局面ではホテルが伸び、後退局面ではオフィスが支える設計。 | F15: ホテルは変動費型で業績連動性が高く、外的ショックに脆い。集中度の高さがそれを増幅する。 | G15: 認証95.0%は最高水準。DBJ18件で、評価語（国内トップクラス等）ベースの高位認証を多数保有。 | H15: 20 | I15: 0.54 | J15: 26821 | K15: 57.3 | L15: 5.09 | M15: 27.4 | N15: 100 | O15: 20952 | P15: 75 | Q15: 45 | R15: 50 | S15: オフィス50% / ホテル30% / 商業15% | T15: 都心5区45% / 東京圏20% / 他3大都市圏15% | U15: 95 | V15: 20 | W15: 100 | X15: 0.46 | Y15: 18 | Z15: 20
A16: SKR | B16: サンケイリアルエステート投資法人 | C16: 総合型への転換途上 | D16: オフィス単独から用途分散へ舵を切っている最中 | E16: 16物件・オフィス56%・ホテル38%・物流6%。築年中央値8.85年と16法人で最も築浅。2023年に運用ガイドラインを変更し総合型REITへ転換しており、現在のポートフォリオは移行途上の姿。 | F16: 規模が小さく上位5物件で51.1%を占める。2026年に非公開化を目的としたTOBが実施され不成立に終わっており、資本政策の不確実性を抱える。 | G16: 認証25.0%と低位。ただし築浅比率が高く、今後の認証取得余地は大きい。 | H16: 16 | I16: 0.1 | J16: 6041 | K16: 51.1 | M16: 8.85 | N16: 100 | O16: 5386 | P16: 56.2 | Q16: 37.5 | R16: 56.2 | S16: オフィス56% / ホテル38% / 物流6% | T16: 都心5区38% / 地方圏25% / 他3大都市圏19% | U16: 25 | V16: 16 | W16: 100 | X16: 0.09 | Y16: 0 | Z16: 16
A17: KDX | B17: ＫＤＸ不動産投資法人 | C17: 超分散・独立系マルチアセット型 | D17: スポンサー系列に依存せず、市場から広く買い集める | E17: 343物件は16法人で最多、1物件平均39億円・上位5物件の集中度9.0%は最小。住宅39%・オフィス25%・商業17%と用途を広く分散し、東京圏68%・地方圏32%。特定の開発会社の供給に依存せず、市場全体を調達源とする独立系の典型。 | F17: 物件数の多さは管理・情報開示の負荷を高める。分散は下振れを抑えるが、個別物件のバリューアップ効果は薄まる。 | G17: 管理をケネディクス・プロパティ・デザインに集約し、183棟を実名公開。16法人で最も管理体制の透明性が高い。 | H17: 343 | I17: 1.34 | J17: 3913 | K17: 9 | L17: 5.33 | N17: 100 | O17: 3534 | P17: 67.9 | Q17: 0 | R17: 25.1 | S17: 住宅39% / オフィス25% / 商業17% | T17: 東京圏68% / 地方圏32% | U17: 56.6 | V17: 343 | W17: 99.4 | X17: 1.22 | Y17: 243 | Z17: 343
A18: CTR | B18: セントラル・リート投資法人 | C18: 小型総合型・中部圏シフト途上 | D18: PM実績を持つスポンサーの運営力で中小型物件の収益を引き上げる | E18: 20物件・1物件平均32億円と16法人中で最小の部類。オフィス55%・商業30%・ホテル10%の総合型で、都心5区25%・他3大都市圏35%と地方分散が進む。スポンサーのザイマックスはJ-REITのPM受託で実績首位であり、自ら運営する物件を組み入れることで、中小型ビルでも管理品質を担保する構造。2025年10月に名鉄都市開発が51%を取得しダブルスポンサー体制へ移行、2026年3月に名古屋の2物件を取得し中部圏へのシフトを開始した。 | F18: 資産規模506億円は16法人で最小級で、1物件の稼働変動が分配金に直結する。オフィス・商業・ホテル・住宅と用途が分散する一方、各用途の物件数が少なく用途別の運営ノウハウの蓄積が限定的。スポンサー交代に伴う投資方針の変化も不確実性となる。 | G18: 認証取得は12物件・延床面積ベース76.1%。CASBEE不動産8物件（うちSランク7）とBELS4物件を保有し、エニシオ名駅はBELS★5。保有オフィス9物件すべてで再生可能エネルギー100%電力を導入。GRESBリアルエステイト評価で4スター・グリーンスター、開示評価はAレベル。 | H18: 20 | I18: 0.06 | J18: 3231 | K18: 46.7 | M18: 26.4 | P18: 65 | Q18: 25 | R18: 55 | S18: オフィス55% / 商業30% / ホテル10% | T18: 他3大都市圏35% / 都心5区25% / 東京圏25% | U18: 60 | V18: 20 | W18: 100 | X18: 0.05 | Y18: 0 | Z18: 0
A19: ORI | B19: Oneリート投資法人 | C19: 中小型オフィス特化からホテル併走型への転換途上 | D19: みずほの情報網で中小型ビルを仕入れ、運営改善で価値を引き上げる | E19: 34物件・1物件平均51億円。延床概ね33,000㎡未満の中小規模オフィスを重点対象とし、都心5区は17.6%と低く、その他23区・東京周辺都市部・地方中核市に分散する。2025年5月に用途無限定の総合型へ規約変更し、2026年3月にホテル5物件（286億円）を一括取得してホテル比率を約25%へ引き上げた。物件入替を継続的に行い、2025年以降だけで南品川3物件・MY熊本・ONEST南大塚・新川一丁目を売却、京都烏丸スクエアも東京建物へ4回分割で譲渡中。中長期の資産規模目標は2,000億円。 | F19: 中小型ビルは大企業の集約移転の受け皿になりにくく、テナント数が多いぶん個別の退去が積み上がりやすい。築年中央値34.5年と16法人で最も古い部類にあり、資本的支出が重い（第25期は533百万円で修繕費131百万円と合わせ664百万円）。ホテルへの急速な傾斜は収益の変動性を高める可能性があり、運営ノウハウの蓄積も途上。 | G19: 認証取得は25物件（CASBEE不動産21件・DBJ Green Building 3件・BELS 2件）。CASBEEはAランクが18件と中心で、Sランクは立川錦町ビルと大同生命水戸ビルの2件。ONEST箱崎ビルはBELS6つ星。延床面積ベースのグリーンビル認証取得割合を2030年度に90%とするKPIを掲げる。GRESBリアルエステイト評価で4スター・Green Starを8年連続獲得。 | H19: 34 | I19: 0.17 | J19: 5081 | K19: 32 | M19: 34.5 | N19: 100 | O19: 4200 | P19: 61.8 | Q19: 17.6 | R19: 79.4 | S19: オフィス79% / ホテル21% | T19: その他23区24% / 東京周辺都市部21% / その他3大都市圏21% / 都心5区18% / 政令市12% / 地方6% | U19: 73.5 | V19: 34 | W19: 100 | X19: 0.15 | Z19: 28

Sheet 物件マスタ
A1: 物件ID | B1: 法人ID | C1: 物件名 | D1: 主用途 | E1: 都道府県 | F1: 市区町村 | G1: 住所（詳細） | H1: エリア区分 | I1: 所有形態 | J1: 持分割合 | K1: 敷地面積(㎡) | L1: 延床面積(㎡) | M1: 賃貸可能面積(㎡) | N1: 階数(地上) | O1: 階数(地下) | P1: 竣工年月 | Q1: 築年数(年) | R1: 取得年月 | S1: 取得価格(百万円) | T1: 期末帳簿価額(百万円) | U1: 期末鑑定評価額(百万円) | V1: 含み損益(百万円) | W1: 期末稼働率 | X1: テナント数 | Y1: PML(%) | Z1: 出典（資料名・頁） | AA1: 確認ステータス | AB1: 備考 | AC1: 環境認証数 | AD1: 含み損益率(%)＝鑑定÷帳簿−1 | AE1: 対取得価格の値上がり率(%)＝鑑定÷取得−1
A2: NBF-ALL | B2: NBF | C2: 【NBFポートフォリオ全体】 | D2: オフィス | E2: 東京都 | F2: 千代田区 | H2: ─ | I2: 70物件（2025/12/31時点） | L2: 51094.82 | M2: 1239418 | P2: 40148 | Q2: =IF(OR($A199="",P199=""),"",ROUND(YEARFRAC(P199,README!$C$5),1)) -> 24.9 | S2: 1519039 | T2: 1411111 | U2: 1778190 | V2: =IF($A199="","",IF(OR(T199="",U199=""),"",U199-T199)) -> 1869 | W2: 0.983 | X2: 1584 | Y2: 2.9 | Z2: NBF 2025年12月期(第49期)決算短信(2026/2/16公表) | AA2: 確認済※ | AB2: J-REIT最大規模(取得価格累計1兆5,190億円)。取得・帳簿・鑑定は千円開示を百万円換算(小数3位=千円精度)。本行は短信合計欄の値。【原資料の丸め表示に関する注記】帳簿価額は円単位の値を千円未満切捨て表示のため、70物件個別値の合算(1,411,110,984千円)は合計欄より35千円小(各地域小計の差-16/-6/-3/-9千円も全て負符号で物件数以内=切捨て累積として整合的)。取得価格も按分物件の円未満端数により総計欄と-1千円差(地域小計は完全一致)。NLAは個別値の小数点以下四捨五入により合計欄と1㎡差。鑑定・テナント数は完全一致。期末稼働98.3%/期中平均98.5%。NLA・テナント数にNBF虎ノ門ビル(底地)は含まず。最大テナント三井不動産(賃貸面積47.0%・サブリース転貸方式24物件)。期後: 2026/1公募増資等(発行済8,815,000口へ)、2026/3/31日本橋本町M-SQUARE(32,108百万円)・豊洲ベイサイドクロスタワー追加持分(14,810百万円)取得予定、2026/6/30住友電設ビル・2026/7/1 NBF札幌南二条ビル譲渡予定 | AC2: =COUNTIF(環境認証!$A$2:$A$849,A199) -> 1 | AD2: 42.4 | AE2: 29.7
A3: NBF-01 | B3: NBF | C3: 新宿三井ビルディング | D3: オフィス | E3: 東京都 | F3: 新宿区 | H3: 都心5区 | I3: 所有権（信託受益権準共有80%） | J3: 0.8 | L3: 20958.79 | M3: 102718 | P3: 37742 | Q3: =IF(OR($A129="",P129=""),"",ROUND(YEARFRAC(P129,README!$C$5),1)) | S3: 170000 | T3: 175537.94 | U3: 184000 | V3: 8462 | W3: 0.984 | X3: 100 | Y3: 2.8 | Z3: NBF 2025年12月期(第49期)決算短信(2026/2/16公表) | AA3: 確認済 | AB3: オフィス。竣工年月・階数・面積は短信非掲載(有報等で補完予定)。J-REIT運用資産中最大の旗艦物件。サブリース型(変動賃料) | AC3: =COUNTIF(環境認証!$A$2:$A$849,A129) -> 1 | AD3: 4.8 | AE3: 8.2
A4: NBF-02 | B4: NBF | C4: 飯田橋グラン・ブルーム | D4: オフィス | E4: 東京都 | F4: 千代田区 | H4: 都心5区 | I4: 区分所有権（信託受益権） | L4: 140667.09 | M4: 54185 | P4: 41122 | Q4: =IF(OR($A130="",P130=""),"",ROUND(YEARFRAC(P130,README!$C$5),1)) | S4: 138909.1 | T4: 135524 | U4: 154000 | V4: 18476 | W4: 1 | X4: 34 | Y4: 0.3 | Z4: NBF 2025年12月期(第49期)決算短信(2026/2/16公表) | AA4: 確認済 | AB4: オフィス。竣工年月・階数・面積は短信非掲載(有報等で補完予定)。2021/9・2022/3・2023/3の3回取得合計。サブリース型(変動) | AC4: =COUNTIF(環境認証!$A$2:$A$849,A130) -> 1 | AD4: 13.6 | AE4: 10.9
A5: NBF-03 | B5: NBF | C5: 六本木ティーキューブ | D5: オフィス | E5: 東京都 | F5: 港区 | H5: 都心5区 | I5: 区分所有権（信託受益権） | L5: 15467.77 | M5: 34608 | P5: 40179 | Q5: =IF(OR($A131="",P131=""),"",ROUND(YEARFRAC(P131,README!$C$5),1)) | S5: 62800 | T5: 62129.469 | U5: 63200 | V5: 1071 | W5: 0.965 | X5: 65 | Y5: 1.8 | Z5: NBF 2025年12月期(第49期)決算短信(2026/2/16公表) | AA5: 確認済 | AB5: オフィス。竣工年月・階数・面積は短信非掲載(有報等で補完予定)。サブリース型(変動) | AC5: =COUNTIF(環境認証!$A$2:$A$849,A131) -> 2 | AD5: 1.7 | AE5: 0.6
A6: NBF-04 | B6: NBF | C6: 西新宿三井ビルディング | D6: オフィス | E6: 東京都 | F6: 新宿区 | H6: 都心5区 | I6: 所有権（信託受益権準共有50%） | J6: 0.5 | L6: 41741.18 | M6: 33770 | P6: 40391 | Q6: =IF(OR($A132="",P132=""),"",ROUND(YEARFRAC(P132,README!$C$5),1)) | S6: 45392.204 | T6: 31915.468 | U6: 46100 | V6: 14185 | W6: 0.997 | X6: 52 | Y6: 7 | Z6: NBF 2025年12月期(第49期)決算短信(2026/2/16公表) | AA6: 確認済 | AB6: オフィス。竣工年月・階数・面積は短信非掲載(有報等で補完予定)。任意組合出資持分(西新宿六丁目共有組合)含む。2002〜2023年の8回分割取得合計。サブリース型(変動) | AC6: =COUNTIF(環境認証!$A$2:$A$849,A132) -> 1 | AD6: 44.4 | AE6: 1.6
A7: NBF-05 | B7: NBF | C7: セレスティン芝三井ビルディング | D7: オフィス | E7: 東京都 | F7: 港区 | G7: 横浜市神奈川区金港町2-6 | H7: 都心5区 | I7: 所有権（信託受益権準共有）※期末60% | J7: 0.6 | K7: 2720.3 | L7: 19968.2 | M7: 38011 | P7: 40210 | Q7: =IF(OR($A133="",P133=""),"",ROUND(YEARFRAC(P133,README!$C$5),1)) | S7: 42000 | T7: 41134.739 | U7: 47200 | V7: 6065 | W7: 1 | X7: 11 | Z7: NBF 2025年12月期(第49期)決算短信(2026/2/16公表) | AA7: 確認済 | AB7: オフィス。竣工年月・階数・面積は短信非掲載(有報等で補完予定)。2013/5・2018/3の取得合計。ホテル部分は固定賃料契約 | AC7: =COUNTIF(環境認証!$A$2:$A$849,A133) -> 1 | AD7: 14.7 | AE7: 12.4
A8: NBF-06 | B8: NBF | C8: ＮＢＦ品川タワー | D8: オフィス | E8: 東京都 | F8: 港区 | H8: 都心5区 | I8: 所有権 共有持分50%（信託受益権） | J8: 0.5 | L8: 78897.42 | M8: 22778 | P8: 37316 | Q8: =IF(OR($A134="",P134=""),"",ROUND(YEARFRAC(P134,README!$C$5),1)) | S8: 36300 | T8: 37303.912 | U8: 47700 | V8: 10396 | W8: 0.997 | X8: 11 | Y8: 2.8 | Z8: NBF 2025年12月期(第49期)決算短信(2026/2/16公表) | AA8: 確認済 | AB8: オフィス。竣工年月・階数・面積は短信非掲載(有報等で補完予定)。主要テナント:楽天グループ | AC8: =COUNTIF(環境認証!$A$2:$A$849,A134) -> 1 | AD8: 27.9 | AE8: 31.4
A9: NBF-07 | B9: NBF | C9: ＮＢＦプラチナタワー | D9: オフィス | E9: 東京都 | F9: 港区 | G9: 千葉市中央区富士見2-5-12 | H9: 都心5区 | I9: 所有権（信託受益権） | J9: 1 | K9: 2487.92 | L9: 14201.97 | M9: 33503 | N9: 11 | O9: 0 | P9: 44927 | Q9: =IF(OR($A135="",P135=""),"",ROUND(YEARFRAC(P135,README!$C$5),1)) | R9: 46111 | S9: 31000 | T9: 25321.171 | U9: 60800 | V9: 35479 | W9: 0.981 | X9: 8 | Y9: 9.2 | Z9: NBF 2025年12月期(第49期)決算短信(2026/2/16公表) | AA9: 確認済 | AB9: オフィス。竣工年月・階数・面積は短信非掲載(有報等で補完予定)。鑑定評価額60,800百万円は取得価格の約2倍。主要テナント:アクサ生命 | AC9: =COUNTIF(環境認証!$A$2:$A$849,A135) -> 1 | AD9: 140.1 | AE9: 96.1
A10: NBF-08 | B10: NBF | C10: ＮＢＦコモディオ汐留 | D10: オフィス | E10: 東京都 | F10: 港区 | H10: 都心5区 | I10: 所有権（信託受益権） | J10: 1 | L10: 23161.27 | M10: 20538 | P10: 34759 | Q10: =IF(OR($A136="",P136=""),"",ROUND(YEARFRAC(P136,README!$C$5),1)) | S10: 28800 | T10: 27591.934 | U10: 35800 | V10: 8208 | W10: 1 | X10: 22 | Y10: 9.9 | Z10: NBF 2025年12月期(第49期)決算短信(2026/2/16公表) | AA10: 確認済 | AB10: オフィス。竣工年月・階数・面積は短信非掲載(有報等で補完予定)。 | AC10: =COUNTIF(環境認証!$A$2:$A$849,A136) -> 2 | AD10: 29.7 | AE10: 24.3
A11: NBF-09 | B11: NBF | C11: Ｇ－ＢＡＳＥ田町 | D11: オフィス | E11: 東京都 | F11: 港区 | H11: 都心5区 | I11: 所有権（共有持分20%） | J11: 0.2 | L11: 35198.77 | M11: 12481 | P11: 39995 | Q11: =IF(OR($A137="",P137=""),"",ROUND(YEARFRAC(P137,README!$C$5),1)) | S11: 28200 | T11: 26674.626 | U11: 29100 | V11: 2425 | W11: 1 | X11: 13 | Y11: 1.9 | Z11: NBF 2025年12月期(第49期)決算短信(2026/2/16公表) | AA11: 確認済 | AB11: オフィス。竣工年月・階数・面積は短信非掲載(有報等で補完予定)。2019年3・4月の取得合計 | AC11: =COUNTIF(環境認証!$A$2:$A$849,A137) -> 1 | AD11: 9.1 | AE11: 3.2
A12: NBF-10 | B12: NBF | C12: 虎ノ門琴平タワー | D12: オフィス | E12: 東京都 | F12: 港区 | G12: 大阪市東淀川区東中島1-19-4 | H12: 都心5区 | I12: 所有権（信託受益権） | J12: 1 | K12: 2034.62 | L12: 9383.85 | M12: 16848 | N12: 12 | O12: 0 | P12: 33178 | Q12: =IF(OR($A138="",P138=""),"",ROUND(YEARFRAC(P138,README!$C$5),1)) | R12: 45996 | S12: 24543 | T12: 17026 | U12: 34300 | V12: 17274 | W12: 0.988 | X12: 26 | Y12: 7.2 | Z12: NBF 2025年12月期(第49期)決算短信(2026/2/16公表) | AA12: 確認済 | AB12: オフィス。竣工年月・階数・面積は短信非掲載(有報等で補完予定)。敷地の賃借権を含む。2004/11・2006/4の取得合計。サブリース型(変動) | AC12: =COUNTIF(環境認証!$A$2:$A$849,A138) -> 2 | AD12: 101.5 | AE12: 39.8
A13: NBF-11 | B13: NBF | C13: ＮＢＦ渋谷ガーデンフロント | D13: オフィス | E13: 東京都 | F13: 渋谷区 | H13: 都心5区 | I13: 所有権（共有持分5%） | J13: 0.05 | L13: 75826.76 | M13: 14887 | P13: 42064 | Q13: =IF(OR($A139="",P139=""),"",ROUND(YEARFRAC(P139,README!$C$5),1)) | S13: 20269 | T13: 19878.48 | U13: 37200 | V13: 17322 | W13: 0.999 | X13: 4 | Y13: 0.8 | Z13: NBF 2025年12月期(第49期)決算短信(2026/2/16公表) | AA13: 確認済 | AB13: オフィス。竣工年月・階数・面積は短信非掲載(有報等で補完予定)。2004/2・2013/3の取得合計。主要テナント:インフィニオンテクノロジーズジャパン | AC13: =COUNTIF(環境認証!$A$2:$A$849,A139) -> 1 | AD13: 87.1 | AE13: 83.5
A14: NBF-12 | B14: NBF | C14: ＮＢＦ銀座通りビル | D14: オフィス | E14: 東京都 | F14: 中央区 | G14: 大阪市北区梅田3-3-20 | H14: 都心5区 | I14: 所有権（信託受益権準共有）※期末28% | J14: 0.28 | K14: 5999.33 | L14: 52982.94 | M14: 3440 | N14: 31 | O14: 2 | P14: 36678 | Q14: =IF(OR($A140="",P140=""),"",ROUND(YEARFRAC(P140,README!$C$5),1)) | R14: 45772 | S14: 17000 | T14: 17425.076 | U14: 19000 | V14: 1575 | W14: 1 | X14: 1 | Y14: 0.5 | Z14: NBF 2025年12月期(第49期)決算短信(2026/2/16公表) | AA14: 確認済 | AB14: オフィス。竣工年月・階数・面積は短信非掲載(有報等で補完予定)。地上権を含む | AC14: =COUNTIF(環境認証!$A$2:$A$849,A140) -> 2 | AD14: 9 | AE14: 11.8
A15: NBF-13 | B15: NBF | C15: 新宿三井ビルディング二号館 | D15: オフィス | E15: 東京都 | F15: 新宿区 | H15: 都心5区 | I15: 所有権（共有持分50%） | J15: 0.5 | L15: 32997.6 | M15: 14617 | P15: 37073 | Q15: =IF(OR($A141="",P141=""),"",ROUND(YEARFRAC(P141,README!$C$5),1)) | S15: 16285.4 | T15: 15775.462 | U15: 19600 | V15: 3825 | W15: 1 | X15: 44 | Y15: 0.5 | Z15: NBF 2025年12月期(第49期)決算短信(2026/2/16公表) | AA15: 確認済 | AB15: オフィス。竣工年月・階数・面積は短信非掲載(有報等で補完予定)。 | AC15: =COUNTIF(環境認証!$A$2:$A$849,A141) -> 0 | AD15: 24.2 | AE15: 20.4
A16: NBF-14 | B16: NBF | C16: 興和西新橋ビルＢ棟 | D16: オフィス | E16: 東京都 | F16: 港区 | G16: 福岡市博多区中洲中島町1-3 | H16: 都心5区 | I16: 所有権（信託受益権準共有83%） | J16: 0.83 | K16: 2064.27 | L16: 15647.62 | M16: 10405 | N16: 14 | O16: 0 | P16: 45078 | Q16: =IF(OR($A142="",P142=""),"",ROUND(YEARFRAC(P142,README!$C$5),1)) | R16: 45968 | S16: 13536.2 | T16: 11710.476 | U16: 13400 | V16: 1690 | W16: 0.989 | X16: 22 | Y16: 0.2 | Z16: NBF 2025年12月期(第49期)決算短信(2026/2/16公表) | AA16: 確認済 | AB16: オフィス。竣工年月・階数・面積は短信非掲載(有報等で補完予定)。2001〜2024年の5回分割取得合計。住宅部分はサブリース(変動) | AC16: =COUNTIF(環境認証!$A$2:$A$849,A142) -> 2 | AD16: 14.4 | AE16: -1
A17: NBF-15 | B17: NBF | C17: リバーシティＭ－ＳＱＵＡＲＥ | D17: オフィス | E17: 東京都 | F17: 中央区 | H17: 都心5区 | I17: 所有権（信託受益権） | J17: 1 | L17: 12823.15 | M17: 16261 | P17: 44348 | Q17: =IF(OR($A143="",P143=""),"",ROUND(YEARFRAC(P143,README!$C$5),1)) | S17: 13350 | T17: 11167.859 | U17: 13500 | V17: 2332 | W17: 1 | X17: 7 | Y17: 0.3 | Z17: NBF 2025年12月期(第49期)決算短信(2026/2/16公表) | AA17: 確認済 | AB17: オフィス。竣工年月・階数・面積は短信非掲載(有報等で補完予定)。 | AC17: =COUNTIF(環境認証!$A$2:$A$849,A143) -> 1 | AD17: 20.9 | AE17: 1.1
A18: NBF-16 | B18: NBF | C18: 新橋Ｍ－ＳＱＵＡＲＥ | D18: オフィス | E18: 東京都 | F18: 港区 | G18: 墨田区錦糸1-2-1 | H18: 都心5区 | I18: （期中譲渡済） | J18: 0 | K18: 18100.41 | L18: 49753.92 | M18: 5390 | Q18: =IF(OR($A144="",P144=""),"",ROUND(YEARFRAC(P144,README!$C$5),1)) | S18: 11900 | T18: 11061.277 | U18: 15100 | V18: 4039 | W18: 1 | X18: 10 | Z18: NBF 2025年12月期(第49期)決算短信(2026/2/16公表) | AA18: 確認済 | AB18: オフィス。竣工年月・階数・面積は短信非掲載(有報等で補完予定)。 | AC18: =COUNTIF(環境認証!$A$2:$A$849,A144) -> 1 | AD18: 36.5 | AE18: 26.9
A19: NBF-17 | B19: NBF | C19: ＮＢＦ虎ノ門ビル（底地） | D19: オフィス | E19: 東京都 | F19: 港区 | G19: 港区芝3-2-18 | H19: 都心5区 | I19: 所有権（信託受益権） | J19: 1 | K19: 1895.59 | L19: 11661.69 | M19: 7253.87 | N19: 12 | O19: 2 | P19: 33086 | Q19: =IF(OR($A145="",P145=""),"",ROUND(YEARFRAC(P145,README!$C$5),1)) | R19: 46135 | S19: 11416 | T19: 11869.021 | U19: 18600 | V19: 6731 | Y19: 10.8 | Z19: NBF 2025年12月期(第49期)決算短信(2026/2/16公表) | AA19: 確認済 | AB19: オフィス。竣工年月・階数・面積は短信非掲載(有報等で補完予定)。2025/1/6付で建物を譲渡(売却益7,838千円)し底地のみ保有。NLA・稼働率・テナント数は開示対象外。取得価格は物件取得時の土地取得価格 | AC19: =COUNTIF(環境認証!$A$2:$A$849,A145) -> 1 | AD19: 56.7 | AE19: 62.9
A20: NBF-18 | B20: NBF | C20: グラントウキョウサウスタワー | D20: オフィス | E20: 東京都 | F20: 千代田区 | H20: 都心5区 | I20: 16物件（2026/3/31時点） | M20: 2175 | Q20: =IF(OR($A146="",P146=""),"",ROUND(YEARFRAC(P146,README!$C$5),1)) | S20: 9398.168 | T20: 9441.945 | U20: 9610 | V20: 168 | W20: 0.961 | X20: 4 | Y20: 1.9 | Z20: NBF 2025年12月期(第49期)決算短信(2026/2/16公表) | AA20: 確認済 | AB20: オフィス。竣工年月・階数・面積は短信非掲載(有報等で補完予定)。2021/1取得価格から2024/3一部譲渡持分(約80%)を控除した残存持分の価格 | AC20: =COUNTIF(環境認証!$A$2:$A$849,A146) -> 1 | AD20: 1.8 | AE20: 2.3
A21: NBF-19 | B21: NBF | C21: ＮＢＦ ＡＬＬＩＡＮＣＥ | D21: オフィス | E21: 東京都 | F21: 品川区 | H21: 都心5区 | M21: 4035 | Q21: =IF(OR($A147="",P147=""),"",ROUND(YEARFRAC(P147,README!$C$5),1)) | S21: 9126 | T21: 9562.539 | U21: 13700 | V21: 4137 | W21: 1 | X21: 5 | Y21: 4.5 | Z21: NBF 2025年12月期(第49期)決算短信(2026/2/16公表) | AA21: 確認済 | AB21: オフィス。竣工年月・階数・面積は短信非掲載(有報等で補完予定)。 | AC21: =COUNTIF(環境認証!$A$2:$A$849,A147) -> 2 | AD21: 43.3 | AE21: 50.1
A22: NBF-20 | B22: NBF | C22: 四谷メディカルビル | D22: オフィス | E22: 東京都 | F22: 新宿区 | H22: 都心5区 | M22: 7481 | Q22: =IF(OR($A148="",P148=""),"",ROUND(YEARFRAC(P148,README!$C$5),1)) | S22: 8800 | T22: 7512.403 | U22: 7460 | V22: -52 | W22: 0.971 | X22: 39 | Y22: 5.8 | Z22: NBF 2025年12月期(第49期)決算短信(2026/2/16公表) | AA22: 確認済 | AB22: オフィス。竣工年月・階数・面積は短信非掲載(有報等で補完予定)。鑑定評価額が取得価格を下回る数少ない物件。サブリース型(変動) | AC22: =COUNTIF(環境認証!$A$2:$A$849,A148) -> 1 | AD22: -0.7 | AE22: -15.2
A23: NBF-21 | B23: NBF | C23: ＮＢＦ渋谷イースト | D23: オフィス | E23: 東京都 | F23: 渋谷区 | H23: 都心5区 | M23: 4999 | Q23: =IF(OR($A149="",P149=""),"",ROUND(YEARFRAC(P149,README!$C$5),1)) | S23: 8000 | T23: 8279.706 | U23: 11000 | V23: 2720 | W23: 1 | X23: 4 | Y23: 7.9 | Z23: NBF 2025年12月期(第49期)決算短信(2026/2/16公表) | AA23: 確認済 | AB23: オフィス。竣工年月・階数・面積は短信非掲載(有報等で補完予定)。 | AC23: =COUNTIF(環境認証!$A$2:$A$849,A149) -> 1 | AD23: 32.9 | AE23: 37.5
A24: NBF-22 | B24: NBF | C24: ＮＢＦ高輪ビル | D24: オフィス | E24: 東京都 | F24: 港区 | H24: 都心5区 | M24: 10448 | Q24: =IF(OR($A150="",P150=""),"",ROUND(YEARFRAC(P150,README!$C$5),1)) | S24: 6667.2 | T24: 6027.755 | U24: 7850 | V24: 1822 | W24: 1 | X24: 13 | Y24: 1.8 | Z24: NBF 2025年12月期(第49期)決算短信(2026/2/16公表) | AA24: 確認済 | AB24: オフィス。竣工年月・階数・面積は短信非掲載(有報等で補完予定)。 | AC24: =COUNTIF(環境認証!$A$2:$A$849,A150) -> 1 | AD24: 30.2 | AE24: 17.7
A25: NBF-23 | B25: NBF | C25: ＮＢＦ赤坂山王スクエア | D25: オフィス | E25: 東京都 | F25: 港区 | H25: 都心5区 | M25: 5258 | Q25: =IF(OR($A151="",P151=""),"",ROUND(YEARFRAC(P151,README!$C$5),1)) | S25: 6250 | T25: 6277.029 | U25: 8140 | V25: 1863 | W25: 1 | X25: 6 | Y25: 6.3 | Z25: NBF 2025年12月期(第49期)決算短信(2026/2/16公表) | AA25: 確認済 | AB25: オフィス。竣工年月・階数・面積は短信非掲載(有報等で補完予定)。 | AC25: =COUNTIF(環境認証!$A$2:$A$849,A151) -> 1 | AD25: 29.7 | AE25: 30.2
A26: NBF-24 | B26: NBF | C26: ＮＢＦ神田須田町ビル | D26: オフィス | E26: 東京都 | F26: 千代田区 | H26: 都心5区 | M26: 4470 | Q26: =IF(OR($A152="",P152=""),"",ROUND(YEARFRAC(P152,README!$C$5),1)) | S26: 5960 | T26: 5086.939 | U26: 8680 | V26: 3593 | W26: 1 | X26: 10 | Y26: 0.2 | Z26: NBF 2025年12月期(第49期)決算短信(2026/2/16公表) | AA26: 確認済 | AB26: オフィス。竣工年月・階数・面積は短信非掲載(有報等で補完予定)。 | AC26: =COUNTIF(環境認証!$A$2:$A$849,A152) -> 0 | AD26: 70.6 | AE26: 45.6
A27: NBF-25 | B27: NBF | C27: ＮＢＦ小川町ビルディング | D27: オフィス | E27: 東京都 | F27: 千代田区 | H27: 都心5区 | M27: 5340 | Q27: =IF(OR($A153="",P153=""),"",ROUND(YEARFRAC(P153,README!$C$5),1)) | S27: 5420 | T27: 5400.299 | U27: 6600 | V27: 1200 | W27: 1 | X27: 18 | Y27: 4.7 | Z27: NBF 2025年12月期(第49期)決算短信(2026/2/16公表) | AA27: 確認済 | AB27: オフィス。竣工年月・階数・面積は短信非掲載(有報等で補完予定)。2005/9・2020/11の取得合計。サブリース型(変動) | AC27: =COUNTIF(環境認証!$A$2:$A$849,A153) -> 0 | AD27: 22.2 | AE27: 21.8
A28: NBF-26 | B28: NBF | C28: 住友電設ビル | D28: オフィス | E28: 東京都 | F28: 港区 | H28: 都心5区 | M28: 5971 | Q28: =IF(OR($A154="",P154=""),"",ROUND(YEARFRAC(P154,README!$C$5),1)) -> 16.7 | S28: 5365 | T28: 4796.836 | U28: 5360 | V28: 563 | W28: 1 | X28: 1 | Y28: 5.3 | Z28: NBF 2025年12月期(第49期)決算短信(2026/2/16公表) | AA28: 確認済 | AB28: オフィス。竣工年月・階数・面積は短信非掲載(有報等で補完予定)。2026/6/30付で三井不動産へ譲渡予定(譲渡価格10,000百万円=鑑定5,360百万円の約1.9倍、売却益5,112百万円見込)。港区三田・1991年6月竣工・SRC地下1階付12階建・延床9,185.13㎡(後発事象注記より) | AC28: =COUNTIF(環境認証!$A$2:$A$849,A154) -> 2 | AD28: 11.7 | AE28: -0.1
A29: NBF-27 | B29: NBF | C29: ＮＢＦ東銀座スクエア | D29: オフィス | E29: 東京都 | F29: 中央区 | G29: 港区赤坂1-8-1 | H29: 都心5区 | M29: 4871 | Q29: =IF(OR($A155="",P155=""),"",ROUND(YEARFRAC(P155,README!$C$5),1)) -> 23.3 | S29: 5200 | T29: 4232.236 | U29: 7990 | V29: 3758 | W29: 1 | X29: 8 | Y29: 1.9 | Z29: NBF 2025年12月期(第49期)決算短信(2026/2/16公表) | AA29: 確認済 | AB29: オフィス。竣工年月・階数・面積は短信非掲載(有報等で補完予定)。 | AC29: =COUNTIF(環境認証!$A$2:$A$849,A155) -> 1 | AD29: 88.8 | AE29: 53.7
A30: NBF-28 | B30: NBF | C30: 日本橋兜町Ｍ－ＳＱＵＡＲＥ | D30: オフィス | E30: 東京都 | F30: 中央区 | G30: 港区赤坂3-1-2 | H30: 都心5区 | M30: 3298 | Q30: =IF(OR($A156="",P156=""),"",ROUND(YEARFRAC(P156,README!$C$5),1)) -> 14 | S30: 4850 | T30: 4257.858 | U30: 5570 | V30: 1312 | W30: 1 | X30: 2 | Y30: 5.7 | Z30: NBF 2025年12月期(第49期)決算短信(2026/2/16公表) | AA30: 確認済 | AB30: オフィス。竣工年月・階数・面積は短信非掲載(有報等で補完予定)。 | AC30: =COUNTIF(環境認証!$A$2:$A$849,A156) -> 2 | AD30: 30.8 | AE30: 14.8
A31: NBF-29 | B31: NBF | C31: ＮＢＦ八丁堀テラス | D31: オフィス | E31: 東京都 | F31: 中央区 | H31: 都心5区 | M31: 5270 | Q31: =IF(OR($A157="",P157=""),"",ROUND(YEARFRAC(P157,README!$C$5),1)) -> 16.6 | S31: 4528.349 | T31: 4101.664 | U31: 5540 | V31: 1438 | W31: 1 | X31: 1 | Y31: 7 | Z31: NBF 2025年12月期(第49期)決算短信(2026/2/16公表) | AA31: 確認済 | AB31: オフィス。竣工年月・階数・面積は短信非掲載(有報等で補完予定)。旧NBF新川ビルの取得価格を2020/6/30鑑定評価額比率で按分した金額 | AC31: =COUNTIF(環境認証!$A$2:$A$849,A157) -> 1 | AD31: 35.1 | AE31: 22.3
A32: NBF-30 | B32: NBF | C32: 龍角散ビル | D32: オフィス | E32: 東京都 | F32: 千代田区 | H32: 都心5区 | M32: 5332 | Q32: =IF(OR($A158="",P158=""),"",ROUND(YEARFRAC(P158,README!$C$5),1)) -> 16 | S32: 4050 | T32: 4327.607 | U32: 5270 | V32: 942 | W32: 1 | X32: 16 | Y32: 5.4 | Z32: NBF 2025年12月期(第49期)決算短信(2026/2/16公表) | AA32: 確認済 | AB32: オフィス。竣工年月・階数・面積は短信非掲載(有報等で補完予定)。 | AC32: =COUNTIF(環境認証!$A$2:$A$849,A158) -> 2 | AD32: 21.8 | AE32: 30.1
A33: NBF-31 | B33: NBF | C33: 神宮前Ｍ－ＳＱＵＡＲＥ | D33: オフィス | E33: 東京都 | F33: 渋谷区 | H33: 都心5区 | M33: 7213 | Q33: =IF(OR($A159="",P159=""),"",ROUND(YEARFRAC(P159,README!$C$5),1)) -> 16.5 | S33: 3700 | T33: 2596.703 | U33: 4320 | V33: 1723 | W33: 0.88 | X33: 7 | Y33: 5 | Z33: NBF 2025年12月期(第49期)決算短信(2026/2/16公表) | AA33: 確認済 | AB33: オフィス。竣工年月・階数・面積は短信非掲載(有報等で補完予定)。 | AC33: =COUNTIF(環境認証!$A$2:$A$849,A159) -> 1 | AD33: 66.4 | AE33: 16.8
A34: NBF-32 | B34: NBF | C34: 豊洲ベイサイドクロスタワー | D34: オフィス | E34: 東京都 | F34: 江東区 | H34: その他東京23区 | M34: 51512 | Q34: =IF(OR($A160="",P160=""),"",ROUND(YEARFRAC(P160,README!$C$5),1)) -> 24.4 | S34: 80100 | T34: 78755.379 | U34: 80900 | V34: 2145 | W34: 1 | X34: 4 | Y34: 1.7 | Z34: NBF 2025年12月期(第49期)決算短信(2026/2/16公表) | AA34: 確認済 | AB34: オフィス。竣工年月・階数・面積は短信非掲載(有報等で補完予定)。区分所有権(2022〜2024年3回取得・既存保有約47.69%)。2026/3/31付で追加取得予定(約9.19%・14,810百万円→合計約56.88%)。2020年3月竣工・地下2階付36階建・延床178,504.10㎡(建物全体)。店舗区画は固定賃料型ML | AC34: =COUNTIF(環境認証!$A$2:$A$849,A160) -> 1 | AD34: 2.7 | AE34: 1
A35: NBF-33 | B35: NBF | C35: ＮＢＦ大崎ビル | D35: オフィス | E35: 東京都 | F35: 品川区 | H35: その他東京23区 | M35: 74425 | Q35: =IF(OR($A161="",P161=""),"",ROUND(YEARFRAC(P161,README!$C$5),1)) -> 3.6 | S35: 66660 | T35: 59991.582 | U35: 87400 | V35: 27408 | W35: 1 | X35: 3 | Y35: 1.8 | Z35: NBF 2025年12月期(第49期)決算短信(2026/2/16公表) | AA35: 確認済 | AB35: オフィス。竣工年月・階数・面積は短信非掲載(有報等で補完予定)。主要テナント:ソニーグループ(賃貸面積73,477㎡=ポートフォリオ全体の6.0%) | AC35: =COUNTIF(環境認証!$A$2:$A$849,A161) -> 1 | AD35: 45.7 | AE35: 31.1
A36: NBF-34 | B36: NBF | C36: ゲートシティ大崎 | D36: オフィス | E36: 東京都 | F36: 品川区 | H36: その他東京23区 | M36: 41880 | Q36: =IF(OR($A162="",P162=""),"",ROUND(YEARFRAC(P162,README!$C$5),1)) -> 31.4 | S36: 57281.06 | T36: 47525.115 | U36: 72000 | V36: 24475 | W36: 0.996 | X36: 80 | Y36: 4 | Z36: NBF 2025年12月期(第49期)決算短信(2026/2/16公表) | AA36: 確認済 | AB36: オフィス。竣工年月・階数・面積は短信非掲載(有報等で補完予定)。2006・2011・2013年の3回取得合計。サブリース型(変動) | AC36: =COUNTIF(環境認証!$A$2:$A$849,A162) -> 1 | AD36: 51.5 | AE36: 25.7
A37: NBF-35 | B37: NBF | C37: ＮＢＦ豊洲キャナルフロント | D37: オフィス | E37: 東京都 | F37: 江東区 | H37: その他東京23区 | M37: 36639 | Q37: =IF(OR($A163="",P163=""),"",ROUND(YEARFRAC(P163,README!$C$5),1)) -> 17.1 | S37: 35200 | T37: 27034.033 | U37: 38500 | V37: 11466 | W37: 1 | X37: 17 | Y37: 3.2 | Z37: NBF 2025年12月期(第49期)決算短信(2026/2/16公表) | AA37: 確認済 | AB37: オフィス。竣工年月・階数・面積は短信非掲載(有報等で補完予定)。主要テナント:ソフトバンク | AC37: =COUNTIF(環境認証!$A$2:$A$849,A163) -> 0 | AD37: 42.4 | AE37: 9.4
A38: NBF-36 | B38: NBF | C38: 上野イーストタワー | D38: オフィス | E38: 東京都 | F38: 台東区 | H38: その他東京23区 | M38: 28711 | Q38: =IF(OR($A164="",P164=""),"",ROUND(YEARFRAC(P164,README!$C$5),1)) -> 35.8 | S38: 35000 | T38: 32031.252 | U38: 42300 | V38: 10269 | W38: 1 | X38: 2 | Y38: 3.2 | Z38: NBF 2025年12月期(第49期)決算短信(2026/2/16公表) | AA38: 確認済 | AB38: オフィス。竣工年月・階数・面積は短信非掲載(有報等で補完予定)。2016/6・2021/3の取得合計。主要テナント:日立リアルエステートパートナーズ | AC38: =COUNTIF(環境認証!$A$2:$A$849,A164) -> 1 | AD38: 32.1 | AE38: 20.9
A39: NBF-37 | B39: NBF | C39: ＮＢＦ豊洲ガーデンフロント | D39: オフィス | E39: 東京都 | F39: 江東区 | H39: その他東京23区 | M39: 28299 | Q39: =IF(OR($A165="",P165=""),"",ROUND(YEARFRAC(P165,README!$C$5),1)) -> 11.4 | S39: 25018 | T39: 21221.922 | U39: 30100 | V39: 8878 | W39: 1 | X39: 5 | Y39: 4.2 | Z39: NBF 2025年12月期(第49期)決算短信(2026/2/16公表) | AA39: 確認済 | AB39: オフィス。竣工年月・階数・面積は短信非掲載(有報等で補完予定)。主要テナント:博報堂DYホールディングス | AC39: =COUNTIF(環境認証!$A$2:$A$849,A165) -> 0 | AD39: 41.8 | AE39: 20.3
A40: NBF-38 | B40: NBF | C40: 大崎ブライトコア・ブライトプラザ | D40: オフィス | E40: 東京都 | F40: 品川区 | H40: その他東京23区 | M40: 14179 | Q40: =IF(OR($A166="",P166=""),"",ROUND(YEARFRAC(P166,README!$C$5),1)) -> 26.2 | S40: 24380 | T40: 22582.726 | U40: 25600 | V40: 3017 | W40: 0.994 | X40: 22 | Y40: 5.5 | Z40: NBF 2025年12月期(第49期)決算短信(2026/2/16公表) | AA40: 確認済 | AB40: オフィス。竣工年月・階数・面積は短信非掲載(有報等で補完予定)。2016〜2020年の5回分割取得合計。サブリース型(変動) | AC40: =COUNTIF(環境認証!$A$2:$A$849,A166) -> 1 | AD40: 13.4 | AE40: 5
A41: NBF-39 | B41: NBF | C41: 中目黒ＧＴタワー | D41: オフィス | E41: 東京都 | F41: 目黒区 | H41: その他東京23区 | M41: 21438 | Q41: =IF(OR($A167="",P167=""),"",ROUND(YEARFRAC(P167,README!$C$5),1)) -> 25.1 | S41: 23856 | T41: 15801.952 | U41: 21000 | V41: 5198 | W41: 1 | X41: 17 | Y41: 6.8 | Z41: NBF 2025年12月期(第49期)決算短信(2026/2/16公表) | AA41: 確認済 | AB41: オフィス。竣工年月・階数・面積は短信非掲載(有報等で補完予定)。任意組合出資持分(中目黒GTタワー共有床組合)含む。2003〜2005年の3回取得合計。サブリース型(変動) | AC41: =COUNTIF(環境認証!$A$2:$A$849,A167) -> 1 | AD41: 32.9 | AE41: -12
A42: NBF-40 | B42: NBF | C42: 大崎ブライトタワー | D42: オフィス | E42: 東京都 | F42: 品川区 | H42: その他東京23区 | M42: 6079 | Q42: =IF(OR($A168="",P168=""),"",ROUND(YEARFRAC(P168,README!$C$5),1)) -> 3.2 | S42: 13970 | T42: 13384.632 | U42: 14700 | V42: 1315 | W42: 0.998 | X42: 12 | Y42: 2.6 | Z42: NBF 2025年12月期(第49期)決算短信(2026/2/16公表) | AA42: 確認済 | AB42: オフィス。竣工年月・階数・面積は短信非掲載(有報等で補完予定)。サブリース型(変動) | AC42: =COUNTIF(環境認証!$A$2:$A$849,A168) -> 1 | AD42: 9.8 | AE42: 5.2
... A53: NBF-51 | B53: NBF | C53: ＮＢＦ浦和ビル | D53: オフィス | E53: 埼玉県 | F53: さいたま市 | H53: 東京周辺都市部 | M53: 3455 | Q53: =IF(OR($A179="",P179=""),"",ROUND(YEARFRAC(P179,README!$C$5),1)) -> 29.8 | S53: 2000 | T53: 1835.672 | U53: 2230 | V53: 394 | W53: 1 | X53: 15 | Y53: 1.9 | Z53: NBF 2025年12月期(第49期)決算短信(2026/2/16公表) | AA53: 確認済 | AB53: オフィス。竣工年月・階数・面積は短信非掲載(有報等で補完予定)。 | AC53: =COUNTIF(環境認証!$A$2:$A$849,A179) -> 1 | AD53: 21.5 | AE53: 11.5
A54: NBF-52 | B54: NBF | C54: ＮＢＦ松戸ビル | D54: オフィス | E54: 千葉県 | F54: 松戸市 | H54: 東京周辺都市部 | M54: 4770 | Q54: =IF(OR($A180="",P180=""),"",ROUND(YEARFRAC(P180,README!$C$5),1)) -> 30.1 | S54: 2455 | T54: 2029.18 | U54: 2550 | V54: 521 | W54: 1 | X54: 31 | Z54: NBF 2025年12月期(第49期)決算短信(2026/2/16公表) | AA54: 確認済 | AB54: オフィス。竣工年月・階数・面積は短信非掲載(有報等で補完予定)。 | AC54: =COUNTIF(環境認証!$A$2:$A$849,A180) -> 1 | AD54: 25.7 | AE54: 3.9
A55: NBF-53 | B55: NBF | C55: ＮＢＦ ＣＯＮＮＥＣＴ ＳＡＰＰＯＲＯ | D55: オフィス | E55: 北海道 | F55: 札幌市 | H55: 3大都市圏以外の政令市 | I55: 33物件（2025/12/31時点） | M55: 9422 | Q55: =IF(OR($A181="",P181=""),"",ROUND(YEARFRAC(P181,README!$C$5),1)) -> 30.6 | S55: 13800 | T55: 13897.617 | U55: 14600 | V55: 702 | W55: 0.623 | X55: 9 | Y55: 2.3 | Z55: NBF 2025年12月期(第49期)決算短信(2026/2/16公表) | AA55: 確認済 | AB55: オフィス。竣工年月・階数・面積は短信非掲載(有報等で補完予定)。2025/11取得(当期期中取得・約2ヶ月のため収益17百万円は期間僅少)。稼働62.3%はリースアップ途上。2026/4/1付で「CONNECT SAPPORO」から名称変更予定 | AC55: =COUNTIF(環境認証!$A$2:$A$849,A181) -> 1 | AD55: 5.1 | AE55: 5.8
A56: NBF-54 | B56: NBF | C56: 札幌エルプラザ | D56: オフィス | E56: 北海道 | F56: 札幌市 | H56: 3大都市圏以外の政令市 | M56: 11396 | N56: 12 | O56: 3 | P56: 23193 | Q56: =IF(OR($A182="",P182=""),"",ROUND(YEARFRAC(P182,README!$C$5),1)) -> 36.6 | S56: 4404.405 | T56: 2871.483 | U56: 9240 | V56: 6369 | W56: 1 | X56: 13 | Z56: NBF 2025年12月期(第49期)決算短信(2026/2/16公表) | AA56: 確認済 | AB56: オフィス。竣工年月・階数・面積は短信非掲載(有報等で補完予定)。2003〜2005年の4回分割取得合計 | AC56: =COUNTIF(環境認証!$A$2:$A$849,A182) -> 1 | AD56: 221.8 | AE56: 109.8
A57: NBF-55 | B57: NBF | C57: ＮＢＦ札幌南二条ビル | D57: オフィス | E57: 北海道 | F57: 札幌市 | H57: 3大都市圏以外の政令市 | M57: 5351 | N57: 8 | O57: 3 | P57: 26512 | Q57: =IF(OR($A183="",P183=""),"",ROUND(YEARFRAC(P183,README!$C$5),1)) -> 33.4 | S57: 1870.3 | T57: 1682.974 | U57: 1740 | V57: 57 | W57: 1 | X57: 3 | Z57: NBF 2025年12月期(第49期)決算短信(2026/2/16公表) | AA57: 確認済 | AB57: オフィス。竣工年月・階数・面積は短信非掲載(有報等で補完予定)。2026/7/1付で譲渡予定(譲渡価格1,900百万円・売却益217百万円見込)。1990年11月竣工・SRC地下2階付9階建・延床8,149.78㎡(後発事象注記より) | AC57: =COUNTIF(環境認証!$A$2:$A$849,A183) -> 1 | AD57: 3.4 | AE57: -7
A58: NBF-56 | B58: NBF | C58: Ｄタワー富山 | D58: オフィス | E58: 富山県 | F58: 富山市 | H58: その他地方都市 | M58: 10949 | N58: 12 | O58: 1 | P58: 32051 | Q58: =IF(OR($A184="",P184=""),"",ROUND(YEARFRAC(P184,README!$C$5),1)) -> 42.4 | S58: 9000 | T58: 9200.066 | U58: 9240 | V58: 40 | W58: 0.466 | X58: 13 | Z58: NBF 2025年12月期(第49期)決算短信(2026/2/16公表) | AA58: 確認済 | AB58: オフィス。竣工年月・階数・面積は短信非掲載(有報等で補完予定)。2025年(第48期)取得。稼働46.6%はリースアップ途上 | AC58: =COUNTIF(環境認証!$A$2:$A$849,A184) -> 0 | AD58: 0.4 | AE58: 2.7
A59: NBF-57 | B59: NBF | C59: 三井住友銀行名古屋ビル | D59: オフィス | E59: 愛知県 | F59: 名古屋市 | H59: その他3大都市圏 | M59: 17658 | N59: 8 | P59: 31199 | Q59: =IF(OR($A185="",P185=""),"",ROUND(YEARFRAC(P185,README!$C$5),1)) -> 30.9 | S59: 14900 | T59: 14419.538 | U59: 16900 | V59: 2480 | W59: 0.98 | X59: 11 | Z59: NBF 2025年12月期(第49期)決算短信(2026/2/16公表) | AA59: 確認済 | AB59: オフィス。竣工年月・階数・面積は短信非掲載(有報等で補完予定)。 | AC59: =COUNTIF(環境認証!$A$2:$A$849,A185) -> 2 | AD59: 17.2 | AE59: 13.4
A60: NBF-58 | B60: NBF | C60: 名古屋三井ビルディング新館 | D60: オフィス | E60: 愛知県 | F60: 名古屋市 | H60: その他3大都市圏 | M60: 11222 | N60: 10 | O60: 2 | P60: 34151 | Q60: =IF(OR($A186="",P186=""),"",ROUND(YEARFRAC(P186,README!$C$5),1)) -> 41.4 | S60: 13200 | T60: 13077.899 | U60: 15300 | V60: 2222 | W60: 1 | X60: 31 | Z60: NBF 2025年12月期(第49期)決算短信(2026/2/16公表) | AA60: 確認済 | AB60: オフィス。竣工年月・階数・面積は短信非掲載(有報等で補完予定)。サブリース型(変動) | AC60: =COUNTIF(環境認証!$A$2:$A$849,A186) -> 0 | AD60: 17 | AE60: 15.9
A61: NBF-59 | B61: NBF | C61: 名古屋三井ビルディング本館 | D61: オフィス | E61: 愛知県 | F61: 名古屋市 | H61: その他3大都市圏 | M61: 12989 | N61: 4 | O61: 1 | P61: 35765 | Q61: =IF(OR($A187="",P187=""),"",ROUND(YEARFRAC(P187,README!$C$5),1)) -> 33.1 | S61: 13050 | T61: 13949.395 | U61: 14300 | V61: 351 | W61: 0.971 | X61: 66 | Z61: NBF 2025年12月期(第49期)決算短信(2026/2/16公表) | AA61: 確認済 | AB61: オフィス。竣工年月・階数・面積は短信非掲載(有報等で補完予定)。サブリース型(変動) | AC61: =COUNTIF(環境認証!$A$2:$A$849,A187) -> 1 | AD61: 2.5 | AE61: 9.6
A62: NBF-60 | B62: NBF | C62: ＮＢＦ名古屋広小路ビル | D62: オフィス | E62: 愛知県 | F62: 名古屋市 | H62: その他3大都市圏 | M62: 9883 | N62: 7 | O62: 1 | P62: 35370 | Q62: =IF(OR($A188="",P188=""),"",ROUND(YEARFRAC(P188,README!$C$5),1)) -> 16.4 | S62: 7232 | T62: 5919.911 | U62: 6790 | V62: 870 | W62: 0.976 | X62: 24 | Z62: NBF 2025年12月期(第49期)決算短信(2026/2/16公表) | AA62: 確認済 | AB62: オフィス。竣工年月・階数・面積は短信非掲載(有報等で補完予定)。2004/3・2008/3の取得合計 | AC62: =COUNTIF(環境認証!$A$2:$A$849,A188) -> 2 | AD62: 14.7 | AE62: -6.1
A63: NBF-61 | B63: NBF | C63: 中之島三井ビルディング | D63: オフィス | E63: 大阪府 | F63: 大阪市 | H63: その他3大都市圏 | M63: 42389 | N63: 8 | P63: 35247 | Q63: =IF(OR($A189="",P189=""),"",ROUND(YEARFRAC(P189,README!$C$5),1)) -> 16.5 | S63: 44000 | T63: 44157.319 | U63: 46500 | V63: 2343 | W63: 0.985 | X63: 54 | Z63: NBF 2025年12月期(第49期)決算短信(2026/2/16公表) | AA63: 確認済 | AB63: オフィス。竣工年月・階数・面積は短信非掲載(有報等で補完予定)。サブリース型(変動) | AC63: =COUNTIF(環境認証!$A$2:$A$849,A189) -> 1 | AD63: 5.3 | AE63: 5.7
A64: NBF-62 | B64: NBF | C64: アクア堂島ＮＢＦタワー | D64: オフィス | E64: 大阪府 | F64: 大阪市 | H64: その他3大都市圏 | M64: 21917 | N64: 10 | P64: 35065 | Q64: =IF(OR($A190="",P190=""),"",ROUND(YEARFRAC(P190,README!$C$5),1)) -> 23.9 | S64: 17810 | T64: 14200.467 | U64: 22400 | V64: 8200 | W64: 0.95 | X64: 44 | Z64: NBF 2025年12月期(第49期)決算短信(2026/2/16公表) | AA64: 確認済 | AB64: オフィス。竣工年月・階数・面積は短信非掲載(有報等で補完予定)。 | AC64: =COUNTIF(環境認証!$A$2:$A$849,A190) -> 1 | AD64: 57.7 | AE64: 25.8
A65: NBF-63 | B65: NBF | C65: 中之島セントラルタワー | D65: オフィス | E65: 大阪府 | F65: 大阪市 | H65: その他3大都市圏 | M65: 17279 | N65: 7 | O65: 1 | P65: 32874 | Q65: =IF(OR($A191="",P191=""),"",ROUND(YEARFRAC(P191,README!$C$5),1)) -> 16.3 | S65: 14900 | T65: 13171.252 | U65: 20200 | V65: 7029 | W65: 1 | X65: 30 | Z65: NBF 2025年12月期(第49期)決算短信(2026/2/16公表) | AA65: 確認済 | AB65: オフィス。竣工年月・階数・面積は短信非掲載(有報等で補完予定)。 | AC65: =COUNTIF(環境認証!$A$2:$A$849,A191) -> 1 | AD65: 53.4 | AE65: 35.6
A66: NBF-64 | B66: NBF | C66: 信濃橋三井ビルディング | D66: オフィス | E66: 大阪府 | F66: 大阪市 | H66: その他3大都市圏 | M66: 24413 | N66: 7 | O66: 2 | P66: 34060 | Q66: =IF(OR($A192="",P192=""),"",ROUND(YEARFRAC(P192,README!$C$5),1)) -> 14.6 | S66: 14400 | T66: 10124.32 | U66: 14000 | V66: 3876 | W66: 0.985 | X66: 61 | Z66: NBF 2025年12月期(第49期)決算短信(2026/2/16公表) | AA66: 確認済 | AB66: オフィス。竣工年月・階数・面積は短信非掲載(有報等で補完予定)。サブリース型(変動) | AC66: =COUNTIF(環境認証!$A$2:$A$849,A192) -> 1 | AD66: 38.3 | AE66: -2.8
A67: NBF-65 | B67: NBF | C67: 堺筋本町センタービル | D67: オフィス | E67: 大阪府 | F67: 大阪市 | H67: その他3大都市圏 | M67: 23163 | N67: 9 | O67: 2 | P67: 30773 | Q67: =IF(OR($A193="",P193=""),"",ROUND(YEARFRAC(P193,README!$C$5),1)) -> 35.9 | S67: 12700 | T67: 12979.57 | U67: 16200 | V67: 3220 | W67: 0.991 | X67: 56 | Z67: NBF 2025年12月期(第49期)決算短信(2026/2/16公表) | AA67: 確認済 | AB67: オフィス。竣工年月・階数・面積は短信非掲載(有報等で補完予定)。2005/3・2014/1の取得合計 | AC67: =COUNTIF(環境認証!$A$2:$A$849,A193) -> 0 | AD67: 24.8 | AE67: 27.6
A68: NBF-66 | B68: NBF | C68: 淀屋橋フレックスタワー | D68: オフィス | E68: 大阪府 | F68: 大阪市 | H68: その他3大都市圏 | M68: 7432 | N68: 34 | O68: 3 | P68: 34943 | Q68: =IF(OR($A194="",P194=""),"",ROUND(YEARFRAC(P194,README!$C$5),1)) -> 37.7 | S68: 9833 | T68: 8203.695 | U68: 10600 | V68: 2396 | W68: 1 | X68: 13 | Z68: NBF 2025年12月期(第49期)決算短信(2026/2/16公表) | AA68: 確認済 | AB68: オフィス。竣工年月・階数・面積は短信非掲載(有報等で補完予定)。 | AC68: =COUNTIF(環境認証!$A$2:$A$849,A194) -> 0 | AD68: 29.2 | AE68: 7.8
A69: NBF-67 | B69: NBF | C69: 広島袋町ビルディング | D69: オフィス | E69: 広島県 | F69: 広島市 | H69: 3大都市圏以外の政令市 | M69: 3930 | N69: 8 | P69: 31107 | Q69: =IF(OR($A195="",P195=""),"",ROUND(YEARFRAC(P195,README!$C$5),1)) -> 16.9 | S69: 2215 | T69: 1739.519 | U69: 2390 | V69: 650 | W69: 1 | X69: 19 | Z69: NBF 2025年12月期(第49期)決算短信(2026/2/16公表) | AA69: 確認済 | AB69: オフィス。竣工年月・階数・面積は短信非掲載(有報等で補完予定)。2003/11・2012/4の取得合計 | AC69: =COUNTIF(環境認証!$A$2:$A$849,A195) -> 1 | AD69: 37.4 | AE69: 7.9
A70: NBF-68 | B70: NBF | C70: ＮＢＦ松山日銀前ビル | D70: オフィス | E70: 愛媛県 | F70: 松山市 | H70: その他地方都市 | M70: 5984 | N70: 10 | O70: 1 | P70: 34151 | Q70: =IF(OR($A196="",P196=""),"",ROUND(YEARFRAC(P196,README!$C$5),1)) -> 28.7 | S70: 3310 | T70: 2717.828 | U70: 4040 | V70: 1322 | W70: 0.947 | X70: 22 | Z70: NBF 2025年12月期(第49期)決算短信(2026/2/16公表) | AA70: 確認済 | AB70: オフィス。竣工年月・階数・面積は短信非掲載(有報等で補完予定)。 | AC70: =COUNTIF(環境認証!$A$2:$A$849,A196) -> 0 | AD70: 48.6 | AE70: 22.1
A71: NBF-69 | B71: NBF | C71: 博多祇園Ｍ－ＳＱＵＡＲＥ | D71: オフィス | E71: 福岡県 | F71: 福岡市 | H71: 3大都市圏以外の政令市 | M71: 14328 | N71: 8 | O71: 1 | P71: 40269 | Q71: =IF(OR($A197="",P197=""),"",ROUND(YEARFRAC(P197,README!$C$5),1)) -> 16 | S71: 8000 | T71: 6033.403 | U71: 13800 | V71: 7767 | W71: 0.97 | X71: 20 | Z71: NBF 2025年12月期(第49期)決算短信(2026/2/16公表) | AA71: 確認済 | AB71: オフィス。竣工年月・階数・面積は短信非掲載(有報等で補完予定)。 | AC71: =COUNTIF(環境認証!$A$2:$A$849,A197) -> 1 | AD71: 128.7 | AE71: 72.5
A72: NBF-70 | B72: NBF | C72: ＮＢＦ熊本ビル | D72: オフィス | E72: 熊本県 | F72: 熊本市 | H72: 3大都市圏以外の政令市 | M72: 7931 | N72: 9 | P72: 40210 | Q72: =IF(OR($A198="",P198=""),"",ROUND(YEARFRAC(P198,README!$C$5),1)) -> 24.8 | S72: 4500 | T72: 3164.171 | U72: 4880 | V72: 1716 | W72: 1 | X72: 13 | Z72: NBF 2025年12月期(第49期)決算短信(2026/2/16公表) | AA72: 確認済 | AB72: オフィス。竣工年月・階数・面積は短信非掲載(有報等で補完予定)。 | AC72: =COUNTIF(環境認証!$A$2:$A$849,A198) -> 0 | AD72: 54.2 | AE72: 8.4
A73: JRE-ALL | B73: JRE | C73: （JRE全79物件一括） | D73: オフィス | E73: 東京都 | F73: 渋谷区 | H73: （法人一括） | M73: 13960.84 | N73: 15 | O73: 1 | P73: 37530 | Q73: =IF(OR($A1253="",P1253=""),"",ROUND(YEARFRAC(P1253,README!$C$5),1)) | S73: 1197029 | T73: 1082573 | U73: 1447290 | V73: =IF($A1253="","",IF(OR(T1253="",U1253=""),"",U1253-T1253)) -> -55 | W73: 0.989 | X73: 1674 | Z73: JRE 2026年3月期(第49期)決算短信(2026/5/15公表) | AA73: 確認済※ | AB73: JRE全79物件の一括行。取得価格合計1,197,029,274千円(千円単位開示)は物件別合算と完全一致。鑑定1,447,290百万円・テナント総数1,674も完全一致、簿価合算1,082,536は合計1,082,573比-37=百万円切捨て累積、NLA合算891,709㎡は合計891,744㎡比-35=㎡未満切捨て累積。入居率98.9%(前期比+1.5pt)。2001年9月上場の日本初のJ-REIT2銘柄の一つ(オフィス特化・スポンサー三菱地所)。期中: The Link Sapporo取得(21,340)・サッポロアーチビル取得(8,175)・神田橋追加取得(2,150)・新宿ES追加取得(20,353)、赤坂パークビル16.66%譲渡(13,444百万円)・天神クリスタル50%譲渡(3,315百万円)。期後: 2026/4/1赤坂3回目16.66%譲渡+天神残50%譲渡、4/2コモレ四谷7.1%追加取得(15,540)、5/20大同生命新潟ビル譲渡予定→2026年9月期は77物件前提。2026/4/1公募増資(161,200口・約18,110百万円)+4/24第三者割当(8,060口)→7,283,580口。渋谷クロスタワーは底地のみ(物件数・取得価格に含み、NLA・テナント数に含まず)。格付: JCR AA+/R&I AA/S&P A+(いずれも安定的)。LTV44.8%。主要テナント: 三菱地所4,556,587千円 | AC73: =COUNTIF(環境認証!$A$2:$A$849,A1253) -> 0 | AD73: 75.4 | AE73: 67.9
A74: JRE-001 | B74: JRE | C74: 北の丸スクエア | D74: オフィス | E74: 東京都 | F74: 千代田区 | H74: 都心5区 | M74: 25678 | N74: 8 | P74: 40299 | Q74: =IF(OR($A1174="",P1174=""),"",ROUND(YEARFRAC(P1174,README!$C$5),1)) | S74: 81555.5 | T74: 68057 | U74: 84400 | V74: 16343 | W74: 1 | X74: 8 | Z74: JRE 2026年3月期(第49期)決算短信(2026/5/15公表) | AA74: 確認済 | AB74: 住宅部分(NLA11,694㎡・入居98.6%)は本表数値に含まず | AC74: =COUNTIF(環境認証!$A$2:$A$849,A1174) -> 2 | AD74: 24 | AE74: 3.5
A75: JRE-002 | B75: JRE | C75: ＪＲＥ神田小川町ビル | D75: オフィス | E75: 東京都 | F75: 千代田区 | H75: 都心5区 | M75: 6269 | N75: 11 | O75: 2 | P75: 40909 | Q75: =IF(OR($A1175="",P1175=""),"",ROUND(YEARFRAC(P1175,README!$C$5),1)) | S75: 9520 | T75: 8513 | U75: 9600 | V75: 1087 | W75: 1 | X75: 9 | Z75: JRE 2026年3月期(第49期)決算短信(2026/5/15公表) | AA75: 確認済 | AB75: 構造S・RC、鑑定直接還元利回り3.0%。延床面積は短信非掲載(賃貸可能面積を収録)、住所詳細は有報で補完予定 | AC75: =COUNTIF(環境認証!$A$2:$A$849,A1175) -> 1 | AD75: 12.8 | AE75: 0.8
A76: JRE-003 | B76: JRE | C76: 神田橋パークビルヂング | D76: オフィス | E76: 東京都 | F76: 千代田区 | H76: 都心5区 | M76: 5551 | N76: 7 | O76: 2 | P76: 33117 | Q76: =IF(OR($A1176="",P1176=""),"",ROUND(YEARFRAC(P1176,README!$C$5),1)) | S76: 6960 | T76: 6510 | U76: 8210 | V76: 1700 | W76: 1 | X76: 10 | Z76: JRE 2026年3月期(第49期)決算短信(2026/5/15公表) | AA76: 確認済 | AB76: 2026/1/21に持分28.68%追加取得(2,150百万円)→持分85.44% | AC76: =COUNTIF(環境認証!$A$2:$A$849,A1176) -> 0 | AD76: 26.1 | AE76: 18
A77: JRE-004 | B77: JRE | C77: 大手町フィナンシャルシティノースタワー | D77: オフィス | E77: 東京都 | F77: 千代田区 | H77: 都心5区 | M77: 7659 | N77: 12 | O77: 1 | P77: 32478 | Q77: =IF(OR($A1177="",P1177=""),"",ROUND(YEARFRAC(P1177,README!$C$5),1)) | S77: 21842.9 | T77: 20091 | U77: 29300 | V77: 9209 | W77: 0.999 | X77: 16 | Z77: JRE 2026年3月期(第49期)決算短信(2026/5/15公表) | AA77: 確認済 | AB77: 構造S、鑑定直接還元利回り3.1%。2024年5月以降、再開発組合から家賃損失補償を受領(賃貸面積・稼働率は補償部分込み)。延床面積は短信非掲載(賃貸可能面積を収録)、住所詳細は有報で補完予定 | AC77: =COUNTIF(環境認証!$A$2:$A$849,A1177) -> 0 | AD77: 45.8 | AE77: 34.1
A78: JRE-005 | B78: JRE | C78: 大手町パークビルディング | D78: オフィス | E78: 東京都 | F78: 千代田区 | H78: 都心5区 | M78: 2372 | N78: 6 | O78: 1 | P78: 40057 | Q78: =IF(OR($A1178="",P1178=""),"",ROUND(YEARFRAC(P1178,README!$C$5),1)) | S78: 10175 | T78: 9854 | U78: 11500 | V78: 1646 | W78: 1 | X78: 21 | Z78: JRE 2026年3月期(第49期)決算短信(2026/5/15公表) | AA78: 確認済 | AB78: 構造S・RC、鑑定直接還元利回り3.3%。延床面積は短信非掲載(賃貸可能面積を収録)、住所詳細は有報で補完予定 | AC78: =COUNTIF(環境認証!$A$2:$A$849,A1178) -> 1 | AD78: 16.7 | AE78: 13
A79: JRE-006 | B79: JRE | C79: 二番町ガーデン | D79: オフィス | E79: 東京都 | F79: 千代田区 | H79: 都心5区 | M79: 9316 | N79: 9 | O79: 1 | P79: 35765 | Q79: =IF(OR($A1179="",P1179=""),"",ROUND(YEARFRAC(P1179,README!$C$5),1)) | S79: 14700 | T79: 11935 | U79: 18000 | V79: 6065 | W79: 1 | X79: 1 | Z79: JRE 2026年3月期(第49期)決算短信(2026/5/15公表) | AA79: 確認済 | AB79: 住宅部分(NLA1,686㎡・入居100.0%)は本表数値に含まず | AC79: =COUNTIF(環境認証!$A$2:$A$849,A1179) -> 0 | AD79: 50.8 | AE79: 22.4
A80: JRE-007 | B80: JRE | C80: 三菱ＵＦＪ信託銀行本店ビル | D80: オフィス | E80: 東京都 | F80: 千代田区 | H80: 都心5区 | M80: 11904 | N80: 10 | P80: 40391 | Q80: =IF(OR($A1180="",P1180=""),"",ROUND(YEARFRAC(P1180,README!$C$5),1)) | S80: 44700 | T80: 28382 | U80: 57700 | V80: 29318 | W80: 1 | X80: 11 | Z80: JRE 2026年3月期(第49期)決算短信(2026/5/15公表) | AA80: 確認済 | AB80: 構造S、鑑定直接還元利回り3.1%。延床面積は短信非掲載(賃貸可能面積を収録)、住所詳細は有報で補完予定 | AC80: =COUNTIF(環境認証!$A$2:$A$849,A1180) -> 1 | AD80: 103.3 | AE80: 29.1
A81: JRE-008 | B81: JRE | C81: ビュレックス麹町 | D81: オフィス | E81: 東京都 | F81: 千代田区 | H81: 都心5区 | M81: 4495 | N81: 7 | O81: 1 | P81: 37196 | Q81: =IF(OR($A1181="",P1181=""),"",ROUND(YEARFRAC(P1181,README!$C$5),1)) | S81: 7000 | T81: 5094 | U81: 7610 | V81: 2516 | W81: 1 | X81: 1 | Z81: JRE 2026年3月期(第49期)決算短信(2026/5/15公表) | AA81: 確認済 | AB81: 構造S・RC、鑑定直接還元利回り3.0%。延床面積は短信非掲載(賃貸可能面積を収録)、住所詳細は有報で補完予定 | AC81: =COUNTIF(環境認証!$A$2:$A$849,A1181) -> 1 | AD81: 49.4 | AE81: 8.7
A82: JRE-009 | B82: JRE | C82: CIRCLES平河町 | D82: オフィス | E82: 東京都 | F82: 千代田区 | H82: 都心5区 | M82: 979 | N82: 9 | O82: 1 | P82: 37135 | Q82: =IF(OR($A1182="",P1182=""),"",ROUND(YEARFRAC(P1182,README!$C$5),1)) | S82: 1780 | T82: 1739 | U82: 1900 | V82: 161 | W82: 1 | X82: 11 | Z82: JRE 2026年3月期(第49期)決算短信(2026/5/15公表) | AA82: 確認済 | AB82: 構造RC、鑑定直接還元利回り3.1%。延床面積は短信非掲載(賃貸可能面積を収録)、住所詳細は有報で補完予定 | AC82: =COUNTIF(環境認証!$A$2:$A$849,A1182) -> 0 | AD82: 9.3 | AE82: 6.7
A83: JRE-010 | B83: JRE | C83: 山王グランドビル | D83: オフィス | E83: 東京都 | F83: 千代田区 | H83: 都心5区 | M83: 19896 | N83: 11 | O83: 1 | P83: 38018 | Q83: =IF(OR($A1183="",P1183=""),"",ROUND(YEARFRAC(P1183,README!$C$5),1)) | S83: 20900 | T83: 21623 | U83: 23100 | V83: 1477 | W83: 0.952 | X83: 54 | Z83: JRE 2026年3月期(第49期)決算短信(2026/5/15公表) | AA83: 確認済 | AB83: 賃貸事業損益は掲載値114百万円(F-I=115との差は百万円切捨て由来) | AC83: =COUNTIF(環境認証!$A$2:$A$849,A1183) -> 0 | AD83: 6.8 | AE83: 10.5
A84: JRE-011 | B84: JRE | C84: 有楽町電気ビルヂング | D84: オフィス | E84: 東京都 | F84: 千代田区 | H84: 都心5区 | M84: 4697 | N84: 20 | O84: 2 | P84: 34366 | Q84: =IF(OR($A1184="",P1184=""),"",ROUND(YEARFRAC(P1184,README!$C$5),1)) | S84: 7200 | T84: 7720 | U84: 9940 | V84: 2220 | W84: 1 | X84: 13 | Z84: JRE 2026年3月期(第49期)決算短信(2026/5/15公表) | AA84: 確認済 | AB84: 構造S・SRC・RC、鑑定直接還元利回り3.4%。延床面積は短信非掲載(賃貸可能面積を収録)、住所詳細は有報で補完予定 | AC84: =COUNTIF(環境認証!$A$2:$A$849,A1184) -> 1 | AD84: 28.8 | AE84: 38.1
A85: JRE-012 | B85: JRE | C85: フロントプレイス日本橋 | D85: オフィス | E85: 東京都 | F85: 中央区 | H85: 都心5区 | M85: 8468 | N85: 10 | O85: 1 | P85: 38749 | Q85: =IF(OR($A1185="",P1185=""),"",ROUND(YEARFRAC(P1185,README!$C$5),1)) | S85: 17560 | T85: 16946 | U85: 22200 | V85: 5254 | W85: 1 | X85: 2 | Z85: JRE 2026年3月期(第49期)決算短信(2026/5/15公表) | AA85: 確認済 | AB85: 構造S・SRC、鑑定直接還元利回り3.3%。延床面積は短信非掲載(賃貸可能面積を収録)、住所詳細は有報で補完予定 | AC85: =COUNTIF(環境認証!$A$2:$A$849,A1185) -> 1 | AD85: 31 | AE85: 26.4
A86: JRE-013 | B86: JRE | C86: ＪＲＥ茅場町二丁目ビル | D86: オフィス | E86: 東京都 | F86: 中央区 | H86: 都心5区 | M86: 4419 | N86: 9 | O86: 1 | P86: 35096 | Q86: =IF(OR($A1186="",P1186=""),"",ROUND(YEARFRAC(P1186,README!$C$5),1)) | S86: 4410 | T86: 4008 | U86: 5160 | V86: 1152 | W86: 0.931 | X86: 9 | Z86: JRE 2026年3月期(第49期)決算短信(2026/5/15公表) | AA86: 確認済 | AB86: 構造SRC、鑑定直接還元利回り3.4%。延床面積は短信非掲載(賃貸可能面積を収録)、住所詳細は有報で補完予定 | AC86: =COUNTIF(環境認証!$A$2:$A$849,A1186) -> 0 | AD86: 28.7 | AE86: 17
A87: JRE-014 | B87: JRE | C87: ビュレックス京橋 | D87: オフィス | E87: 東京都 | F87: 中央区 | H87: 都心5区 | M87: 4279 | N87: 11 | O87: 2 | P87: 33451 | Q87: =IF(OR($A1187="",P1187=""),"",ROUND(YEARFRAC(P1187,README!$C$5),1)) | S87: 5250 | T87: 4261 | U87: 8920 | V87: 4659 | W87: 1 | X87: 1 | Z87: JRE 2026年3月期(第49期)決算短信(2026/5/15公表) | AA87: 確認済 | AB87: 構造SRC・RC・S、鑑定直接還元利回り3.1%。延床面積は短信非掲載(賃貸可能面積を収録)、住所詳細は有報で補完予定 | AC87: =COUNTIF(環境認証!$A$2:$A$849,A1187) -> 0 | AD87: 109.3 | AE87: 69.9
A88: JRE-015 | B88: JRE | C88: ＪＲＥ銀座一丁目イーストビル | D88: オフィス | E88: 東京都 | F88: 中央区 | H88: 都心5区 | M88: 4513 | N88: 7 | P88: 36192 | Q88: =IF(OR($A1188="",P1188=""),"",ROUND(YEARFRAC(P1188,README!$C$5),1)) | S88: 6459 | T88: 5738 | U88: 8910 | V88: 3172 | W88: 1 | X88: 8 | Z88: JRE 2026年3月期(第49期)決算短信(2026/5/15公表) | AA88: 確認済 | AB88: 構造S・SRC、鑑定直接還元利回り3.6%。延床面積は短信非掲載(賃貸可能面積を収録)、住所詳細は有報で補完予定 | AC88: =COUNTIF(環境認証!$A$2:$A$849,A1188) -> 1 | AD88: 55.3 | AE88: 37.9
A89: JRE-016 | B89: JRE | C89: 銀座三和ビル | D89: オフィス | E89: 東京都 | F89: 中央区 | H89: 都心5区 | M89: 4266 | N89: 7 | P89: 39508 | Q89: =IF(OR($A1189="",P1189=""),"",ROUND(YEARFRAC(P1189,README!$C$5),1)) | S89: 16830 | T89: 17298 | U89: 27300 | V89: 10002 | W89: 1 | X89: 10 | Z89: JRE 2026年3月期(第49期)決算短信(2026/5/15公表) | AA89: 確認済 | AB89: 構造S、鑑定直接還元利回り3.6%。延床面積は短信非掲載(賃貸可能面積を収録)、住所詳細は有報で補完予定 | AC89: =COUNTIF(環境認証!$A$2:$A$849,A1189) -> 1 | AD89: 57.8 | AE89: 62.2
A90: JRE-017 | B90: JRE | C90: ＪＲＥ銀座三丁目ビル | D90: オフィス | E90: 東京都 | F90: 中央区 | H90: 都心5区 | M90: 4255 | N90: 6 | P90: 36951 | Q90: =IF(OR($A1190="",P1190=""),"",ROUND(YEARFRAC(P1190,README!$C$5),1)) | S90: 7999.4 | T90: 6953 | U90: 6640 | V90: -313 | W90: 1 | X90: 9 | Z90: JRE 2026年3月期(第49期)決算短信(2026/5/15公表) | AA90: 確認済 | AB90: 取得価格は隣接地取得・解体・増築工事費を含む合計 | AC90: =COUNTIF(環境認証!$A$2:$A$849,A1190) -> 0 | AD90: -4.5 | AE90: -17
A91: JRE-018 | B91: JRE | C91: 赤坂パークビル | D91: オフィス | E91: 東京都 | F91: 港区 | H91: 都心5区 | M91: 29957 | N91: 4 | P91: 32568 | Q91: =IF(OR($A1191="",P1191=""),"",ROUND(YEARFRAC(P1191,README!$C$5),1)) | S91: 40517.1 | T91: 37425 | U91: 53400 | V91: 15975 | W91: 1 | X91: 38 | Z91: JRE 2026年3月期(第49期)決算短信(2026/5/15公表) | AA91: 確認済 | AB91: 分割譲渡中: 2025/4/1に準共有持分16.70%、2025/10/1に16.66%譲渡(当期売却益3,946,189千円)、2026/4/1に3回目16.66%譲渡。住宅部分(NLA7,183㎡・入居88.6%)は本表数値に含まず | AC91: =COUNTIF(環境認証!$A$2:$A$849,A1191) -> 1 | AD91: 42.7 | AE91: 31.8
A92: JRE-019 | B92: JRE | C92: the ARGYLE aoyama | D92: オフィス | E92: 東京都 | F92: 港区 | H92: 都心5区 | M92: 7478 | N92: 7 | O92: 1 | P92: 33239 | Q92: =IF(OR($A1192="",P1192=""),"",ROUND(YEARFRAC(P1192,README!$C$5),1)) | S92: 23900 | T92: 23612 | U92: 26200 | V92: 2588 | W92: 1 | X92: 11 | Z92: JRE 2026年3月期(第49期)決算短信(2026/5/15公表) | AA92: 確認済 | AB92: 構造SRC・S、鑑定直接還元利回り3.7%。延床面積は短信非掲載(賃貸可能面積を収録)、住所詳細は有報で補完予定 | AC92: =COUNTIF(環境認証!$A$2:$A$849,A1192) -> 1 | AD92: 11 | AE92: 9.6
A93: JRE-020 | B93: JRE | C93: 3rd MINAMI AOYAMA | D93: オフィス | E93: 東京都 | F93: 港区 | H93: 都心5区 | M93: 7781 | N93: 9 | P93: 38384 | Q93: =IF(OR($A1193="",P1193=""),"",ROUND(YEARFRAC(P1193,README!$C$5),1)) | S93: 21000 | T93: 21172 | U93: 22200 | V93: 1028 | W93: 1 | X93: 14 | Z93: JRE 2026年3月期(第49期)決算短信(2026/5/15公表) | AA93: 確認済 | AB93: 構造S、鑑定直接還元利回り3.2%。延床面積は短信非掲載(賃貸可能面積を収録)、住所詳細は有報で補完予定 | AC93: =COUNTIF(環境認証!$A$2:$A$849,A1193) -> 1 | AD93: 4.9 | AE93: 5.7
A94: JRE-021 | B94: JRE | C94: ＪＲＥ青山クリスタルビル | D94: オフィス | E94: 東京都 | F94: 港区 | H94: 都心5区 | M94: 4898 | N94: 10 | O94: 1 | P94: 33086 | Q94: =IF(OR($A1194="",P1194=""),"",ROUND(YEARFRAC(P1194,README!$C$5),1)) | S94: 7680 | T94: 6862 | U94: 10900 | V94: 4038 | W94: 1 | X94: 9 | Z94: JRE 2026年3月期(第49期)決算短信(2026/5/15公表) | AA94: 確認済 | AB94: 構造S・RC、鑑定直接還元利回り3.5%。延床面積は短信非掲載(賃貸可能面積を収録)、住所詳細は有報で補完予定 | AC94: =COUNTIF(環境認証!$A$2:$A$849,A1194) -> 1 | AD94: 58.8 | AE94: 41.9
A95: JRE-022 | B95: JRE | C95: クローバー芝公園 | D95: オフィス | E95: 東京都 | F95: 港区 | H95: 都心5区 | M95: 2550 | N95: 18 | O95: 2 | P95: 34001 | Q95: =IF(OR($A1195="",P1195=""),"",ROUND(YEARFRAC(P1195,README!$C$5),1)) | S95: 4500 | T95: 4331 | U95: 4950 | V95: 619 | W95: 1 | X95: 9 | Z95: JRE 2026年3月期(第49期)決算短信(2026/5/15公表) | AA95: 確認済 | AB95: 構造SRC・RC・S、鑑定直接還元利回り3.7%。延床面積は短信非掲載(賃貸可能面積を収録)、住所詳細は有報で補完予定 | AC95: =COUNTIF(環境認証!$A$2:$A$849,A1195) -> 1 | AD95: 14.3 | AE95: 10
A96: JRE-023 | B96: JRE | C96: 汐留ビルディング | D96: オフィス | E96: 東京都 | F96: 港区 | H96: 都心5区 | M96: 44213 | N96: 8 | O96: 1 | P96: 33573 | Q96: =IF(OR($A1196="",P1196=""),"",ROUND(YEARFRAC(P1196,README!$C$5),1)) | S96: 106930 | T96: 97914 | U96: 122000 | V96: 24086 | W96: 0.998 | X96: 50 | Z96: JRE 2026年3月期(第49期)決算短信(2026/5/15公表) | AA96: 確認済 | AB96: 構造SRC・S、鑑定直接還元利回り3.8%。延床面積は短信非掲載(賃貸可能面積を収録)、住所詳細は有報で補完予定 | AC96: =COUNTIF(環境認証!$A$2:$A$849,A1196) -> 0 | AD96: 24.6 | AE96: 14.1
A97: JRE-024 | B97: JRE | C97: ＪＲＥ芝二丁目大門ビル | D97: オフィス | E97: 東京都 | F97: 港区 | H97: 都心5区 | M97: 9503 | N97: 12 | O97: 1 | P97: 39448 | Q97: =IF(OR($A1197="",P1197=""),"",ROUND(YEARFRAC(P1197,README!$C$5),1)) | S97: 4859 | T97: 5618 | U97: 9600 | V97: 3982 | W97: 1 | X97: 28 | Z97: JRE 2026年3月期(第49期)決算短信(2026/5/15公表) | AA97: 確認済 | AB97: 構造S、鑑定直接還元利回り3.5%。延床面積は短信非掲載(賃貸可能面積を収録)、住所詳細は有報で補完予定 | AC97: =COUNTIF(環境認証!$A$2:$A$849,A1197) -> 0 | AD97: 70.9 | AE97: 97.6
A98: JRE-025 | B98: JRE | C98: ＪＲＥコスモ金杉橋ビル | D98: オフィス | E98: 東京都 | F98: 港区 | H98: 都心5区 | M98: 4062 | N98: 8 | P98: 42795 | Q98: =IF(OR($A1198="",P1198=""),"",ROUND(YEARFRAC(P1198,README!$C$5),1)) | S98: 2808 | T98: 2381 | U98: 3880 | V98: 1499 | W98: 1 | X98: 9 | Z98: JRE 2026年3月期(第49期)決算短信(2026/5/15公表) | AA98: 確認済 | AB98: 構造S、鑑定直接還元利回り3.5%。延床面積は短信非掲載(賃貸可能面積を収録)、住所詳細は有報で補完予定 | AC98: =COUNTIF(環境認証!$A$2:$A$849,A1198) -> 1 | AD98: 63 | AE98: 38.2
A99: JRE-026 | B99: JRE | C99: シーバンスＳ棟 | D99: オフィス | E99: 東京都 | F99: 港区 | H99: 都心5区 | M99: 7979 | N99: 8 | P99: 40179 | Q99: =IF(OR($A1199="",P1199=""),"",ROUND(YEARFRAC(P1199,README!$C$5),1)) | S99: 7690 | T99: 7902 | U99: 9500 | V99: 1598 | W99: 1 | X99: 16 | Z99: JRE 2026年3月期(第49期)決算短信(2026/5/15公表) | AA99: 確認済 | AB99: 構造S、鑑定直接還元利回り3.3%。区分所有。ML事業収入の持分は301,220分の183,715(面積は同持分按分、テナント数・稼働率は事業対象部分全体)。延床面積は短信非掲載(賃貸可能面積を収録)、住所詳細は有報で補完予定 | AC99: =COUNTIF(環境認証!$A$2:$A$849,A1199) -> 0 | AD99: 20.2 | AE99: 23.5
A100: JRE-027 | B100: JRE | C100: 田町フロントビル | D100: オフィス | E100: 東京都 | F100: 港区 | H100: 都心5区 | M100: 3792 | N100: 10 | P100: 44866 | Q100: =IF(OR($A1200="",P1200=""),"",ROUND(YEARFRAC(P1200,README!$C$5),1)) | S100: 6210 | T100: 5774 | U100: 8070 | V100: 2296 | W100: 1 | X100: 10 | Z100: JRE 2026年3月期(第49期)決算短信(2026/5/15公表) | AA100: 確認済 | AB100: 構造S、鑑定直接還元利回り3.4%。取得価格は土地取得価格＋建物建築コスト。延床面積は短信非掲載(賃貸可能面積を収録)、住所詳細は有報で補完予定 | AC100: =COUNTIF(環境認証!$A$2:$A$849,A1200) -> 0 | AD100: 39.8 | AE100: 30
A101: JRE-028 | B101: JRE | C101: 新宿イーストサイドスクエア | D101: オフィス | E101: 東京都 | F101: 新宿区 | H101: 都心5区 | M101: 56145 | N101: 10 | O101: 1 | P101: 40026 | Q101: =IF(OR($A1201="",P1201=""),"",ROUND(YEARFRAC(P1201,README!$C$5),1)) | S101: 92533 | T101: 86308 | U101: 109000 | V101: 22692 | W101: 0.998 | X101: 45 | Z101: JRE 2026年3月期(第49期)決算短信(2026/5/15公表) | AA101: 確認済 | AB101: 2026/3/13に共有持分9%追加取得(20,353百万円)→持分48.0% | AC101: =COUNTIF(環境認証!$A$2:$A$849,A1201) -> 0 | AD101: 26.3 | AE101: 17.8
A102: JRE-029 | B102: JRE | C102: 新宿フロントタワー | D102: オフィス | E102: 東京都 | F102: 新宿区 | H102: 都心5区 | M102: 21416 | N102: 12 | O102: 1 | P102: 45444 | Q102: =IF(OR($A1202="",P1202=""),"",ROUND(YEARFRAC(P1202,README!$C$5),1)) | S102: 35125 | T102: 33131 | U102: 37800 | V102: 4669 | W102: 1 | X102: 44 | Z102: JRE 2026年3月期(第49期)決算短信(2026/5/15公表) | AA102: 確認済 | AB102: 構造RC・SRC・S、鑑定直接還元利回り3.3%。取得価格は土地取得価格＋建物建築コスト。延床面積は短信非掲載(賃貸可能面積を収録)、住所詳細は有報で補完予定 | AC102: =COUNTIF(環境認証!$A$2:$A$849,A1202) -> 0 | AD102: 14.1 | AE102: 7.6
A103: JRE-030 | B103: JRE | C103: コモレ四谷 | D103: オフィス | E103: 東京都 | F103: 新宿区 | H103: 都心5区 | M103: 10997 | N103: 11 | O103: 1 | P103: 45017 | Q103: =IF(OR($A1203="",P1203=""),"",ROUND(YEARFRAC(P1203,README!$C$5),1)) | S103: 29050 | T103: 29351 | U103: 29800 | V103: 449 | W103: 0.999 | X103: 18 | Z103: JRE 2026年3月期(第49期)決算短信(2026/5/15公表) | AA103: 確認済 | AB103: 期後2026/4/2に持分7.1%追加取得(15,540百万円)。前年取得分は公租公課0(取得原価算入) | AC103: =COUNTIF(環境認証!$A$2:$A$849,A1203) -> 0 | AD103: 1.5 | AE103: 2.6
A104: JRE-031 | B104: JRE | C104: ＪＲＥ西新宿テラス | D104: オフィス | E104: 東京都 | F104: 新宿区 | H104: 都心5区 | M104: 6036 | N104: 11 | P104: 44927 | Q104: =IF(OR($A1204="",P1204=""),"",ROUND(YEARFRAC(P1204,README!$C$5),1)) | S104: 7830 | T104: 7649 | U104: 10100 | V104: 2451 | W104: 1 | X104: 12 | Z104: JRE 2026年3月期(第49期)決算短信(2026/5/15公表) | AA104: 確認済 | AB104: 構造S、鑑定直接還元利回り3.4%。2026/3/27取得(期中約2ヶ月分の収益)。延床面積は短信非掲載(賃貸可能面積を収録)、住所詳細は有報で補完予定 | AC104: =COUNTIF(環境認証!$A$2:$A$849,A1204) -> 1 | AD104: 32 | AE104: 29
A105: JRE-032 | B105: JRE | C105: 東京オペラシティビル | D105: オフィス | E105: 東京都 | F105: 新宿区 | H105: 都心5区 | M105: 34948 | N105: 8 | P105: 39934 | Q105: =IF(OR($A1205="",P1205=""),"",ROUND(YEARFRAC(P1205,README!$C$5),1)) | S105: 31776.8 | T105: 28127 | U105: 35800 | V105: 7673 | W105: 0.997 | X105: 103 | Z105: JRE 2026年3月期(第49期)決算短信(2026/5/15公表) | AA105: 確認済 | AB105: 共同事業者の要望により費用内訳・NOI・NCFは非開示(収益・費用計・損益は開示)。付随して運営会社株式等を保有 | AC105: =COUNTIF(環境認証!$A$2:$A$849,A1205) -> 1 | AD105: 27.3 | AE105: 12.7
A106: JRE-033 | B106: JRE | C106: フロントプレイス南新宿 | D106: オフィス | E106: 東京都 | F106: 渋谷区 | H106: 都心5区 | M106: 4095 | N106: 9 | O106: 1 | P106: 34121 | Q106: =IF(OR($A1206="",P1206=""),"",ROUND(YEARFRAC(P1206,README!$C$5),1)) | S106: 9250 | T106: 9014 | U106: 9720 | V106: 706 | W106: 1 | X106: 2 | Z106: JRE 2026年3月期(第49期)決算短信(2026/5/15公表) | AA106: 確認済 | AB106: 構造SRC・S、鑑定直接還元利回り3.9%。延床面積は短信非掲載(賃貸可能面積を収録)、住所詳細は有報で補完予定 | AC106: =COUNTIF(環境認証!$A$2:$A$849,A1206) -> 0 | AD106: 7.8 | AE106: 5.1
A107: JRE-034 | B107: JRE | C107: リンクスクエア新宿 | D107: オフィス | E107: 東京都 | F107: 渋谷区 | H107: 都心5区 | M107: 9786 | N107: 11 | O107: 1 | P107: 33420 | Q107: =IF(OR($A1207="",P1207=""),"",ROUND(YEARFRAC(P1207,README!$C$5),1)) | S107: 22800 | T107: 21503 | U107: 27700 | V107: 6197 | W107: 1 | X107: 23 | Z107: JRE 2026年3月期(第49期)決算短信(2026/5/15公表) | AA107: 確認済 | AB107: 構造SRC、鑑定直接還元利回り4.0%。延床面積は短信非掲載(賃貸可能面積を収録)、住所詳細は有報で補完予定 | AC107: =COUNTIF(環境認証!$A$2:$A$849,A1207) -> 0 | AD107: 28.8 | AE107: 21.5
A108: JRE-035 | B108: JRE | C108: ＪＲＥ代々木一丁目ビル | D108: オフィス | E108: 東京都 | F108: 渋谷区 | H108: 都心5区 | M108: 7745 | N108: 7 | O108: 3 | P108: 40664 | Q108: =IF(OR($A1208="",P1208=""),"",ROUND(YEARFRAC(P1208,README!$C$5),1)) | S108: 8700 | T108: 6856 | U108: 14100 | V108: 7244 | W108: 1 | X108: 7 | Z108: JRE 2026年3月期(第49期)決算短信(2026/5/15公表) | AA108: 確認済 | AB108: 構造S・SRC、鑑定直接還元利回り4.3%。延床面積は短信非掲載(賃貸可能面積を収録)、住所詳細は有報で補完予定 | AC108: =COUNTIF(環境認証!$A$2:$A$849,A1208) -> 1 | AD108: 105.7 | AE108: 62.1
A109: JRE-036 | B109: JRE | C109: ＪＲＥ神宮前テラス | D109: オフィス | E109: 東京都 | F109: 渋谷区 | H109: 都心5区 | M109: 3147 | N109: 18 | O109: 2 | P109: 34121 | Q109: =IF(OR($A1209="",P1209=""),"",ROUND(YEARFRAC(P1209,README!$C$5),1)) | S109: 4885 | T109: 4672 | U109: 8060 | V109: 3388 | W109: 1 | X109: 5 | Z109: JRE 2026年3月期(第49期)決算短信(2026/5/15公表) | AA109: 確認済 | AB109: 構造S・SRC、鑑定直接還元利回り3.5%。建物は3登記で構成(主要建物を記載)。延床面積は短信非掲載(賃貸可能面積を収録)、住所詳細は有報で補完予定 | AC109: =COUNTIF(環境認証!$A$2:$A$849,A1209) -> 1 | AD109: 72.5 | AE109: 65
A110: JRE-037 | B110: JRE | C110: ＪＲＥ神宮前メディアスクエアビル | D110: オフィス | E110: 東京都 | F110: 渋谷区 | H110: 都心5区 | M110: 5558 | N110: 14 | O110: 2 | P110: 39995 | Q110: =IF(OR($A1210="",P1210=""),"",ROUND(YEARFRAC(P1210,README!$C$5),1)) | S110: 12200 | T110: 10537 | U110: 10500 | V110: -37 | W110: 1 | X110: 6 | Z110: JRE 2026年3月期(第49期)決算短信(2026/5/15公表) | AA110: 確認済 | AB110: 構造S・SRC、鑑定直接還元利回り3.3%。延床面積は短信非掲載(賃貸可能面積を収録)、住所詳細は有報で補完予定 | AC110: =COUNTIF(環境認証!$A$2:$A$849,A1210) -> 0 | AD110: -0.4 | AE110: -13.9
...

Sheet 物件収支
A1: 物件ID | B1: 法人ID | C1: 決算期 | D1: 期間月数 | E1: 開示区分 | F1: 賃貸事業収入合計(千円) | G1: うち賃料・共益費(千円) | H1: うちその他収入(千円) | I1: 賃貸事業費用合計(千円) | J1: うち外注委託費(千円) | K1: うち水道光熱費(千円) | L1: うち公租公課(千円) | M1: うち損害保険料(千円) | N1: うち修繕費(千円) | O1: うち減価償却費(千円) | P1: うちその他費用(千円) | Q1: 賃貸事業損益(千円) | R1: NOI(千円) | S1: 資本的支出(千円) | T1: NCF(千円) | U1: 内訳チェック(0=整合) | V1: 出典（資料名・頁） | W1: 確認ステータス | X1: 備考 | Y1: 通期保有フラグ | Z1: 年換算の妥当性 | AA1: 収入の単位精度
A2: NBF-ALL | B2: NBF | C2: 2025年12月期（第49期） | D2: 6 | E2: 開示（法人一括） | F2: 48547009 | G2: 44809206 | H2: 3737803 | I2: 25250123 | J2: 7600503 | K2: 0 | L2: 4854835 | M2: 43257 | N2: 976251 | O2: 7852749 | P2: 3922526 | Q2: =IF($A198="","",IF(OR(F198="",I198=""),"",F198-I198)) -> -24977805 | R2: =IF($A198="","",IF(Q198="","",Q198+IF(O198="",0,O198))) -> 8394749 | S2: 4987000 | T2: =IF($A198="","",IF(R198="","",R198-IF(S198="",0,S198))) -> -5234000 | U2: =IF($A198="","",IF(I198="","",I198-SUM(J198:P198))) -> 2 | V2: NBF 2025年12月期(第49期)決算短信(2026/2/16公表) p.20 不動産等賃貸事業損益の内訳・p.36-37 資本的支出 | W2: 確認済※ | X2: 法人一括収支(千円)。G=不動産賃貸収入(家賃42,402,552+共益費2,022,901+その他賃貸収入383,752)、H=その他賃貸事業収入(駐車場697,134/施設使用料311,730/付帯収益2,604,635/解約金58,998/雑収益65,304)。J=外注委託費。K水道光熱費は独立科目なし(その他費用「諸経費」3,922,526に含む)→K=0は科目非区分のため費用構造比較で留意。内訳チェック2千円は原資料の千円未満切捨て由来。損益23,296,886(開示一致)。CAPEX4,987百万円+費用処理修繕976百万円=5,964百万円の工事実施。当期不動産売却なし(前期は芝NBFタワー等で売却益4,847百万円)。開示59物件の収益計39,685百万円+非開示11物件残差8,862百万円(一括比18.3%)=一括48,547百万円と整合(非開示11物件の取得価格比率19.2%と符合) | Y2: ○（通期保有） | Z2: 年換算可 | AA2: 千円単位（正確値）
A3: NBF-01 | B3: NBF | C3: 2025年12月期（第49期） | D3: 6 | E3: 開示（物件別・収益のみ、百万円単位） | F3: 5077000 | Q3: =IF($A128="","",IF(OR(F128="",I128=""),"",F128-I128)) -> 242000 | R3: =IF($A128="","",IF(Q128="","",Q128+IF(O128="",0,O128))) -> 283000 | T3: =IF($A128="","",IF(R128="","",R128-IF(S128="",0,S128))) | U3: =IF($A128="","",IF(I128="","",I128-SUM(J128:P128))) -> 2000 | V3: NBF 2025年12月期(第49期)決算短信(2026/2/16公表) p.31-32 テナント等の概要 | W3: 確認済 | X3: 総賃貸収入(=当該物件の営業収益計・百万円未満切捨て)を千円換算した概数。費用内訳は物件別非開示(法人一括のNBF-ALL行参照)。J-REIT運用資産中最大の旗艦物件。サブリース型(変動賃料) | Y3: ○（通期保有） | Z3: 年換算可 | AA3: 百万円単位（下3桁は概数）
A4: NBF-02 | B4: NBF | C4: 2025年12月期（第49期） | D4: 6 | E4: 開示（物件別・収益のみ、百万円単位） | F4: 3084000 | Q4: =IF($A129="","",IF(OR(F129="",I129=""),"",F129-I129)) -> 98000 | R4: =IF($A129="","",IF(Q129="","",Q129+IF(O129="",0,O129))) -> 243000 | T4: =IF($A129="","",IF(R129="","",R129-IF(S129="",0,S129))) | U4: =IF($A129="","",IF(I129="","",I129-SUM(J129:P129))) -> 2000 | V4: NBF 2025年12月期(第49期)決算短信(2026/2/16公表) p.31-32 テナント等の概要 | W4: 確認済 | X4: 総賃貸収入(=当該物件の営業収益計・百万円未満切捨て)を千円換算した概数。費用内訳は物件別非開示(法人一括のNBF-ALL行参照)。2021/9・2022/3・2023/3の3回取得合計。サブリース型(変動) | Y4: ○（通期保有） | Z4: 年換算可 | AA4: 百万円単位（下3桁は概数）
A5: NBF-03 | B5: NBF | C5: 2025年12月期（第49期） | D5: 6 | E5: 開示（物件別・収益のみ、百万円単位） | F5: 1532000 | Q5: =IF($A130="","",IF(OR(F130="",I130=""),"",F130-I130)) -> 19000 | R5: =IF($A130="","",IF(Q130="","",Q130+IF(O130="",0,O130))) -> 32000 | T5: =IF($A130="","",IF(R130="","",R130-IF(S130="",0,S130))) | U5: =IF($A130="","",IF(I130="","",I130-SUM(J130:P130))) -> 1000 | V5: NBF 2025年12月期(第49期)決算短信(2026/2/16公表) p.31-32 テナント等の概要 | W5: 確認済 | X5: 総賃貸収入(=当該物件の営業収益計・百万円未満切捨て)を千円換算した概数。費用内訳は物件別非開示(法人一括のNBF-ALL行参照)。サブリース型(変動) | Y5: ○（通期保有） | Z5: 年換算可 | AA5: 百万円単位（下3桁は概数）
A6: NBF-04 | B6: NBF | C6: 2025年12月期（第49期） | D6: 6 | E6: 開示（物件別・収益のみ、百万円単位） | F6: 1283000 | Q6: =IF($A131="","",IF(OR(F131="",I131=""),"",F131-I131)) -> 386000 | R6: =IF($A131="","",IF(Q131="","",Q131+IF(O131="",0,O131))) -> 453000 | T6: =IF($A131="","",IF(R131="","",R131-IF(S131="",0,S131))) | U6: =IF($A131="","",IF(I131="","",I131-SUM(J131:P131))) -> 2000 | V6: NBF 2025年12月期(第49期)決算短信(2026/2/16公表) p.31-32 テナント等の概要 | W6: 確認済 | X6: 総賃貸収入(=当該物件の営業収益計・百万円未満切捨て)を千円換算した概数。費用内訳は物件別非開示(法人一括のNBF-ALL行参照)。任意組合出資持分(西新宿六丁目共有組合)含む。2002〜2023年の8回分割取得合計。サブリース型(変動) | Y6: ○（通期保有） | Z6: 年換算可 | AA6: 百万円単位（下3桁は概数）
A7: NBF-05 | B7: NBF | C7: 2025年12月期（第49期） | D7: 6 | E7: 開示（物件別・収益のみ、百万円単位） | F7: 1481000 | Q7: =IF($A132="","",IF(OR(F132="",I132=""),"",F132-I132)) -> 17000 | R7: =IF($A132="","",IF(Q132="","",Q132+IF(O132="",0,O132))) -> 40000 | T7: =IF($A132="","",IF(R132="","",R132-IF(S132="",0,S132))) | U7: =IF($A132="","",IF(I132="","",I132-SUM(J132:P132))) -> 3000 | V7: NBF 2025年12月期(第49期)決算短信(2026/2/16公表) p.31-32 テナント等の概要 | W7: 確認済 | X7: 総賃貸収入(=当該物件の営業収益計・百万円未満切捨て)を千円換算した概数。費用内訳は物件別非開示(法人一括のNBF-ALL行参照)。2013/5・2018/3の取得合計。ホテル部分は固定賃料契約 | Y7: ○（通期保有） | Z7: 年換算可 | AA7: 百万円単位（下3桁は概数）
A8: NBF-06 | B8: NBF | C8: 2025年12月期（第49期） | D8: 6 | E8: 非開示（テナント同意なし） | F8: 1001000 | Q8: =IF($A133="","",IF(OR(F133="",I133=""),"",F133-I133)) -> 352000 | R8: =IF($A133="","",IF(Q133="","",Q133+IF(O133="",0,O133))) -> 486000 | T8: =IF($A133="","",IF(R133="","",R133-IF(S133="",0,S133))) | U8: =IF($A133="","",IF(I133="","",I133-SUM(J133:P133))) -> 3000 | V8: NBF 2025年12月期(第49期)決算短信(2026/2/16公表) p.31-32 | W8: 確認済 | X8: テナント又は共有者の同意が得られず収益非開示(短信注3)。主要テナント:楽天グループ | Y8: ○（通期保有） | Z8: 年換算可 | AA8: 千円単位（正確値）
A9: NBF-07 | B9: NBF | C9: 2025年12月期（第49期） | D9: 6 | E9: 開示（物件別・収益のみ、百万円単位） | F9: 1420000 | Q9: =IF($A134="","",IF(OR(F134="",I134=""),"",F134-I134)) -> 9000 | R9: =IF($A134="","",IF(Q134="","",Q134+IF(O134="",0,O134))) -> 39000 | T9: =IF($A134="","",IF(R134="","",R134-IF(S134="",0,S134))) | U9: =IF($A134="","",IF(I134="","",I134-SUM(J134:P134))) -> 2000 | V9: NBF 2025年12月期(第49期)決算短信(2026/2/16公表) p.31-32 テナント等の概要 | W9: 確認済 | X9: 総賃貸収入(=当該物件の営業収益計・百万円未満切捨て)を千円換算した概数。費用内訳は物件別非開示(法人一括のNBF-ALL行参照)。鑑定評価額60,800百万円は取得価格の約2倍。主要テナント:アクサ生命 | Y9: ○（通期保有） | Z9: 年換算可 | AA9: 百万円単位（下3桁は概数）
A10: NBF-08 | B10: NBF | C10: 2025年12月期（第49期） | D10: 6 | E10: 開示（物件別・収益のみ、百万円単位） | F10: 856000 | Q10: =IF($A135="","",IF(OR(F135="",I135=""),"",F135-I135)) -> 217000 | R10: =IF($A135="","",IF(Q135="","",Q135+IF(O135="",0,O135))) -> 321000 | T10: =IF($A135="","",IF(R135="","",R135-IF(S135="",0,S135))) | U10: =IF($A135="","",IF(I135="","",I135-SUM(J135:P135))) -> 3000 | V10: NBF 2025年12月期(第49期)決算短信(2026/2/16公表) p.31-32 テナント等の概要 | W10: 確認済 | X10: 総賃貸収入(=当該物件の営業収益計・百万円未満切捨て)を千円換算した概数。費用内訳は物件別非開示(法人一括のNBF-ALL行参照) | Y10: ○（通期保有） | Z10: 年換算可 | AA10: 百万円単位（下3桁は概数）
A11: NBF-09 | B11: NBF | C11: 2025年12月期（第49期） | D11: 6 | E11: 開示（物件別・収益のみ、百万円単位） | F11: 551000 | Q11: =IF($A136="","",IF(OR(F136="",I136=""),"",F136-I136)) -> 54000 | R11: =IF($A136="","",IF(Q136="","",Q136+IF(O136="",0,O136))) -> 81000 | T11: =IF($A136="","",IF(R136="","",R136-IF(S136="",0,S136))) | U11: =IF($A136="","",IF(I136="","",I136-SUM(J136:P136))) -> 3000 | V11: NBF 2025年12月期(第49期)決算短信(2026/2/16公表) p.31-32 テナント等の概要 | W11: 確認済 | X11: 総賃貸収入(=当該物件の営業収益計・百万円未満切捨て)を千円換算した概数。費用内訳は物件別非開示(法人一括のNBF-ALL行参照)。2019年3・4月の取得合計 | Y11: ○（通期保有） | Z11: 年換算可 | AA11: 百万円単位（下3桁は概数）
A12: NBF-10 | B12: NBF | C12: 2025年12月期（第49期） | D12: 6 | E12: 開示（物件別・収益のみ、百万円単位） | F12: 889000 | Q12: =IF($A137="","",IF(OR(F137="",I137=""),"",F137-I137)) -> 99000 | R12: =IF($A137="","",IF(Q137="","",Q137+IF(O137="",0,O137))) -> 163000 | T12: =IF($A137="","",IF(R137="","",R137-IF(S137="",0,S137))) | U12: =IF($A137="","",IF(I137="","",I137-SUM(J137:P137))) -> 3000 | V12: NBF 2025年12月期(第49期)決算短信(2026/2/16公表) p.31-32 テナント等の概要 | W12: 確認済 | X12: 総賃貸収入(=当該物件の営業収益計・百万円未満切捨て)を千円換算した概数。費用内訳は物件別非開示(法人一括のNBF-ALL行参照)。敷地の賃借権を含む。2004/11・2006/4の取得合計。サブリース型(変動) | Y12: ○（通期保有） | Z12: 年換算可 | AA12: 百万円単位（下3桁は概数）
A13: NBF-11 | B13: NBF | C13: 2025年12月期（第49期） | D13: 6 | E13: 非開示（テナント同意なし） | F13: 91000 | Q13: =IF($A138="","",IF(OR(F138="",I138=""),"",F138-I138)) -> 202000 | R13: =IF($A138="","",IF(Q138="","",Q138+IF(O138="",0,O138))) -> 265000 | T13: =IF($A138="","",IF(R138="","",R138-IF(S138="",0,S138))) | U13: =IF($A138="","",IF(I138="","",I138-SUM(J138:P138))) -> 3000 | V13: NBF 2025年12月期(第49期)決算短信(2026/2/16公表) p.31-32 | W13: 確認済 | X13: テナント又は共有者の同意が得られず収益非開示(短信注3)。2004/2・2013/3の取得合計。主要テナント:インフィニオンテクノロジーズジャパン | Y13: ○（通期保有） | Z13: 年換算可 | AA13: 千円単位（正確値）
A14: NBF-12 | B14: NBF | C14: 2025年12月期（第49期） | D14: 6 | E14: 非開示（テナント同意なし） | F14: 274000 | Q14: =IF($A139="","",IF(OR(F139="",I139=""),"",F139-I139)) -> 58000 | R14: =IF($A139="","",IF(Q139="","",Q139+IF(O139="",0,O139))) -> 205000 | T14: =IF($A139="","",IF(R139="","",R139-IF(S139="",0,S139))) | U14: =IF($A139="","",IF(I139="","",I139-SUM(J139:P139))) -> 4000 | V14: NBF 2025年12月期(第49期)決算短信(2026/2/16公表) p.31-32 | W14: 確認済 | X14: テナント又は共有者の同意が得られず収益非開示(短信注3)。地上権を含む | Y14: ○（通期保有） | Z14: 年換算可 | AA14: 千円単位（正確値）
... A18: NBF-16 | B18: NBF | C18: 2025年12月期（第49期） | D18: 6 | E18: 開示（物件別・収益のみ、百万円単位） | F18: 318000 | Q18: =IF($A143="","",IF(OR(F143="",I143=""),"",F143-I143)) -> 259000 | R18: =IF($A143="","",IF(Q143="","",Q143+IF(O143="",0,O143))) -> 349000 | T18: =IF($A143="","",IF(R143="","",R143-IF(S143="",0,S143))) | U18: =IF($A143="","",IF(I143="","",I143-SUM(J143:P143))) -> 2000 | V18: NBF 2025年12月期(第49期)決算短信(2026/2/16公表) p.31-32 テナント等の概要 | W18: 確認済 | X18: 総賃貸収入(=当該物件の営業収益計・百万円未満切捨て)を千円換算した概数。費用内訳は物件別非開示(法人一括のNBF-ALL行参照) | Y18: ○（通期保有） | Z18: 年換算可 | AA18: 百万円単位（下3桁は概数）
A19: NBF-17 | B19: NBF | C19: 2025年12月期（第49期） | D19: 6 | E19: 開示（物件別・収益のみ、百万円単位） | F19: 98000 | G19: 5013812 | H19: 525450 | I19: 2268046 | J19: 569792 | K19: 362982 | L19: 429193 | M19: 12561 | N19: 102215 | O19: 774962 | P19: 16338 | Q19: =IF($A144="","",IF(OR(F144="",I144=""),"",F144-I144)) -> 146000 | R19: =IF($A144="","",IF(Q144="","",Q144+IF(O144="",0,O144))) -> 170000 | S19: 624656 | T19: =IF($A144="","",IF(R144="","",R144-IF(S144="",0,S144))) | U19: =IF($A144="","",IF(I144="","",I144-SUM(J144:P144))) -> 3000 | V19: NBF 2025年12月期(第49期)決算短信(2026/2/16公表) p.31-32 テナント等の概要 | W19: 確認済 | X19: 総賃貸収入(=当該物件の営業収益計・百万円未満切捨て)を千円換算した概数。費用内訳は物件別非開示(法人一括のNBF-ALL行参照)。2025/1/6付で建物を譲渡(売却益7,838千円)し底地のみ保有。NL稼働率・テナント数は開示対象外。取得価格は物件取得時の土地取得価格 | Y19: ○（通期保有） | Z19: 年換算可 | AA19: 百万円単位（下3桁は概数）
A20: NBF-18 | B20: NBF | C20: 2025年12月期（第49期） | D20: 6 | E20: 開示（物件別・収益のみ、百万円単位） | F20: 151000 | Q20: =IF($A145="","",IF(OR(F145="",I145=""),"",F145-I145)) -> 168000 | R20: =IF($A145="","",IF(Q145="","",Q145+IF(O145="",0,O145))) -> 298000 | T20: =IF($A145="","",IF(R145="","",R145-IF(S145="",0,S145))) | U20: =IF($A145="","",IF(I145="","",I145-SUM(J145:P145))) -> 3000 | V20: NBF 2025年12月期(第49期)決算短信(2026/2/16公表) p.31-32 テナント等の概要 | W20: 確認済 | X20: 総賃貸収入(=当該物件の営業収益計・百万円未満切捨て)を千円換算した概数。費用内訳は物件別非開示(法人一括のNBF-ALL行参照)。2021/1取得価格から2024/3一部譲渡持分(約80%)を控除した残存持分の価格 | Y20: ×（期の一部のみ） | Z20: 年換算値は実態と乖離するため利回り算定に用いない（期中の持分譲渡により分母（取得価格）のみ減額） | AA20: 百万円単位（下3桁は概数）
A21: NBF-19 | B21: NBF | C21: 2025年12月期（第49期） | D21: 6 | E21: 開示（物件別・収益のみ、百万円単位） | F21: 323000 | Q21: =IF($A146="","",IF(OR(F146="",I146=""),"",F146-I146)) -> 294000 | R21: =IF($A146="","",IF(Q146="","",Q146+IF(O146="",0,O146))) -> 377000 | T21: =IF($A146="","",IF(R146="","",R146-IF(S146="",0,S146))) | U21: =IF($A146="","",IF(I146="","",I146-SUM(J146:P146))) -> 3000 | V21: NBF 2025年12月期(第49期)決算短信(2026/2/16公表) p.31-32 テナント等の概要 | W21: 確認済 | X21: 総賃貸収入(=当該物件の営業収益計・百万円未満切捨て)を千円換算した概数。費用内訳は物件別非開示(法人一括のNBF-ALL行参照) | Y21: ○（通期保有） | Z21: 年換算可 | AA21: 百万円単位（下3桁は概数）
A22: NBF-20 | B22: NBF | C22: 2025年12月期（第49期） | D22: 6 | E22: 開示（物件別・収益のみ、百万円単位） | F22: 236000 | Q22: =IF($A147="","",IF(OR(F147="",I147=""),"",F147-I147)) -> 235000 | R22: =IF($A147="","",IF(Q147="","",Q147+IF(O147="",0,O147))) -> 309000 | T22: =IF($A147="","",IF(R147="","",R147-IF(S147="",0,S147))) | U22: =IF($A147="","",IF(I147="","",I147-SUM(J147:P147))) -> 3000 | V22: NBF 2025年12月期(第49期)決算短信(2026/2/16公表) p.31-32 テナント等の概要 | W22: 確認済 | X22: 総賃貸収入(=当該物件の営業収益計・百万円未満切捨て)を千円換算した概数。費用内訳は物件別非開示(法人一括のNBF-ALL行参照)。鑑定評価額が取得価格を下回る数少ない物件。サブリース型(変動) | Y22: ○（通期保有） | Z22: 年換算可 | AA22: 百万円単位（下3桁は概数）
A23: NBF-21 | B23: NBF | C23: 2025年12月期（第49期） | D23: 6 | E23: 開示（物件別・収益のみ、百万円単位） | F23: 242000 | Q23: =IF($A148="","",IF(OR(F148="",I148=""),"",F148-I148)) -> 83000 | R23: =IF($A148="","",IF(Q148="","",Q148+IF(O148="",0,O148))) -> 127000 | T23: =IF($A148="","",IF(R148="","",R148-IF(S148="",0,S148))) | U23: =IF($A148="","",IF(I148="","",I148-SUM(J148:P148))) -> 1000 | V23: NBF 2025年12月期(第49期)決算短信(2026/2/16公表) p.31-32 テナント等の概要 | W23: 確認済 | X23: 総賃貸収入(=当該物件の営業収益計・百万円未満切捨て)を千円換算した概数。費用内訳は物件別非開示(法人一括のNBF-ALL行参照) | Y23: ○（通期保有） | Z23: 年換算可 | AA23: 百万円単位（下3桁は概数）
A24: NBF-22 | B24: NBF | C24: 2025年12月期（第49期） | D24: 6 | E24: 開示（物件別・収益のみ、百万円単位） | F24: 304000 | Q24: =IF($A149="","",IF(OR(F149="",I149=""),"",F149-I149)) -> 24000 | R24: =IF($A149="","",IF(Q149="","",Q149+IF(O149="",0,O149))) -> 107000 | T24: =IF($A149="","",IF(R149="","",R149-IF(S149="",0,S149))) | U24: =IF($A149="","",IF(I149="","",I149-SUM(J149:P149))) -> 3000 | V24: NBF 2025年12月期(第49期)決算短信(2026/2/16公表) p.31-32 テナント等の概要 | W24: 確認済 | X24: 総賃貸収入(=当該物件の営業収益計・百万円未満切捨て)を千円換算した概数。費用内訳は物件別非開示(法人一括のNBF-ALL行参照) | Y24: ○（通期保有） | Z24: 年換算可 | AA24: 百万円単位（下3桁は概数）
A25: NBF-23 | B25: NBF | C25: 2025年12月期（第49期） | D25: 6 | E25: 開示（物件別・収益のみ、百万円単位） | F25: 203000 | Q25: =IF($A150="","",IF(OR(F150="",I150=""),"",F150-I150)) -> 50000 | R25: =IF($A150="","",IF(Q150="","",Q150+IF(O150="",0,O150))) -> 64000 | T25: =IF($A150="","",IF(R150="","",R150-IF(S150="",0,S150))) | U25: =IF($A150="","",IF(I150="","",I150-SUM(J150:P150))) -> 1000 | V25: NBF 2025年12月期(第49期)決算短信(2026/2/16公表) p.31-32 テナント等の概要 | W25: 確認済 | X25: 総賃貸収入(=当該物件の営業収益計・百万円未満切捨て)を千円換算した概数。費用内訳は物件別非開示(法人一括のNBF-ALL行参照) | Y25: ○（通期保有） | Z25: 年換算可 | AA25: 百万円単位（下3桁は概数）
A26: NBF-24 | B26: NBF | C26: 2025年12月期（第49期） | D26: 6 | E26: 開示（物件別・収益のみ、百万円単位） | F26: 211000 | Q26: =IF($A151="","",IF(OR(F151="",I151=""),"",F151-I151)) -> 20000 | R26: =IF($A151="","",IF(Q151="","",Q151+IF(O151="",0,O151))) -> 88000 | T26: =IF($A151="","",IF(R151="","",R151-IF(S151="",0,S151))) | U26: =IF($A151="","",IF(I151="","",I151-SUM(J151:P151))) -> 1000 | V26: NBF 2025年12月期(第49期)決算短信(2026/2/16公表) p.31-32 テナント等の概要 | W26: 確認済 | X26: 総賃貸収入(=当該物件の営業収益計・百万円未満切捨て)を千円換算した概数。費用内訳は物件別非開示(法人一括のNBF-ALL行参照) | Y26: ○（通期保有） | Z26: 年換算可 | AA26: 百万円単位（下3桁は概数）
A27: NBF-25 | B27: NBF | C27: 2025年12月期（第49期） | D27: 6 | E27: 開示（物件別・収益のみ、百万円単位） | F27: 199000 | Q27: =IF($A152="","",IF(OR(F152="",I152=""),"",F152-I152)) -> 79000 | R27: =IF($A152="","",IF(Q152="","",Q152+IF(O152="",0,O152))) -> 97000 | T27: =IF($A152="","",IF(R152="","",R152-IF(S152="",0,S152))) | U27: =IF($A152="","",IF(I152="","",I152-SUM(J152:P152))) -> 2000 | V27: NBF 2025年12月期(第49期)決算短信(2026/2/16公表) p.31-32 テナント等の概要 | W27: 確認済 | X27: 総賃貸収入(=当該物件の営業収益計・百万円未満切捨て)を千円換算した概数。費用内訳は物件別非開示(法人一括のNBF-ALL行参照)。2005/9・2020/11の取得合計。サブリース型(変動) | Y27: ○（通期保有） | Z27: 年換算可 | AA27: 百万円単位（下3桁は概数）
A28: NBF-26 | B28: NBF | C28: 2025年12月期（第49期） | D28: 6 | E28: 非開示（テナント同意なし） | Q28: =IF($A153="","",IF(OR(F153="",I153=""),"",F153-I153)) -> 3271216 | R28: =IF($A153="","",IF(Q153="","",Q153+IF(O153="",0,O153))) -> -1395084 | T28: =IF($A153="","",IF(R153="","",R153-IF(S153="",0,S153))) -> 296306 | U28: =IF($A153="","",IF(I153="","",I153-SUM(J153:P153))) -> 3 | V28: NBF 2025年12月期(第49期)決算短信(2026/2/16公表) p.31-32 | W28: 確認済 | X28: テナント又は共有者の同意が得られず収益非開示(短信注3)。2026/6/30付で三井不動産へ譲渡予定(譲渡価格10,000百万円=鑑定5,360百万円の約1.9倍、売却益5,112百万円見込)。港区三田・1991年6月竣工・SRC地下1階付12階建・延床9,185.13㎡(後発事象注記より) | Y28: ○（通期保有） | Z28: 年換算可 | AA28: 千円単位（正確値）
A29: NBF-27 | B29: NBF | C29: 2025年12月期（第49期） | D29: 6 | E29: 開示（物件別・収益のみ、百万円単位） | F29: 194000 | Q29: =IF($A154="","",IF(OR(F154="",I154=""),"",F154-I154)) | R29: =IF($A154="","",IF(Q154="","",Q154+IF(O154="",0,O154))) -> 23296886 | T29: =IF($A154="","",IF(R154="","",R154-IF(S154="",0,S154))) -> -17125056 | U29: =IF($A154="","",IF(I154="","",I154-SUM(J154:P154))) | V29: NBF 2025年12月期(第49期)決算短信(2026/2/16公表) p.31-32 テナント等の概要 | W29: 確認済 | X29: 総賃貸収入(=当該物件の営業収益計・百万円未満切捨て)を千円換算した概数。費用内訳は物件別非開示(法人一括のNBF-ALL行参照) | Y29: ○（通期保有） | Z29: 年換算可 | AA29: 百万円単位（下3桁は概数）
A30: NBF-28 | B30: NBF | C30: 2025年12月期（第49期） | D30: 6 | E30: 非開示（テナント同意なし） | Q30: =IF($A155="","",IF(OR(F155="",I155=""),"",F155-I155)) | R30: =IF($A155="","",IF(Q155="","",Q155+IF(O155="",0,O155))) | T30: =IF($A155="","",IF(R155="","",R155-IF(S155="",0,S155))) -> 242000 | U30: =IF($A155="","",IF(I155="","",I155-SUM(J155:P155))) | V30: NBF 2025年12月期(第49期)決算短信(2026/2/16公表) p.31-32 | W30: 確認済 | X30: テナント又は共有者の同意が得られず収益非開示(短信注3) | Y30: ○（通期保有） | Z30: 年換算可 | AA30: 千円単位（正確値）
A31: NBF-29 | B31: NBF | C31: 2025年12月期（第49期） | D31: 6 | E31: 非開示（テナント同意なし） | F31: 163769 | Q31: =IF($A156="","",IF(OR(F156="",I156=""),"",F156-I156)) | R31: =IF($A156="","",IF(Q156="","",Q156+IF(O156="",0,O156))) | T31: =IF($A156="","",IF(R156="","",R156-IF(S156="",0,S156))) -> 98000 | U31: =IF($A156="","",IF(I156="","",I156-SUM(J156:P156))) | V31: NBF 2025年12月期(第49期)決算短信(2026/2/16公表) p.31-32 | W31: 確認済 | X31: テナント又は共有者の同意が得られず収益非開示(短信注3)。旧NBF新川ビルの取得価格を2020/6/30鑑定評価額比率で按分した金額 | Y31: ○（通期保有） | Z31: 年換算可 | AA31: 千円単位（正確値）
A32: NBF-30 | B32: NBF | C32: 2025年12月期（第49期） | D32: 6 | E32: 開示（物件別・収益のみ、百万円単位） | F32: 185000 | Q32: =IF($A157="","",IF(OR(F157="",I157=""),"",F157-I157)) | R32: =IF($A157="","",IF(Q157="","",Q157+IF(O157="",0,O157))) | T32: =IF($A157="","",IF(R157="","",R157-IF(S157="",0,S157))) -> 19000 | U32: =IF($A157="","",IF(I157="","",I157-SUM(J157:P157))) | V32: NBF 2025年12月期(第49期)決算短信(2026/2/16公表) p.31-32 テナント等の概要 | W32: 確認済 | X32: 総賃貸収入(=当該物件の営業収益計・百万円未満切捨て)を千円換算した概数。費用内訳は物件別非開示(法人一括のNBF-ALL行参照) | Y32: ○（通期保有） | Z32: 年換算可 | AA32: 百万円単位（下3桁は概数）
A33: NBF-31 | B33: NBF | C33: 2025年12月期（第49期） | D33: 6 | E33: 開示（物件別・収益のみ、百万円単位） | F33: 400000 | Q33: =IF($A158="","",IF(OR(F158="",I158=""),"",F158-I158)) | R33: =IF($A158="","",IF(Q158="","",Q158+IF(O158="",0,O158))) | T33: =IF($A158="","",IF(R158="","",R158-IF(S158="",0,S158))) -> 386000 | U33: =IF($A158="","",IF(I158="","",I158-SUM(J158:P158))) | V33: NBF 2025年12月期(第49期)決算短信(2026/2/16公表) p.31-32 テナント等の概要 | W33: 確認済 | X33: 総賃貸収入(=当該物件の営業収益計・百万円未満切捨て)を千円換算した概数。費用内訳は物件別非開示(法人一括のNBF-ALL行参照) | Y33: ○（通期保有） | Z33: 年換算可 | AA33: 百万円単位（下3桁は概数）
A34: NBF-32 | B34: NBF | C34: 2025年12月期（第49期） | D34: 6 | E34: 非開示（テナント同意なし） | F34: 421097 | Q34: =IF($A159="","",IF(OR(F159="",I159=""),"",F159-I159)) | R34: =IF($A159="","",IF(Q159="","",Q159+IF(O159="",0,O159))) | T34: =IF($A159="","",IF(R159="","",R159-IF(S159="",0,S159))) -> 17000 | U34: =IF($A159="","",IF(I159="","",I159-SUM(J159:P159))) | V34: NBF 2025年12月期(第49期)決算短信(2026/2/16公表) p.31-32 | W34: 確認済 | X34: テナント又は共有者の同意が得られず収益非開示(短信注3)。区分所有権(2022〜2024年3回取得・既存保有約47.69%)。2026/3/31付で追加取得予定(約9.19%・14,810百万円→合計約56.88%)。2020年3月竣工・地下2階付36階建・延床178,504.10㎡(建物全体)。店舗区画は固定賃料型ML | Y34: ○（通期保有） | Z34: 年換算可 | AA34: 千円単位（正確値）
A35: NBF-33 | B35: NBF | C35: 2025年12月期（第49期） | D35: 6 | E35: 非開示（テナント同意なし） | F35: 369172 | Q35: =IF($A160="","",IF(OR(F160="",I160=""),"",F160-I160)) | R35: =IF($A160="","",IF(Q160="","",Q160+IF(O160="",0,O160))) | T35: =IF($A160="","",IF(R160="","",R160-IF(S160="",0,S160))) -> 352000 | U35: =IF($A160="","",IF(I160="","",I160-SUM(J160:P160))) | V35: NBF 2025年12月期(第49期)決算短信(2026/2/16公表) p.31-32 | W35: 確認済 | X35: テナント又は共有者の同意が得られず収益非開示(短信注3)。主要テナント:ソニーグループ(賃貸面積73,477㎡=ポートフォリオ全体の6.0%) | Y35: ○（通期保有） | Z35: 年換算可 | AA35: 千円単位（正確値）
A36: NBF-34 | B36: NBF | C36: 2025年12月期（第49期） | D36: 6 | E36: 開示（物件別・収益のみ、百万円単位） | F36: 2084000 | Q36: =IF($A161="","",IF(OR(F161="",I161=""),"",F161-I161)) | R36: =IF($A161="","",IF(Q161="","",Q161+IF(O161="",0,O161))) | T36: =IF($A161="","",IF(R161="","",R161-IF(S161="",0,S161))) -> 9000 | U36: =IF($A161="","",IF(I161="","",I161-SUM(J161:P161))) | V36: NBF 2025年12月期(第49期)決算短信(2026/2/16公表) p.31-32 テナント等の概要 | W36: 確認済 | X36: 総賃貸収入(=当該物件の営業収益計・百万円未満切捨て)を千円換算した概数。費用内訳は物件別非開示(法人一括のNBF-ALL行参照)。2006・2011・2013年の3回取得合計。サブリース型(変動) | Y36: ○（通期保有） | Z36: 年換算可 | AA36: 百万円単位（下3桁は概数）
A37: NBF-35 | B37: NBF | C37: 2025年12月期（第49期） | D37: 6 | E37: 開示（物件別・収益のみ、百万円単位） | F37: 1062000 | Q37: =IF($A162="","",IF(OR(F162="",I162=""),"",F162-I162)) | R37: =IF($A162="","",IF(Q162="","",Q162+IF(O162="",0,O162))) | T37: =IF($A162="","",IF(R162="","",R162-IF(S162="",0,S162))) -> 217000 | U37: =IF($A162="","",IF(I162="","",I162-SUM(J162:P162))) | V37: NBF 2025年12月期(第49期)決算短信(2026/2/16公表) p.31-32 テナント等の概要 | W37: 確認済 | X37: 総賃貸収入(=当該物件の営業収益計・百万円未満切捨て)を千円換算した概数。費用内訳は物件別非開示(法人一括のNBF-ALL行参照)。主要テナント:ソフトバンク | Y37: ○（通期保有） | Z37: 年換算可 | AA37: 百万円単位（下3桁は概数）
A38: NBF-36 | B38: NBF | C38: 2025年12月期（第49期） | D38: 6 | E38: 非開示（テナント同意なし） | F38: 807893 | Q38: =IF($A163="","",IF(OR(F163="",I163=""),"",F163-I163)) | R38: =IF($A163="","",IF(Q163="","",Q163+IF(O163="",0,O163))) | T38: =IF($A163="","",IF(R163="","",R163-IF(S163="",0,S163))) -> 54000 | U38: =IF($A163="","",IF(I163="","",I163-SUM(J163:P163))) | V38: NBF 2025年12月期(第49期)決算短信(2026/2/16公表) p.31-32 | W38: 確認済 | X38: テナント又は共有者の同意が得られず収益非開示(短信注3)。2016/6・2021/3の取得合計。主要テナント:日立リアルエステートパートナーズ | Y38: ○（通期保有） | Z38: 年換算可 | AA38: 千円単位（正確値）
A39: NBF-37 | B39: NBF | C39: 2025年12月期（第49期） | D39: 6 | E39: 開示（物件別・収益のみ、百万円単位） | F39: 834000 | Q39: =IF($A164="","",IF(OR(F164="",I164=""),"",F164-I164)) | R39: =IF($A164="","",IF(Q164="","",Q164+IF(O164="",0,O164))) | T39: =IF($A164="","",IF(R164="","",R164-IF(S164="",0,S164))) -> 99000 | U39: =IF($A164="","",IF(I164="","",I164-SUM(J164:P164))) | V39: NBF 2025年12月期(第49期)決算短信(2026/2/16公表) p.31-32 テナント等の概要 | W39: 確認済 | X39: 総賃貸収入(=当該物件の営業収益計・百万円未満切捨て)を千円換算した概数。費用内訳は物件別非開示(法人一括のNBF-ALL行参照)。主要テナント:博報堂DYホールディングス | Y39: ○（通期保有） | Z39: 年換算可 | AA39: 百万円単位（下3桁は概数）
A40: NBF-38 | B40: NBF | C40: 2025年12月期（第49期） | D40: 6 | E40: 開示（物件別・収益のみ、百万円単位） | F40: 670000 | Q40: =IF($A165="","",IF(OR(F165="",I165=""),"",F165-I165)) | R40: =IF($A165="","",IF(Q165="","",Q165+IF(O165="",0,O165))) | T40: =IF($A165="","",IF(R165="","",R165-IF(S165="",0,S165))) -> 202000 | U40: =IF($A165="","",IF(I165="","",I165-SUM(J165:P165))) | V40: NBF 2025年12月期(第49期)決算短信(2026/2/16公表) p.31-32 テナント等の概要 | W40: 確認済 | X40: 総賃貸収入(=当該物件の営業収益計・百万円未満切捨て)を千円換算した概数。費用内訳は物件別非開示(法人一括のNBF-ALL行参照)。2016〜2020年の5回分割取得合計。サブリース型(変動) | Y40: ○（通期保有） | Z40: 年換算可 | AA40: 百万円単位（下3桁は概数）
A41: NBF-39 | B41: NBF | C41: 2025年12月期（第49期） | D41: 6 | E41: 開示（物件別・収益のみ、百万円単位） | F41: 940000 | Q41: =IF($A166="","",IF(OR(F166="",I166=""),"",F166-I166)) | R41: =IF($A166="","",IF(Q166="","",Q166+IF(O166="",0,O166))) | T41: =IF($A166="","",IF(R166="","",R166-IF(S166="",0,S166))) -> 58000 | U41: =IF($A166="","",IF(I166="","",I166-SUM(J166:P166))) | V41: NBF 2025年12月期(第49期)決算短信(2026/2/16公表) p.31-32 テナント等の概要 | W41: 確認済 | X41: 総賃貸収入(=当該物件の営業収益計・百万円未満切捨て)を千円換算した概数。費用内訳は物件別非開示(法人一括のNBF-ALL行参照)。任意組合出資持分(中目黒GTタワー共有床組合)含む。2003〜2005年の3回取得合計。サブリース型(変動) | Y41: ○（通期保有） | Z41: 年換算可 | AA41: 百万円単位（下3桁は概数）
A42: NBF-40 | B42: NBF | C42: 2025年12月期（第49期） | D42: 6 | E42: 非開示（テナント同意なし） | F42: 1282915 | Q42: =IF($A167="","",IF(OR(F167="",I167=""),"",F167-I167)) | R42: =IF($A167="","",IF(Q167="","",Q167+IF(O167="",0,O167))) | T42: =IF($A167="","",IF(R167="","",R167-IF(S167="",0,S167))) -> 168000 | U42: =IF($A167="","",IF(I167="","",I167-SUM(J167:P167))) | V42: NBF 2025年12月期(第49期)決算短信(2026/2/16公表) p.31-32 | W42: 確認済 | X42: テナント又は共有者の同意が得られず収益非開示(短信注3)。サブリース型(変動) | Y42: ○（通期保有） | Z42: 年換算可 | AA42: 千円単位（正確値）
... A53: NBF-51 | B53: NBF | C53: 2025年12月期（第49期） | D53: 6 | E53: 開示（物件別・収益のみ、百万円単位） | F53: 110000 | Q53: =IF($A178="","",IF(OR(F178="",I178=""),"",F178-I178)) | R53: =IF($A178="","",IF(Q178="","",Q178+IF(O178="",0,O178))) | T53: =IF($A178="","",IF(R178="","",R178-IF(S178="",0,S178))) | U53: =IF($A178="","",IF(I178="","",I178-SUM(J178:P178))) | V53: NBF 2025年12月期(第49期)決算短信(2026/2/16公表) p.31-32 テナント等の概要 | W53: 確認済 | X53: 総賃貸収入(=当該物件の営業収益計・百万円未満切捨て)を千円換算した概数。費用内訳は物件別非開示(法人一括のNBF-ALL行参照) | Y53: ○（通期保有） | Z53: 年換算可 | AA53: 百万円単位（下3桁は概数）
A54: NBF-52 | B54: NBF | C54: 2025年12月期（第49期） | D54: 6 | E54: 開示（物件別・収益のみ、百万円単位） | F54: 110000 | G54: 9796629 | H54: 1318829 | I54: 5799809 | J54: 1579242 | K54: 1104826 | L54: 1009732 | M54: 25125 | N54: 165179 | O54: 1789009 | P54: 126692 | Q54: =IF($A179="","",IF(OR(F179="",I179=""),"",F179-I179)) | R54: =IF($A179="","",IF(Q179="","",Q179+IF(O179="",0,O179))) | S54: 1559000 | T54: =IF($A179="","",IF(R179="","",R179-IF(S179="",0,S179))) | U54: =IF($A179="","",IF(I179="","",I179-SUM(J179:P179))) | V54: NBF 2025年12月期(第49期)決算短信(2026/2/16公表) p.31-32 テナント等の概要 | W54: 確認済 | X54: 総賃貸収入(=当該物件の営業収益計・百万円未満切捨て)を千円換算した概数。費用内訳は物件別非開示(法人一括のNBF-ALL行参照) | Y54: ○（通期保有） | Z54: 年換算可 | AA54: 百万円単位（下3桁は概数）
A55: NBF-53 | B55: NBF | C55: 2025年12月期（第49期） | D55: 6 | E55: 開示（物件別・収益のみ、百万円単位） | F55: 17000 | Q55: =IF($A180="","",IF(OR(F180="",I180=""),"",F180-I180)) | R55: =IF($A180="","",IF(Q180="","",Q180+IF(O180="",0,O180))) | T55: =IF($A180="","",IF(R180="","",R180-IF(S180="",0,S180))) | U55: =IF($A180="","",IF(I180="","",I180-SUM(J180:P180))) | V55: NBF 2025年12月期(第49期)決算短信(2026/2/16公表) p.31-32 テナント等の概要 | W55: 確認済 | X55: 総賃貸収入(=当該物件の営業収益計・百万円未満切捨て)を千円換算した概数。費用内訳は物件別非開示(法人一括のNBF-ALL行参照)。2025/11取得(当期期中取得・約2ヶ月のため収益17百万円は期間僅少)。稼働62.3%はリースアップ途上。2026/4/1付で「CONNECT SAPPORO」から名称変更予定 | Y55: ×（期の一部のみ） | Z55: 年換算値は実態と乖離するため利回り算定に用いない（期中取得） | AA55: 百万円単位・低精度（収入50百万円未満で丸め影響大）
A56: NBF-54 | B56: NBF | C56: 2025年12月期（第49期） | D56: 6 | E56: 開示（物件別・収益のみ、百万円単位） | F56: 348000 | Q56: =IF($A181="","",IF(OR(F181="",I181=""),"",F181-I181)) | R56: =IF($A181="","",IF(Q181="","",Q181+IF(O181="",0,O181))) | T56: =IF($A181="","",IF(R181="","",R181-IF(S181="",0,S181))) | U56: =IF($A181="","",IF(I181="","",I181-SUM(J181:P181))) | V56: NBF 2025年12月期(第49期)決算短信(2026/2/16公表) p.31-32 テナント等の概要 | W56: 確認済 | X56: 総賃貸収入(=当該物件の営業収益計・百万円未満切捨て)を千円換算した概数。費用内訳は物件別非開示(法人一括のNBF-ALL行参照)。2003〜2005年の4回分割取得合計 | Y56: ○（通期保有） | Z56: 年換算可 | AA56: 百万円単位（下3桁は概数）
A57: NBF-55 | B57: NBF | C57: 2025年12月期（第49期） | D57: 6 | E57: 開示（物件別・収益のみ、百万円単位） | F57: 126000 | Q57: =IF($A182="","",IF(OR(F182="",I182=""),"",F182-I182)) | R57: =IF($A182="","",IF(Q182="","",Q182+IF(O182="",0,O182))) | T57: =IF($A182="","",IF(R182="","",R182-IF(S182="",0,S182))) | U57: =IF($A182="","",IF(I182="","",I182-SUM(J182:P182))) | V57: NBF 2025年12月期(第49期)決算短信(2026/2/16公表) p.31-32 テナント等の概要 | W57: 確認済 | X57: 総賃貸収入(=当該物件の営業収益計・百万円未満切捨て)を千円換算した概数。費用内訳は物件別非開示(法人一括のNBF-ALL行参照)。2026/7/1付で譲渡予定(譲渡価格1,900百万円・売却益217百万円見込)。1990年11月竣工・SRC地下2階付9階建・延床8,149.78㎡(後発事象注記より) | Y57: ○（通期保有） | Z57: 年換算可 | AA57: 百万円単位（下3桁は概数）
A58: NBF-56 | B58: NBF | C58: 2025年12月期（第49期） | D58: 6 | E58: 開示（物件別・収益のみ、百万円単位） | F58: 161000 | Q58: =IF($A183="","",IF(OR(F183="",I183=""),"",F183-I183)) | R58: =IF($A183="","",IF(Q183="","",Q183+IF(O183="",0,O183))) | T58: =IF($A183="","",IF(R183="","",R183-IF(S183="",0,S183))) | U58: =IF($A183="","",IF(I183="","",I183-SUM(J183:P183))) | V58: NBF 2025年12月期(第49期)決算短信(2026/2/16公表) p.31-32 テナント等の概要 | W58: 確認済 | X58: 総賃貸収入(=当該物件の営業収益計・百万円未満切捨て)を千円換算した概数。費用内訳は物件別非開示(法人一括のNBF-ALL行参照)。2025年(第48期)取得。稼働46.6%はリースアップ途上 | Y58: ×（期の一部のみ） | Z58: 年換算値は実態と乖離するため利回り算定に用いない（期中取得） | AA58: 百万円単位（下3桁は概数）
A59: NBF-57 | B59: NBF | C59: 2025年12月期（第49期） | D59: 6 | E59: 開示（物件別・収益のみ、百万円単位） | F59: 614000 | Q59: =IF($A184="","",IF(OR(F184="",I184=""),"",F184-I184)) | R59: =IF($A184="","",IF(Q184="","",Q184+IF(O184="",0,O184))) | T59: =IF($A184="","",IF(R184="","",R184-IF(S184="",0,S184))) | U59: =IF($A184="","",IF(I184="","",I184-SUM(J184:P184))) | V59: NBF 2025年12月期(第49期)決算短信(2026/2/16公表) p.31-32 テナント等の概要 | W59: 確認済 | X59: 総賃貸収入(=当該物件の営業収益計・百万円未満切捨て)を千円換算した概数。費用内訳は物件別非開示(法人一括のNBF-ALL行参照) | Y59: ○（通期保有） | Z59: 年換算可 | AA59: 百万円単位（下3桁は概数）
A60: NBF-58 | B60: NBF | C60: 2025年12月期（第49期） | D60: 6 | E60: 開示（物件別・収益のみ、百万円単位） | F60: 457000 | Q60: =IF($A185="","",IF(OR(F185="",I185=""),"",F185-I185)) | R60: =IF($A185="","",IF(Q185="","",Q185+IF(O185="",0,O185))) | T60: =IF($A185="","",IF(R185="","",R185-IF(S185="",0,S185))) | U60: =IF($A185="","",IF(I185="","",I185-SUM(J185:P185))) | V60: NBF 2025年12月期(第49期)決算短信(2026/2/16公表) p.31-32 テナント等の概要 | W60: 確認済 | X60: 総賃貸収入(=当該物件の営業収益計・百万円未満切捨て)を千円換算した概数。費用内訳は物件別非開示(法人一括のNBF-ALL行参照)。サブリース型(変動) | Y60: ○（通期保有） | Z60: 年換算可 | AA60: 百万円単位（下3桁は概数）
A61: NBF-59 | B61: NBF | C61: 2025年12月期（第49期） | D61: 6 | E61: 開示（物件別・収益のみ、百万円単位） | F61: 508000 | Q61: =IF($A186="","",IF(OR(F186="",I186=""),"",F186-I186)) | R61: =IF($A186="","",IF(Q186="","",Q186+IF(O186="",0,O186))) | T61: =IF($A186="","",IF(R186="","",R186-IF(S186="",0,S186))) | U61: =IF($A186="","",IF(I186="","",I186-SUM(J186:P186))) | V61: NBF 2025年12月期(第49期)決算短信(2026/2/16公表) p.31-32 テナント等の概要 | W61: 確認済 | X61: 総賃貸収入(=当該物件の営業収益計・百万円未満切捨て)を千円換算した概数。費用内訳は物件別非開示(法人一括のNBF-ALL行参照)。サブリース型(変動) | Y61: ○（通期保有） | Z61: 年換算可 | AA61: 百万円単位（下3桁は概数）
A62: NBF-60 | B62: NBF | C62: 2025年12月期（第49期） | D62: 6 | E62: 開示（物件別・収益のみ、百万円単位） | F62: 253000 | Q62: =IF($A187="","",IF(OR(F187="",I187=""),"",F187-I187)) | R62: =IF($A187="","",IF(Q187="","",Q187+IF(O187="",0,O187))) | T62: =IF($A187="","",IF(R187="","",R187-IF(S187="",0,S187))) | U62: =IF($A187="","",IF(I187="","",I187-SUM(J187:P187))) | V62: NBF 2025年12月期(第49期)決算短信(2026/2/16公表) p.31-32 テナント等の概要 | W62: 確認済 | X62: 総賃貸収入(=当該物件の営業収益計・百万円未満切捨て)を千円換算した概数。費用内訳は物件別非開示(法人一括のNBF-ALL行参照)。2004/3・2008/3の取得合計 | Y62: ○（通期保有） | Z62: 年換算可 | AA62: 百万円単位（下3桁は概数）
A63: NBF-61 | B63: NBF | C63: 2025年12月期（第49期） | D63: 6 | E63: 開示（物件別・収益のみ、百万円単位） | F63: 1413000 | Q63: =IF($A188="","",IF(OR(F188="",I188=""),"",F188-I188)) | R63: =IF($A188="","",IF(Q188="","",Q188+IF(O188="",0,O188))) | T63: =IF($A188="","",IF(R188="","",R188-IF(S188="",0,S188))) | U63: =IF($A188="","",IF(I188="","",I188-SUM(J188:P188))) | V63: NBF 2025年12月期(第49期)決算短信(2026/2/16公表) p.31-32 テナント等の概要 | W63: 確認済 | X63: 総賃貸収入(=当該物件の営業収益計・百万円未満切捨て)を千円換算した概数。費用内訳は物件別非開示(法人一括のNBF-ALL行参照)。サブリース型(変動) | Y63: ○（通期保有） | Z63: 年換算可 | AA63: 百万円単位（下3桁は概数）
A64: NBF-62 | B64: NBF | C64: 2025年12月期（第49期） | D64: 6 | E64: 開示（物件別・収益のみ、百万円単位） | F64: 666000 | Q64: =IF($A189="","",IF(OR(F189="",I189=""),"",F189-I189)) | R64: =IF($A189="","",IF(Q189="","",Q189+IF(O189="",0,O189))) | T64: =IF($A189="","",IF(R189="","",R189-IF(S189="",0,S189))) | U64: =IF($A189="","",IF(I189="","",I189-SUM(J189:P189))) | V64: NBF 2025年12月期(第49期)決算短信(2026/2/16公表) p.31-32 テナント等の概要 | W64: 確認済 | X64: 総賃貸収入(=当該物件の営業収益計・百万円未満切捨て)を千円換算した概数。費用内訳は物件別非開示(法人一括のNBF-ALL行参照) | Y64: ○（通期保有） | Z64: 年換算可 | AA64: 百万円単位（下3桁は概数）
A65: NBF-63 | B65: NBF | C65: 2025年12月期（第49期） | D65: 6 | E65: 開示（物件別・収益のみ、百万円単位） | F65: 633000 | Q65: =IF($A190="","",IF(OR(F190="",I190=""),"",F190-I190)) | R65: =IF($A190="","",IF(Q190="","",Q190+IF(O190="",0,O190))) | T65: =IF($A190="","",IF(R190="","",R190-IF(S190="",0,S190))) | U65: =IF($A190="","",IF(I190="","",I190-SUM(J190:P190))) | V65: NBF 2025年12月期(第49期)決算短信(2026/2/16公表) p.31-32 テナント等の概要 | W65: 確認済 | X65: 総賃貸収入(=当該物件の営業収益計・百万円未満切捨て)を千円換算した概数。費用内訳は物件別非開示(法人一括のNBF-ALL行参照) | Y65: ○（通期保有） | Z65: 年換算可 | AA65: 百万円単位（下3桁は概数）
A66: NBF-64 | B66: NBF | C66: 2025年12月期（第49期） | D66: 6 | E66: 開示（物件別・収益のみ、百万円単位） | F66: 627000 | Q66: =IF($A191="","",IF(OR(F191="",I191=""),"",F191-I191)) | R66: =IF($A191="","",IF(Q191="","",Q191+IF(O191="",0,O191))) -> 17499163 | T66: =IF($A191="","",IF(R191="","",R191-IF(S191="",0,S191))) -> 23808691 | U66: =IF($A191="","",IF(I191="","",I191-SUM(J191:P191))) | V66: NBF 2025年12月期(第49期)決算短信(2026/2/16公表) p.31-32 テナント等の概要 | W66: 確認済 | X66: 総賃貸収入(=当該物件の営業収益計・百万円未満切捨て)を千円換算した概数。費用内訳は物件別非開示(法人一括のNBF-ALL行参照)。サブリース型(変動) | Y66: ○（通期保有） | Z66: 年換算可 | AA66: 百万円単位（下3桁は概数）
... A72: NBF-70 | B72: NBF | C72: 2025年12月期（第49期） | D72: 6 | E72: 開示（物件別・収益のみ、百万円単位） | F72: 201000 | Q72: =IF($A197="","",IF(OR(F197="",I197=""),"",F197-I197)) | R72: =IF($A197="","",IF(Q197="","",Q197+IF(O197="",0,O197))) -> 267000 | T72: =IF($A197="","",IF(R197="","",R197-IF(S197="",0,S197))) -> 159000 | U72: =IF($A197="","",IF(I197="","",I197-SUM(J197:P197))) | V72: NBF 2025年12月期(第49期)決算短信(2026/2/16公表) p.31-32 テナント等の概要 | W72: 確認済 | X72: 総賃貸収入(=当該物件の営業収益計・百万円未満切捨て)を千円換算した概数。費用内訳は物件別非開示(法人一括のNBF-ALL行参照) | Y72: ○（通期保有） | Z72: 年換算可 | AA72: 百万円単位（下3桁は概数）
A73: JRE-ALL | B73: JRE | C73: 2026年3月期（第49期） | D73: 6 | E73: 開示（法人一括・費用内訳含む） | F73: 36817129 | G73: 36743295 | H73: 73833 | I73: 19317966 | J73: 4157545 | K73: 2748341 | L73: 3906597 | M73: 50981 | N73: 1832972 | O73: 6309528 | P73: 311999 | Q73: =IF($A1252="","",IF(OR(F1252="",I1252=""),"",F1252-I1252)) -> 17499163 | R73: =IF($A1252="","",IF(Q1252="","",Q1252+IF(O1252="",0,O1252))) | S73: 5325000 | T73: =IF($A1252="","",IF(R1252="","",R1252-IF(S1252="",0,S1252))) | U73: =IF($A1252="","",IF(I1252="","",I1252-SUM(J1252:P1252))) -> 3 | V73: JRE 2026年3月期(第49期)決算短信(2026/5/15公表) 損益計算書関係注記 | W73: 確認済※ | X73: 一括実績(損益計算書関係注記・千円単位)。掲載損益17,499,162千円と賃貸事業損益(F-I)17,499,163千円に1千円差=原資料内切捨て(恒例)。費用内訳合算19,317,963とI=19,317,966に3千円差(「内訳チェック(0=整合)」欄)。G=賃貸事業収入計36,743,295(賃料31,146,401+共益費1,773,500+駐車場728,999+その他賃貸収入3,094,394)、H=その他賃貸事業収入73,833(解約違約金29,784+雑収入44,049)。物件別はフル開示76+一部開示1(オペラシティ)+損益NOIのみ2(グランフロント大阪)。物件別F合算(GF除く)36,133百万円と一括の差684百万円=GF2物件分。「資本的支出(千円)」欄は期中資本的支出5,325百万円(修繕費1,832百万円と合わせ7,158百万円の工事・物件別CAPEX合算との差36百万円は切捨て累積)。不動産等売却益5,626,833千円(赤坂パークビル3,946,189+天神クリスタル1,680,644)は賃貸事業外のためF/賃貸事業損益対象外。圧縮積立金563,830千円繰入 | Y73: ○（通期保有） | Z73: 年換算可 | AA73: 千円単位（正確値）
A74: JRE-001 | B74: JRE | C74: 2026年3月期（第49期） | D74: 6 | E74: 開示（物件別・費用内訳含む・百万円単位） | F74: 1786000 | I74: 659000 | J74: 134000 | K74: 88000 | L74: 103000 | M74: 1000 | N74: 82000 | O74: 249000 | P74: 0 | Q74: =IF($A1173="","",IF(OR(F1173="",I1173=""),"",F1173-I1173)) -> 1127000 | R74: =IF($A1173="","",IF(Q1173="","",Q1173+IF(O1173="",0,O1173))) | S74: 278000 | T74: =IF($A1173="","",IF(R1173="","",R1173-IF(S1173="",0,S1173))) | U74: =IF($A1173="","",IF(I1173="","",I1173-SUM(J1173:P1173))) -> 2000 | V74: JRE 2026年3月期(第49期)決算短信(2026/5/15公表) ②不動産等関連資産の損益状況 | W74: 確認済 | X74: 百万円単位開示×1000で収録(下3桁は概数)。各科目は百万円未満切捨てのため内訳チェック欄に最大数百万円、賃貸事業損益(F-I)と掲載損益に最大1百万円の差が系統的に発生(JRE-ALL行参照) | Y74: ○（通期保有） | Z74: 年換算可 | AA74: 百万円単位（下3桁は概数）
A75: JRE-002 | B75: JRE | C75: 2026年3月期（第49期） | D75: 6 | E75: 開示（物件別・費用内訳含む・百万円単位） | F75: 247000 | I75: 93000 | J75: 16000 | K75: 16000 | L75: 24000 | M75: 0 | N75: 3000 | O75: 32000 | P75: 0 | Q75: =IF($A1174="","",IF(OR(F1174="",I1174=""),"",F1174-I1174)) -> 154000 | R75: =IF($A1174="","",IF(Q1174="","",Q1174+IF(O1174="",0,O1174))) | S75: 2000 | T75: =IF($A1174="","",IF(R1174="","",R1174-IF(S1174="",0,S1174))) | U75: =IF($A1174="","",IF(I1174="","",I1174-SUM(J1174:P1174))) -> 2000 | V75: JRE 2026年3月期(第49期)決算短信(2026/5/15公表) ②不動産等関連資産の損益状況 | W75: 確認済 | X75: 百万円単位開示×1000で収録(下3桁は概数)。各科目は百万円未満切捨てのため内訳チェック欄に最大数百万円、賃貸事業損益(F-I)と掲載損益に最大1百万円の差が系統的に発生(JRE-ALL行参照) | Y75: ○（通期保有） | Z75: 年換算可 | AA75: 百万円単位（下3桁は概数）
A76: JRE-003 | B76: JRE | C76: 2026年3月期（第49期） | D76: 6 | E76: 開示（物件別・費用内訳含む・百万円単位） | F76: 158000 | I76: 46000 | J76: 1000 | K76: 0 | L76: 21000 | M76: 0 | N76: 3000 | O76: 20000 | P76: 0 | Q76: =IF($A1175="","",IF(OR(F1175="",I1175=""),"",F1175-I1175)) -> 112000 | R76: =IF($A1175="","",IF(Q1175="","",Q1175+IF(O1175="",0,O1175))) | S76: 25000 | T76: =IF($A1175="","",IF(R1175="","",R1175-IF(S1175="",0,S1175))) | U76: =IF($A1175="","",IF(I1175="","",I1175-SUM(J1175:P1175))) -> 1000 | V76: JRE 2026年3月期(第49期)決算短信(2026/5/15公表) ②不動産等関連資産の損益状況 | W76: 確認済 | X76: 百万円単位開示×1000で収録(下3桁は概数)。各科目は百万円未満切捨てのため内訳チェック欄に最大数百万円、賃貸事業損益(F-I)と掲載損益に最大1百万円の差が系統的に発生(JRE-ALL行参照) | Y76: ○（通期保有） | Z76: 年換算可 | AA76: 百万円単位（下3桁は概数）
A77: JRE-004 | B77: JRE | C77: 2026年3月期（第49期） | D77: 6 | E77: 開示（物件別・費用内訳含む・百万円単位） | F77: 475000 | I77: 301000 | J77: 69000 | K77: 51000 | L77: 69000 | M77: 0 | N77: 8000 | O77: 101000 | P77: 0 | Q77: =IF($A1176="","",IF(OR(F1176="",I1176=""),"",F1176-I1176)) -> 174000 | R77: =IF($A1176="","",IF(Q1176="","",Q1176+IF(O1176="",0,O1176))) | S77: 38000 | T77: =IF($A1176="","",IF(R1176="","",R1176-IF(S1176="",0,S1176))) | U77: =IF($A1176="","",IF(I1176="","",I1176-SUM(J1176:P1176))) -> 3000 | V77: JRE 2026年3月期(第49期)決算短信(2026/5/15公表) ②不動産等関連資産の損益状況 | W77: 確認済 | X77: 百万円単位開示×1000で収録(下3桁は概数)。各科目は百万円未満切捨てのため内訳チェック欄に最大数百万円、賃貸事業損益(F-I)と掲載損益に最大1百万円の差が系統的に発生(JRE-ALL行参照) | Y77: ○（通期保有） | Z77: 年換算可 | AA77: 百万円単位（下3桁は概数）
A78: JRE-005 | B78: JRE | C78: 2026年3月期（第49期） | D78: 6 | E78: 開示（物件別・費用内訳含む・百万円単位） | F78: 186000 | I78: 92000 | J78: 9000 | K78: 12000 | L78: 34000 | M78: 0 | N78: 4000 | O78: 31000 | P78: 0 | Q78: =IF($A1177="","",IF(OR(F1177="",I1177=""),"",F1177-I1177)) -> -73000 | R78: =IF($A1177="","",IF(Q1177="","",Q1177+IF(O1177="",0,O1177))) | S78: 2000 | T78: =IF($A1177="","",IF(R1177="","",R1177-IF(S1177="",0,S1177))) | U78: =IF($A1177="","",IF(I1177="","",I1177-SUM(J1177:P1177))) -> 2000 | V78: JRE 2026年3月期(第49期)決算短信(2026/5/15公表) ②不動産等関連資産の損益状況 | W78: 確認済 | X78: 百万円単位開示×1000で収録(下3桁は概数)。各科目は百万円未満切捨てのため内訳チェック欄に最大数百万円、賃貸事業損益(F-I)と掲載損益に最大1百万円の差が系統的に発生(JRE-ALL行参照) | Y78: ○（通期保有） | Z78: 年換算可 | AA78: 百万円単位（下3桁は概数）
A79: JRE-006 | B79: JRE | C79: 2026年3月期（第49期） | D79: 6 | E79: 開示（物件別・費用内訳含む・百万円単位） | F79: 530000 | I79: 263000 | J79: 62000 | K79: 29000 | L79: 60000 | M79: 0 | N79: 44000 | O79: 64000 | P79: 0 | Q79: =IF($A1178="","",IF(OR(F1178="",I1178=""),"",F1178-I1178)) -> 95000 | R79: =IF($A1178="","",IF(Q1178="","",Q1178+IF(O1178="",0,O1178))) | S79: 239000 | T79: =IF($A1178="","",IF(R1178="","",R1178-IF(S1178="",0,S1178))) | U79: =IF($A1178="","",IF(I1178="","",I1178-SUM(J1178:P1178))) -> 4000 | V79: JRE 2026年3月期(第49期)決算短信(2026/5/15公表) ②不動産等関連資産の損益状況 | W79: 確認済 | X79: 百万円単位開示×1000で収録(下3桁は概数)。各科目は百万円未満切捨てのため内訳チェック欄に最大数百万円、賃貸事業損益(F-I)と掲載損益に最大1百万円の差が系統的に発生(JRE-ALL行参照) | Y79: ○（通期保有） | Z79: 年換算可 | AA79: 百万円単位（下3桁は概数）
A80: JRE-007 | B80: JRE | C80: 2026年3月期（第49期） | D80: 6 | E80: 開示（物件別・費用内訳含む・百万円単位） | F80: 997000 | I80: 455000 | J80: 58000 | K80: 57000 | L80: 173000 | M80: 0 | N80: 68000 | O80: 94000 | P80: 2000 | Q80: =IF($A1179="","",IF(OR(F1179="",I1179=""),"",F1179-I1179)) -> -341000 | R80: =IF($A1179="","",IF(Q1179="","",Q1179+IF(O1179="",0,O1179))) | S80: 127000 | T80: =IF($A1179="","",IF(R1179="","",R1179-IF(S1179="",0,S1179))) | U80: =IF($A1179="","",IF(I1179="","",I1179-SUM(J1179:P1179))) -> 3000 | V80: JRE 2026年3月期(第49期)決算短信(2026/5/15公表) ②不動産等関連資産の損益状況 | W80: 確認済 | X80: 百万円単位開示×1000で収録(下3桁は概数)。各科目は百万円未満切捨てのため内訳チェック欄に最大数百万円、賃貸事業損益(F-I)と掲載損益に最大1百万円の差が系統的に発生(JRE-ALL行参照) | Y80: ○（通期保有） | Z80: 年換算可 | AA80: 百万円単位（下3桁は概数）
A81: JRE-008 | B81: JRE | C81: 2026年3月期（第49期） | D81: 6 | E81: 開示（物件別・費用内訳含む・百万円単位） | F81: 162000 | I81: 66000 | J81: 0 | K81: 0 | L81: 16000 | M81: 0 | N81: 14000 | O81: 35000 | P81: 0 | Q81: =IF($A1180="","",IF(OR(F1180="",I1180=""),"",F1180-I1180)) -> 96000 | R81: =IF($A1180="","",IF(Q1180="","",Q1180+IF(O1180="",0,O1180))) | S81: 0 | T81: =IF($A1180="","",IF(R1180="","",R1180-IF(S1180="",0,S1180))) | U81: =IF($A1180="","",IF(I1180="","",I1180-SUM(J1180:P1180))) -> 1000 | V81: JRE 2026年3月期(第49期)決算短信(2026/5/15公表) ②不動産等関連資産の損益状況 | W81: 確認済 | X81: 百万円単位開示×1000で収録(下3桁は概数)。各科目は百万円未満切捨てのため内訳チェック欄に最大数百万円、賃貸事業損益(F-I)と掲載損益に最大1百万円の差が系統的に発生(JRE-ALL行参照) | Y81: ○（通期保有） | Z81: 年換算可 | AA81: 百万円単位（下3桁は概数）
A82: JRE-009 | B82: JRE | C82: 2026年3月期（第49期） | D82: 6 | E82: 開示（物件別・費用内訳含む・百万円単位） | F82: 36000 | I82: 21000 | J82: 4000 | K82: 1000 | L82: 3000 | M82: 0 | N82: 0 | O82: 11000 | P82: 0 | Q82: =IF($A1181="","",IF(OR(F1181="",I1181=""),"",F1181-I1181)) -> 15000 | R82: =IF($A1181="","",IF(Q1181="","",Q1181+IF(O1181="",0,O1181))) | S82: 0 | T82: =IF($A1181="","",IF(R1181="","",R1181-IF(S1181="",0,S1181))) | U82: =IF($A1181="","",IF(I1181="","",I1181-SUM(J1181:P1181))) -> 2000 | V82: JRE 2026年3月期(第49期)決算短信(2026/5/15公表) ②不動産等関連資産の損益状況 | W82: 確認済 | X82: 百万円単位開示×1000で収録(下3桁は概数)。各科目は百万円未満切捨てのため内訳チェック欄に最大数百万円、賃貸事業損益(F-I)と掲載損益に最大1百万円の差が系統的に発生(JRE-ALL行参照) | Y82: ○（通期保有） | Z82: 年換算可 | AA82: 百万円単位・低精度（収入50百万円未満で丸め影響大）
A83: JRE-010 | B83: JRE | C83: 2026年3月期（第49期） | D83: 6 | E83: 開示（物件別・費用内訳含む・百万円単位） | F83: 647000 | I83: 532000 | J83: 131000 | K83: 48000 | L83: 132000 | M83: 1000 | N83: 162000 | O83: 56000 | P83: 0 | Q83: =IF($A1182="","",IF(OR(F1182="",I1182=""),"",F1182-I1182)) -> 115000 | R83: =IF($A1182="","",IF(Q1182="","",Q1182+IF(O1182="",0,O1182))) | S83: 390000 | T83: =IF($A1182="","",IF(R1182="","",R1182-IF(S1182="",0,S1182))) | U83: =IF($A1182="","",IF(I1182="","",I1182-SUM(J1182:P1182))) -> 2000 | V83: JRE 2026年3月期(第49期)決算短信(2026/5/15公表) ②不動産等関連資産の損益状況 | W83: 確認済 | X83: 百万円単位開示×1000で収録(下3桁は概数)。各科目は百万円未満切捨てのため内訳チェック欄に最大数百万円、賃貸事業損益(F-I)と掲載損益に最大1百万円の差が系統的に発生(JRE-ALL行参照) | Y83: ○（通期保有） | Z83: 年換算可 | AA83: 百万円単位（下3桁は概数）
A84: JRE-011 | B84: JRE | C84: 2026年3月期（第49期） | D84: 6 | E84: 開示（物件別・費用内訳含む・百万円単位） | F84: 290000 | I84: 142000 | J84: 28000 | K84: 20000 | L84: 53000 | M84: 0 | N84: 17000 | O84: 19000 | P84: 1000 | Q84: =IF($A1183="","",IF(OR(F1183="",I1183=""),"",F1183-I1183)) -> 513000 | R84: =IF($A1183="","",IF(Q1183="","",Q1183+IF(O1183="",0,O1183))) | S84: 54000 | T84: =IF($A1183="","",IF(R1183="","",R1183-IF(S1183="",0,S1183))) | U84: =IF($A1183="","",IF(I1183="","",I1183-SUM(J1183:P1183))) -> 4000 | V84: JRE 2026年3月期(第49期)決算短信(2026/5/15公表) ②不動産等関連資産の損益状況 | W84: 確認済 | X84: 百万円単位開示×1000で収録(下3桁は概数)。各科目は百万円未満切捨てのため内訳チェック欄に最大数百万円、賃貸事業損益(F-I)と掲載損益に最大1百万円の差が系統的に発生(JRE-ALL行参照) | Y84: ○（通期保有） | Z84: 年換算可 | AA84: 百万円単位（下3桁は概数）
A85: JRE-012 | B85: JRE | C85: 2026年3月期（第49期） | D85: 6 | E85: 開示（物件別・費用内訳含む・百万円単位） | F85: 422000 | I85: 176000 | J85: 26000 | K85: 20000 | L85: 45000 | M85: 0 | N85: 32000 | O85: 50000 | P85: 0 | Q85: =IF($A1184="","",IF(OR(F1184="",I1184=""),"",F1184-I1184)) -> 211000 | R85: =IF($A1184="","",IF(Q1184="","",Q1184+IF(O1184="",0,O1184))) | S85: 6000 | T85: =IF($A1184="","",IF(R1184="","",R1184-IF(S1184="",0,S1184))) | U85: =IF($A1184="","",IF(I1184="","",I1184-SUM(J1184:P1184))) -> 3000 | V85: JRE 2026年3月期(第49期)決算短信(2026/5/15公表) ②不動産等関連資産の損益状況 | W85: 確認済 | X85: 百万円単位開示×1000で収録(下3桁は概数)。各科目は百万円未満切捨てのため内訳チェック欄に最大数百万円、賃貸事業損益(F-I)と掲載損益に最大1百万円の差が系統的に発生(JRE-ALL行参照) | Y85: ○（通期保有） | Z85: 年換算可 | AA85: 百万円単位（下3桁は概数）
... A104: JRE-031 | B104: JRE | C104: 2026年3月期（第49期） | D104: 6 | E104: 開示（物件別・費用内訳含む・百万円単位） | F104: 249000 | I104: 119000 | J104: 24000 | K104: 15000 | L104: 23000 | M104: 0 | N104: 10000 | O104: 44000 | P104: 0 | Q104: =IF($A1203="","",IF(OR(F1203="",I1203=""),"",F1203-I1203)) -> -67000 | R104: =IF($A1203="","",IF(Q1203="","",Q1203+IF(O1203="",0,O1203))) | S104: 62000 | T104: =IF($A1203="","",IF(R1203="","",R1203-IF(S1203="",0,S1203))) | U104: =IF($A1203="","",IF(I1203="","",I1203-SUM(J1203:P1203))) -> 3000 | V104: JRE 2026年3月期(第49期)決算短信(2026/5/15公表) ②不動産等関連資産の損益状況 | W104: 確認済 | X104: 百万円単位開示×1000で収録(下3桁は概数)。各科目は百万円未満切捨てのため内訳チェック欄に最大数百万円、賃貸事業損益(F-I)と掲載損益に最大1百万円の差が系統的に発生(JRE-ALL行参照) | Y104: ○（通期保有） | Z104: 年換算可 | AA104: 百万円単位（下3桁は概数）
A105: JRE-032 | B105: JRE | C105: 2026年3月期（第49期） | D105: 6 | E105: 一部開示（収益・費用計・損益のみ・百万円単位） | F105: 1570000 | I105: 1363000 | Q105: =IF($A1204="","",IF(OR(F1204="",I1204=""),"",F1204-I1204)) -> -820000 | R105: =IF($A1204="","",IF(Q1204="","",Q1204+IF(O1204="",0,O1204))) | S105: 690000 | T105: =IF($A1204="","",IF(R1204="","",R1204-IF(S1204="",0,S1204))) | U105: =IF($A1204="","",IF(I1204="","",I1204-SUM(J1204:P1204))) -> 1363000 | V105: JRE 2026年3月期(第49期)決算短信(2026/5/15公表) ②不動産等関連資産の損益状況 | W105: 確認済 | X105: 費用内訳非開示のため内訳チェック欄には費用全額が残る(非開示由来・要確認事項ではない)。掲載損益206百万円。百万円単位開示×1000で収録(下3桁は概数)。各科目は百万円未満切捨てのため内訳チェック欄に最大数百万円、賃貸事業損益(F-I)と掲載損益に最大1百万円の差が系統的に発生(JRE-ALL行参照) | Y105: ○（通期保有） | Z105: 年換算可 | AA105: 百万円単位（下3桁は概数）
A106: JRE-033 | B106: JRE | C106: 2026年3月期（第49期） | D106: 6 | E106: 開示（物件別・費用内訳含む・百万円単位） | F106: 200000 | I106: 93000 | J106: 16000 | K106: 11000 | L106: 32000 | M106: 0 | N106: 5000 | O106: 28000 | P106: 0 | Q106: =IF($A1205="","",IF(OR(F1205="",I1205=""),"",F1205-I1205)) -> 107000 | R106: =IF($A1205="","",IF(Q1205="","",Q1205+IF(O1205="",0,O1205))) | S106: 1000 | T106: =IF($A1205="","",IF(R1205="","",R1205-IF(S1205="",0,S1205))) | U106: =IF($A1205="","",IF(I1205="","",I1205-SUM(J1205:P1205))) -> 1000 | V106: JRE 2026年3月期(第49期)決算短信(2026/5/15公表) ②不動産等関連資産の損益状況 | W106: 確認済 | X106: 百万円単位開示×1000で収録(下3桁は概数)。各科目は百万円未満切捨てのため内訳チェック欄に最大数百万円、賃貸事業損益(F-I)と掲載損益に最大1百万円の差が系統的に発生(JRE-ALL行参照) | Y106: ○（通期保有） | Z106: 年換算可 | AA106: 百万円単位（下3桁は概数）
A107: JRE-034 | B107: JRE | C107: 2026年3月期（第49期） | D107: 6 | E107: 開示（物件別・費用内訳含む・百万円単位） | F107: 599000 | I107: 271000 | J107: 45000 | K107: 32000 | L107: 58000 | M107: 0 | N107: 1000 | O107: 132000 | P107: 0 | Q107: =IF($A1206="","",IF(OR(F1206="",I1206=""),"",F1206-I1206)) -> 328000 | R107: =IF($A1206="","",IF(Q1206="","",Q1206+IF(O1206="",0,O1206))) | S107: 0 | T107: =IF($A1206="","",IF(R1206="","",R1206-IF(S1206="",0,S1206))) | U107: =IF($A1206="","",IF(I1206="","",I1206-SUM(J1206:P1206))) -> 3000 | V107: JRE 2026年3月期(第49期)決算短信(2026/5/15公表) ②不動産等関連資産の損益状況 | W107: 確認済 | X107: 百万円単位開示×1000で収録(下3桁は概数)。各科目は百万円未満切捨てのため内訳チェック欄に最大数百万円、賃貸事業損益(F-I)と掲載損益に最大1百万円の差が系統的に発生(JRE-ALL行参照) | Y107: ○（通期保有） | Z107: 年換算可 | AA107: 百万円単位（下3桁は概数）
A108: JRE-035 | B108: JRE | C108: 2026年3月期（第49期） | D108: 6 | E108: 開示（物件別・費用内訳含む・百万円単位） | F108: 352000 | I108: 135000 | J108: 26000 | K108: 18000 | L108: 30000 | M108: 0 | N108: 1000 | O108: 58000 | P108: 0 | Q108: =IF($A1207="","",IF(OR(F1207="",I1207=""),"",F1207-I1207)) -> 217000 | R108: =IF($A1207="","",IF(Q1207="","",Q1207+IF(O1207="",0,O1207))) | S108: 5000 | T108: =IF($A1207="","",IF(R1207="","",R1207-IF(S1207="",0,S1207))) | U108: =IF($A1207="","",IF(I1207="","",I1207-SUM(J1207:P1207))) -> 2000 | V108: JRE 2026年3月期(第49期)決算短信(2026/5/15公表) ②不動産等関連資産の損益状況 | W108: 確認済 | X108: 百万円単位開示×1000で収録(下3桁は概数)。各科目は百万円未満切捨てのため内訳チェック欄に最大数百万円、賃貸事業損益(F-I)と掲載損益に最大1百万円の差が系統的に発生(JRE-ALL行参照) | Y108: ○（通期保有） | Z108: 年換算可 | AA108: 百万円単位（下3桁は概数）
A109: JRE-036 | B109: JRE | C109: 2026年3月期（第49期） | D109: 6 | E109: 開示（物件別・費用内訳含む・百万円単位） | F109: 185000 | I109: 63000 | J109: 11000 | K109: 8000 | L109: 26000 | M109: 0 | N109: 3000 | O109: 13000 | P109: 0 | Q109: =IF($A1208="","",IF(OR(F1208="",I1208=""),"",F1208-I1208)) -> 139000 | R109: =IF($A1208="","",IF(Q1208="","",Q1208+IF(O1208="",0,O1208))) | S109: 0 | T109: =IF($A1208="","",IF(R1208="","",R1208-IF(S1208="",0,S1208))) | U109: =IF($A1208="","",IF(I1208="","",I1208-SUM(J1208:P1208))) -> 2000 | V109: JRE 2026年3月期(第49期)決算短信(2026/5/15公表) ②不動産等関連資産の損益状況 | W109: 確認済 | X109: 百万円単位開示×1000で収録(下3桁は概数)。各科目は百万円未満切捨てのため内訳チェック欄に最大数百万円、賃貸事業損益(F-I)と掲載損益に最大1百万円の差が系統的に発生(JRE-ALL行参照) | Y109: ○（通期保有） | Z109: 年換算可 | AA109: 百万円単位（下3桁は概数）
A110: JRE-037 | B110: JRE | C110: 2026年3月期（第49期） | D110: 6 | E110: 開示（物件別・費用内訳含む・百万円単位） | F110: 336000 | I110: 207000 | J110: 29000 | K110: 26000 | L110: 80000 | M110: 0 | N110: 13000 | O110: 57000 | P110: 0 | Q110: =IF($A1209="","",IF(OR(F1209="",I1209=""),"",F1209-I1209)) -> -40000 | R110: =IF($A1209="","",IF(Q1209="","",Q1209+IF(O1209="",0,O1209))) | S110: 9000 | T110: =IF($A1209="","",IF(R1209="","",R1209-IF(S1209="",0,S1209))) | U110: =IF($A1209="","",IF(I1209="","",I1209-SUM(J1209:P1209))) -> 2000 | V110: JRE 2026年3月期(第49期)決算短信(2026/5/15公表) ②不動産等関連資産の損益状況 | W110: 確認済 | X110: 百万円単位開示×1000で収録(下3桁は概数)。各科目は百万円未満切捨てのため内訳チェック欄に最大数百万円、賃貸事業損益(F-I)と掲載損益に最大1百万円の差が系統的に発生(JRE-ALL行参照) | Y110: ○（通期保有） | Z110: 年換算可 | AA110: 百万円単位（下3桁は概数）
A111: JRE-038 | B111: JRE | C111: 2026年3月期（第49期） | D111: 6 | E111: 開示（物件別・費用内訳含む・百万円単位） | F111: 600000 | I111: 120000 | J111: 0 | K111: 0 | L111: 120000 | M111: 0 | N111: 0 | O111: 0 | P111: 0 | Q111: =IF($A1210="","",IF(OR(F1210="",I1210=""),"",F1210-I1210)) -> 480000 | R111: =IF($A1210="","",IF(Q1210="","",Q1210+IF(O1210="",0,O1210))) | S111: 0 | T111: =IF($A1210="","",IF(R1210="","",R1210-IF(S1210="",0,S1210))) | U111: =IF($A1210="","",IF(I1210="","",I1210-SUM(J1210:P1210))) -> 0 | V111: JRE 2026年3月期(第49期)決算短信(2026/5/15公表) ②不動産等関連資産の損益状況 | W111: 確認済 | X111: 百万円単位開示×1000で収録(下3桁は概数)。各科目は百万円未満切捨てのため内訳チェック欄に最大数百万円、賃貸事業損益(F-I)と掲載損益に最大1百万円の差が系統的に発生(JRE-ALL行参照) | Y111: ○（通期保有） | Z111: 年換算可 | AA111: 百万円単位（下3桁は概数）
A112: JRE-039 | B112: JRE | C112: 2026年3月期（第49期） | D112: 6 | E112: 開示（物件別・費用内訳含む・百万円単位） | F112: 485000 | I112: 245000 | J112: 55000 | K112: 28000 | L112: 43000 | M112: 2000 | N112: 3000 | O112: 112000 | P112: 0 | Q112: =IF($A1211="","",IF(OR(F1211="",I1211=""),"",F1211-I1211)) -> 784000 | R112: =IF($A1211="","",IF(Q1211="","",Q1211+IF(O1211="",0,O1211))) | S112: 7000 | T112: =IF($A1211="","",IF(R1211="","",R1211-IF(S1211="",0,S1211))) | U112: =IF($A1211="","",IF(I1211="","",I1211-SUM(J1211:P1211))) -> 2000 | V112: JRE 2026年3月期(第49期)決算短信(2026/5/15公表) ②不動産等関連資産の損益状況 | W112: 確認済 | X112: 百万円単位開示×1000で収録(下3桁は概数)。各科目は百万円未満切捨てのため内訳チェック欄に最大数百万円、賃貸事業損益(F-I)と掲載損益に最大1百万円の差が系統的に発生(JRE-ALL行参照) | Y112: ○（通期保有） | Z112: 年換算可 | AA112: 百万円単位（下3桁は概数）
A113: JRE-040 | B113: JRE | C113: 2026年3月期（第49期） | D113: 6 | E113: 開示（物件別・費用内訳含む・百万円単位） | F113: 714000 | I113: 300000 | J113: 69000 | K113: 48000 | L113: 41000 | M113: 1000 | N113: 21000 | O113: 118000 | P113: 0 | Q113: =IF($A1212="","",IF(OR(F1212="",I1212=""),"",F1212-I1212)) -> 414000 | R113: =IF($A1212="","",IF(Q1212="","",Q1212+IF(O1212="",0,O1212))) | S113: 6000 | T113: =IF($A1212="","",IF(R1212="","",R1212-IF(S1212="",0,S1212))) | U113: =IF($A1212="","",IF(I1212="","",I1212-SUM(J1212:P1212))) -> 2000 | V113: JRE 2026年3月期(第49期)決算短信(2026/5/15公表) ②不動産等関連資産の損益状況 | W113: 確認済 | X113: 百万円単位開示×1000で収録(下3桁は概数)。各科目は百万円未満切捨てのため内訳チェック欄に最大数百万円、賃貸事業損益(F-I)と掲載損益に最大1百万円の差が系統的に発生(JRE-ALL行参照) | Y113: ○（通期保有） | Z113: 年換算可 | AA113: 百万円単位（下3桁は概数）
A114: JRE-041 | B114: JRE | C114: 2026年3月期（第49期） | D114: 6 | E114: 開示（物件別・費用内訳含む・百万円単位） | F114: 818000 | I114: 409000 | J114: 70000 | K114: 67000 | L114: 67000 | M114: 1000 | N114: 15000 | O114: 186000 | P114: 0 | Q114: =IF($A1213="","",IF(OR(F1213="",I1213=""),"",F1213-I1213)) -> 409000 | R114: =IF($A1213="","",IF(Q1213="","",Q1213+IF(O1213="",0,O1213))) | S114: 44000 | T114: =IF($A1213="","",IF(R1213="","",R1213-IF(S1213="",0,S1213))) | U114: =IF($A1213="","",IF(I1213="","",I1213-SUM(J1213:P1213))) -> 3000 | V114: JRE 2026年3月期(第49期)決算短信(2026/5/15公表) ②不動産等関連資産の損益状況 | W114: 確認済 | X114: 百万円単位開示×1000で収録(下3桁は概数)。各科目は百万円未満切捨てのため内訳チェック欄に最大数百万円、賃貸事業損益(F-I)と掲載損益に最大1百万円の差が系統的に発生(JRE-ALL行参照) | Y114: ○（通期保有） | Z114: 年換算可 | AA114: 百万円単位（下3桁は概数）
A115: JRE-042 | B115: JRE | C115: 2026年3月期（第49期） | D115: 6 | E115: 開示（物件別・費用内訳含む・百万円単位） | F115: 625000 | G115: 14911595 | H115: 14645 | I115: 396000 | J115: 69000 | K115: 49000 | L115: 47000 | M115: 1000 | N115: 59000 | O115: 169000 | P115: 0 | Q115: =IF($A1214="","",IF(OR(F1214="",I1214=""),"",F1214-I1214)) -> 229000 | R115: =IF($A1214="","",IF(Q1214="","",Q1214+IF(O1214="",0,O1214))) | S115: 67000 | T115: =IF($A1214="","",IF(R1214="","",R1214-IF(S1214="",0,S1214))) | U115: =IF($A1214="","",IF(I1214="","",I1214-SUM(J1214:P1214))) -> 2000 | V115: JRE 2026年3月期(第49期)決算短信(2026/5/15公表) ②不動産等関連資産の損益状況 | W115: 確認済 | X115: 百万円単位開示×1000で収録(下3桁は概数)。各科目は百万円未満切捨てのため内訳チェック欄に最大数百万円、賃貸事業損益(F-I)と掲載損益に最大1百万円の差が系統的に発生(JRE-ALL行参照) | Y115: ○（通期保有） | Z115: 年換算可 | AA115: 百万円単位（下3桁は概数）
A116: JRE-043 | B116: JRE | C116: 2026年3月期（第49期） | D116: 6 | E116: 開示（物件別・費用内訳含む・百万円単位） | F116: 199000 | G116: 2851394 | H116: 0 | I116: 87000 | J116: 14000 | K116: 17000 | L116: 17000 | M116: 0 | N116: 6000 | O116: 31000 | P116: 0 | Q116: =IF($A1215="","",IF(OR(F1215="",I1215=""),"",F1215-I1215)) -> 112000 | R116: =IF($A1215="","",IF(Q1215="","",Q1215+IF(O1215="",0,O1215))) | S116: 16000 | T116: =IF($A1215="","",IF(R1215="","",R1215-IF(S1215="",0,S1215))) | U116: =IF($A1215="","",IF(I1215="","",I1215-SUM(J1215:P1215))) -> 2000 | V116: JRE 2026年3月期(第49期)決算短信(2026/5/15公表) ②不動産等関連資産の損益状況 | W116: 確認済 | X116: 百万円単位開示×1000で収録(下3桁は概数)。各科目は百万円未満切捨てのため内訳チェック欄に最大数百万円、賃貸事業損益(F-I)と掲載損益に最大1百万円の差が系統的に発生(JRE-ALL行参照) | Y116: ○（通期保有） | Z116: 年換算可 | AA116: 百万円単位（下3桁は概数）
A117: JRE-044 | B117: JRE | C117: 2026年3月期（第49期） | D117: 6 | E117: 開示（物件別・費用内訳含む・百万円単位） | F117: 735000 | G117: 1351486 | H117: 0 | I117: 452000 | J117: 57000 | K117: 44000 | L117: 25000 | M117: 0 | N117: 17000 | O117: 203000 | P117: 103000 | Q117: =IF($A1216="","",IF(OR(F1216="",I1216=""),"",F1216-I1216)) -> 283000 | R117: =IF($A1216="","",IF(Q1216="","",Q1216+IF(O1216="",0,O1216))) | S117: 138000 | T117: =IF($A1216="","",IF(R1216="","",R1216-IF(S1216="",0,S1216))) | U117: =IF($A1216="","",IF(I1216="","",I1216-SUM(J1216:P1216))) -> 3000 | V117: JRE 2026年3月期(第49期)決算短信(2026/5/15公表) ②不動産等関連資産の損益状況 | W117: 確認済 | X117: 百万円単位開示×1000で収録(下3桁は概数)。各科目は百万円未満切捨てのため内訳チェック欄に最大数百万円、賃貸事業損益(F-I)と掲載損益に最大1百万円の差が系統的に発生(JRE-ALL行参照) | Y117: ○（通期保有） | Z117: 年換算可 | AA117: 百万円単位（下3桁は概数）
A118: JRE-045 | B118: JRE | C118: 2026年3月期（第49期） | D118: 6 | E118: 開示（物件別・費用内訳含む・百万円単位） | F118: 244000 | G118: 660481 | H118: 80291 | I118: 128000 | J118: 29000 | K118: 18000 | L118: 28000 | M118: 0 | N118: 0 | O118: 51000 | P118: 0 | Q118: =IF($A1217="","",IF(OR(F1217="",I1217=""),"",F1217-I1217)) -> 116000 | R118: =IF($A1217="","",IF(Q1217="","",Q1217+IF(O1217="",0,O1217))) | S118: 6000 | T118: =IF($A1217="","",IF(R1217="","",R1217-IF(S1217="",0,S1217))) | U118: =IF($A1217="","",IF(I1217="","",I1217-SUM(J1217:P1217))) -> 2000 | V118: JRE 2026年3月期(第49期)決算短信(2026/5/15公表) ②不動産等関連資産の損益状況 | W118: 確認済 | X118: 百万円単位開示×1000で収録(下3桁は概数)。各科目は百万円未満切捨てのため内訳チェック欄に最大数百万円、賃貸事業損益(F-I)と掲載損益に最大1百万円の差が系統的に発生(JRE-ALL行参照) | Y118: ○（通期保有） | Z118: 年換算可 | AA118: 百万円単位（下3桁は概数）
A119: JRE-046 | B119: JRE | C119: 2026年3月期（第49期） | D119: 6 | E119: 開示（物件別・費用内訳含む・百万円単位） | F119: 499000 | G119: 851352 | H119: 60419 | I119: 280000 | J119: 154000 | K119: 0 | L119: 61000 | M119: 1000 | N119: 13000 | O119: 50000 | P119: 0 | Q119: =IF($A1218="","",IF(OR(F1218="",I1218=""),"",F1218-I1218)) -> 219000 | R119: =IF($A1218="","",IF(Q1218="","",Q1218+IF(O1218="",0,O1218))) | S119: 0 | T119: =IF($A1218="","",IF(R1218="","",R1218-IF(S1218="",0,S1218))) | U119: =IF($A1218="","",IF(I1218="","",I1218-SUM(J1218:P1218))) -> 1000 | V119: JRE 2026年3月期(第49期)決算短信(2026/5/15公表) ②不動産等関連資産の損益状況 | W119: 確認済 | X119: 百万円単位開示×1000で収録(下3桁は概数)。各科目は百万円未満切捨てのため内訳チェック欄に最大数百万円、賃貸事業損益(F-I)と掲載損益に最大1百万円の差が系統的に発生(JRE-ALL行参照) | Y119: ○（通期保有） | Z119: 年換算可 | AA119: 百万円単位（下3桁は概数）
A120: JRE-047 | B120: JRE | C120: 2026年3月期（第49期） | D120: 6 | E120: 開示（物件別・費用内訳含む・百万円単位） | F120: 74000 | G120: 1012320 | H120: 0 | I120: 36000 | J120: 8000 | K120: 6000 | L120: 6000 | M120: 0 | N120: 6000 | O120: 9000 | P120: 0 | Q120: =IF($A1219="","",IF(OR(F1219="",I1219=""),"",F1219-I1219)) -> 38000 | R120: =IF($A1219="","",IF(Q1219="","",Q1219+IF(O1219="",0,O1219))) | S120: 14000 | T120: =IF($A1219="","",IF(R1219="","",R1219-IF(S1219="",0,S1219))) | U120: =IF($A1219="","",IF(I1219="","",I1219-SUM(J1219:P1219))) -> 1000 | V120: JRE 2026年3月期(第49期)決算短信(2026/5/15公表) ②不動産等関連資産の損益状況 | W120: 確認済 | X120: 百万円単位開示×1000で収録(下3桁は概数)。各科目は百万円未満切捨てのため内訳チェック欄に最大数百万円、賃貸事業損益(F-I)と掲載損益に最大1百万円の差が系統的に発生(JRE-ALL行参照) | Y120: ○（通期保有） | Z120: 年換算可 | AA120: 百万円単位（下3桁は概数）
A121: JRE-048 | B121: JRE | C121: 2026年3月期（第49期） | D121: 6 | E121: 開示（物件別・費用内訳含む・百万円単位） | F121: 207000 | G121: 464509 | H121: 31400 | I121: 86000 | J121: 17000 | K121: 15000 | L121: 18000 | M121: 0 | N121: 8000 | O121: 25000 | P121: 0 | Q121: =IF($A1220="","",IF(OR(F1220="",I1220=""),"",F1220-I1220)) -> 121000 | R121: =IF($A1220="","",IF(Q1220="","",Q1220+IF(O1220="",0,O1220))) | S121: 9000 | T121: =IF($A1220="","",IF(R1220="","",R1220-IF(S1220="",0,S1220))) | U121: =IF($A1220="","",IF(I1220="","",I1220-SUM(J1220:P1220))) -> 3000 | V121: JRE 2026年3月期(第49期)決算短信(2026/5/15公表) ②不動産等関連資産の損益状況 | W121: 確認済 | X121: 百万円単位開示×1000で収録(下3桁は概数)。各科目は百万円未満切捨てのため内訳チェック欄に最大数百万円、賃貸事業損益(F-I)と掲載損益に最大1百万円の差が系統的に発生(JRE-ALL行参照) | Y121: ○（通期保有） | Z121: 年換算可 | AA121: 百万円単位（下3桁は概数）
A122: JRE-049 | B122: JRE | C122: 2026年3月期（第49期） | D122: 6 | E122: 開示（物件別・費用内訳含む・百万円単位） | F122: 258000 | G122: 1426552 | H122: 0 | I122: 137000 | J122: 51000 | K122: 7000 | L122: 27000 | M122: 0 | N122: 8000 | O122: 41000 | P122: 0 | Q122: =IF($A1221="","",IF(OR(F1221="",I1221=""),"",F1221-I1221)) -> 121000 | R122: =IF($A1221="","",IF(Q1221="","",Q1221+IF(O1221="",0,O1221))) | S122: 3000 | T122: =IF($A1221="","",IF(R1221="","",R1221-IF(S1221="",0,S1221))) | U122: =IF($A1221="","",IF(I1221="","",I1221-SUM(J1221:P1221))) -> 3000 | V122: JRE 2026年3月期(第49期)決算短信(2026/5/15公表) ②不動産等関連資産の損益状況 | W122: 確認済 | X122: 百万円単位開示×1000で収録(下3桁は概数)。各科目は百万円未満切捨てのため内訳チェック欄に最大数百万円、賃貸事業損益(F-I)と掲載損益に最大1百万円の差が系統的に発生(JRE-ALL行参照) | Y122: ○（通期保有） | Z122: 年換算可 | AA122: 百万円単位（下3桁は概数）
A123: JRE-050 | B123: JRE | C123: 2026年3月期（第49期） | D123: 6 | E123: 開示（物件別・費用内訳含む・百万円単位） | F123: 144000 | G123: 486455 | H123: 23974 | I123: 59000 | J123: 15000 | K123: 9000 | L123: 10000 | M123: 0 | N123: 2000 | O123: 21000 | P123: 0 | Q123: =IF($A1222="","",IF(OR(F1222="",I1222=""),"",F1222-I1222)) -> 85000 | R123: =IF($A1222="","",IF(Q1222="","",Q1222+IF(O1222="",0,O1222))) | S123: 5000 | T123: =IF($A1222="","",IF(R1222="","",R1222-IF(S1222="",0,S1222))) | U123: =IF($A1222="","",IF(I1222="","",I1222-SUM(J1222:P1222))) -> 2000 | V123: JRE 2026年3月期(第49期)決算短信(2026/5/15公表) ②不動産等関連資産の損益状況 | W123: 確認済 | X123: 百万円単位開示×1000で収録(下3桁は概数)。各科目は百万円未満切捨てのため内訳チェック欄に最大数百万円、賃貸事業損益(F-I)と掲載損益に最大1百万円の差が系統的に発生(JRE-ALL行参照) | Y123: ○（通期保有） | Z123: 年換算可 | AA123: 百万円単位（下3桁は概数）
A124: JRE-051 | B124: JRE | C124: 2026年3月期（第49期） | D124: 6 | E124: 開示（物件別・費用内訳含む・百万円単位） | F124: 1292000 | G124: 105407 | H124: 430 | I124: 612000 | J124: 150000 | K124: 165000 | L124: 91000 | M124: 1000 | N124: 20000 | O124: 182000 | P124: 1000 | Q124: =IF($A1223="","",IF(OR(F1223="",I1223=""),"",F1223-I1223)) -> 680000 | R124: =IF($A1223="","",IF(Q1223="","",Q1223+IF(O1223="",0,O1223))) | S124: 40000 | T124: =IF($A1223="","",IF(R1223="","",R1223-IF(S1223="",0,S1223))) | U124: =IF($A1223="","",IF(I1223="","",I1223-SUM(J1223:P1223))) -> 2000 | V124: JRE 2026年3月期(第49期)決算短信(2026/5/15公表) ②不動産等関連資産の損益状況 | W124: 確認済 | X124: 百万円単位開示×1000で収録(下3桁は概数)。各科目は百万円未満切捨てのため内訳チェック欄に最大数百万円、賃貸事業損益(F-I)と掲載損益に最大1百万円の差が系統的に発生(JRE-ALL行参照) | Y124: ○（通期保有） | Z124: 年換算可 | AA124: 百万円単位（下3桁は概数）
A125: JRE-052 | B125: JRE | C125: 2026年3月期（第49期） | D125: 6 | E125: 開示（物件別・費用内訳含む・百万円単位） | F125: 1064000 | G125: 111234 | H125: 273 | I125: 776000 | J125: 218000 | K125: 103000 | L125: 132000 | M125: 3000 | N125: 32000 | O125: 279000 | P125: 7000 | Q125: =IF($A1224="","",IF(OR(F1224="",I1224=""),"",F1224-I1224)) -> 288000 | R125: =IF($A1224="","",IF(Q1224="","",Q1224+IF(O1224="",0,O1224))) | S125: 234000 | T125: =IF($A1224="","",IF(R1224="","",R1224-IF(S1224="",0,S1224))) | U125: =IF($A1224="","",IF(I1224="","",I1224-SUM(J1224:P1224))) -> 2000 | V125: JRE 2026年3月期(第49期)決算短信(2026/5/15公表) ②不動産等関連資産の損益状況 | W125: 確認済 | X125: 百万円単位開示×1000で収録(下3桁は概数)。各科目は百万円未満切捨てのため内訳チェック欄に最大数百万円、賃貸事業損益(F-I)と掲載損益に最大1百万円の差が系統的に発生(JRE-ALL行参照) | Y125: ○（通期保有） | Z125: 年換算可 | AA125: 百万円単位（下3桁は概数）
A126: JRE-053 | B126: JRE | C126: 2026年3月期（第49期） | D126: 6 | E126: 開示（物件別・費用内訳含む・百万円単位） | F126: 175000 | G126: 343806 | H126: 0 | I126: 74000 | J126: 21000 | K126: 3000 | L126: 15000 | M126: 0 | N126: 4000 | O126: 29000 | P126: 0 | Q126: =IF($A1225="","",IF(OR(F1225="",I1225=""),"",F1225-I1225)) -> 101000 | R126: =IF($A1225="","",IF(Q1225="","",Q1225+IF(O1225="",0,O1225))) | S126: 45000 | T126: =IF($A1225="","",IF(R1225="","",R1225-IF(S1225="",0,S1225))) | U126: =IF($A1225="","",IF(I1225="","",I1225-SUM(J1225:P1225))) -> 2000 | V126: JRE 2026年3月期(第49期)決算短信(2026/5/15公表) ②不動産等関連資産の損益状況 | W126: 確認済 | X126: 百万円単位開示×1000で収録(下3桁は概数)。各科目は百万円未満切捨てのため内訳チェック欄に最大数百万円、賃貸事業損益(F-I)と掲載損益に最大1百万円の差が系統的に発生(JRE-ALL行参照) | Y126: ○（通期保有） | Z126: 年換算可 | AA126: 百万円単位（下3桁は概数）
A127: JRE-054 | B127: JRE | C127: 2026年3月期（第49期） | D127: 6 | E127: 開示（物件別・費用内訳含む・百万円単位） | F127: 0 | G127: 9665001 | H127: 196788 | I127: 9000 | J127: 0 | K127: 0 | L127: 0 | M127: 0 | N127: 0 | O127: 8000 | P127: 0 | Q127: =IF($A1226="","",IF(OR(F1226="",I1226=""),"",F1226-I1226)) -> -9000 | R127: =IF($A1226="","",IF(Q1226="","",Q1226+IF(O1226="",0,O1226))) | S127: 0 | T127: =IF($A1226="","",IF(R1226="","",R1226-IF(S1226="",0,S1226))) | U127: =IF($A1226="","",IF(I1226="","",I1226-SUM(J1226:P1226))) -> 1000 | V127: JRE 2026年3月期(第49期)決算短信(2026/5/15公表) ②不動産等関連資産の損益状況 | W127: 確認済 | X127: 2026/3/25取得のため当期運用7日(収益0百万円・費用9百万円で損益マイナス)。百万円単位開示×1000で収録(下3桁は概数)。各科目は百万円未満切捨てのため内訳チェック欄に最大数百万円、賃貸事業損益(F-I)と掲載損益に最大1百万円の差が系統的に発生(JRE-ALL行参照) | Y127: ○（通期保有） | Z127: 年換算可 | AA127: 百万円単位（下3桁は概数）
A128: JRE-055 | B128: JRE | C128: 2026年3月期（第49期） | D128: 6 | E128: 開示（物件別・費用内訳含む・百万円単位） | F128: 404000 | I128: 162000 | J128: 31000 | K128: 52000 | L128: 26000 | M128: 0 | N128: 10000 | O128: 41000 | P128: 0 | Q128: =IF($A1227="","",IF(OR(F1227="",I1227=""),"",F1227-I1227)) -> 242000 | R128: =IF($A1227="","",IF(Q1227="","",Q1227+IF(O1227="",0,O1227))) | S128: 13000 | T128: =IF($A1227="","",IF(R1227="","",R1227-IF(S1227="",0,S1227))) | U128: =IF($A1227="","",IF(I1227="","",I1227-SUM(J1227:P1227))) -> 2000 | V128: JRE 2026年3月期(第49期)決算短信(2026/5/15公表) ②不動産等関連資産の損益状況 | W128: 確認済 | X128: 百万円単位開示×1000で収録(下3桁は概数)。各科目は百万円未満切捨てのため内訳チェック欄に最大数百万円、賃貸事業損益(F-I)と掲載損益に最大1百万円の差が系統的に発生(JRE-ALL行参照) | Y128: ○（通期保有） | Z128: 年換算可 | AA128: 百万円単位（下3桁は概数）
A129: JRE-056 | B129: JRE | C129: 2026年3月期（第49期） | D129: 6 | E129: 開示（物件別・費用内訳含む・百万円単位） | F129: 303000 | I129: 205000 | J129: 31000 | K129: 27000 | L129: 0 | M129: 0 | N129: 0 | O129: 145000 | P129: 0 | Q129: =IF($A1228="","",IF(OR(F1228="",I1228=""),"",F1228-I1228)) -> 98000 | R129: =IF($A1228="","",IF(Q1228="","",Q1228+IF(O1228="",0,O1228))) | S129: 3000 | T129: =IF($A1228="","",IF(R1228="","",R1228-IF(S1228="",0,S1228))) | U129: =IF($A1228="","",IF(I1228="","",I1228-SUM(J1228:P1228))) -> 2000 | V129: JRE 2026年3月期(第49期)決算短信(2026/5/15公表) ②不動産等関連資産の損益状況 | W129: 確認済 | X129: 当期(2025/10/17)取得のため収益は取得日以降の期間のみ・公租公課0。百万円単位開示×1000で収録(下3桁は概数)。各科目は百万円未満切捨てのため内訳チェック欄に最大数百万円、賃貸事業損益(F-I)と掲載損益に最大1百万円の差が系統的に発生(JRE-ALL行参照) | Y129: ×（期の一部のみ） | Z129: 年換算値は実態と乖離するため利回り算定に用いない（当期取得のため収入が保有期間分のみ） | AA129: 百万円単位（下3桁は概数）
A130: JRE-057 | B130: JRE | C130: 2026年3月期（第49期） | D130: 6 | E130: 開示（物件別・費用内訳含む・百万円単位） | F130: 69000 | I130: 50000 | J130: 11000 | K130: 8000 | L130: 8000 | M130: 0 | N130: 9000 | O130: 13000 | P130: 0 | Q130: =IF($A1229="","",IF(OR(F1229="",I1229=""),"",F1229-I1229)) -> 19000 | R130: =IF($A1229="","",IF(Q1229="","",Q1229+IF(O1229="",0,O1229))) | S130: 40000 | T130: =IF($A1229="","",IF(R1229="","",R1229-IF(S1229="",0,S1229))) | U130: =IF($A1229="","",IF(I1229="","",I1229-SUM(J1229:P1229))) -> 1000 | V130: JRE 2026年3月期(第49期)決算短信(2026/5/15公表) ②不動産等関連資産の損益状況 | W130: 確認済 | X130: 百万円単位開示×1000で収録(下3桁は概数)。各科目は百万円未満切捨てのため内訳チェック欄に最大数百万円、賃貸事業損益(F-I)と掲載損益に最大1百万円の差が系統的に発生(JRE-ALL行参照) | Y130: ○（通期保有） | Z130: 年換算可 | AA130: 百万円単位（下3桁は概数）
A131: JRE-058 | B131: JRE | C131: 2026年3月期（第49期） | D131: 6 | E131: 開示（物件別・費用内訳含む・百万円単位） | F131: 661000 | I131: 275000 | J131: 74000 | K131: 59000 | L131: 49000 | M131: 0 | N131: 24000 | O131: 67000 | P131: 0 | Q131: =IF($A1230="","",IF(OR(F1230="",I1230=""),"",F1230-I1230)) -> 386000 | R131: =IF($A1230="","",IF(Q1230="","",Q1230+IF(O1230="",0,O1230))) | S131: 80000 | T131: =IF($A1230="","",IF(R1230="","",R1230-IF(S1230="",0,S1230))) | U131: =IF($A1230="","",IF(I1230="","",I1230-SUM(J1230:P1230))) -> 2000 | V131: JRE 2026年3月期(第49期)決算短信(2026/5/15公表) ②不動産等関連資産の損益状況 | W131: 確認済 | X131: 百万円単位開示×1000で収録(下3桁は概数)。各科目は百万円未満切捨てのため内訳チェック欄に最大数百万円、賃貸事業損益(F-I)と掲載損益に最大1百万円の差が系統的に発生(JRE-ALL行参照) | Y131: ○（通期保有） | Z131: 年換算可 | AA131: 百万円単位（下3桁は概数）
A132: JRE-059 | B132: JRE | C132: 2026年3月期（第49期） | D132: 6 | E132: 開示（物件別・費用内訳含む・百万円単位） | F132: 152000 | I132: 135000 | J132: 24000 | K132: 16000 | L132: 19000 | M132: 0 | N132: 50000 | O132: 23000 | P132: 0 | Q132: =IF($A1231="","",IF(OR(F1231="",I1231=""),"",F1231-I1231)) -> 17000 | R132: =IF($A1231="","",IF(Q1231="","",Q1231+IF(O1231="",0,O1231))) | S132: 0 | T132: =IF($A1231="","",IF(R1231="","",R1231-IF(S1231="",0,S1231))) | U132: =IF($A1231="","",IF(I1231="","",I1231-SUM(J1231:P1231))) -> 3000 | V132: JRE 2026年3月期(第49期)決算短信(2026/5/15公表) ②不動産等関連資産の損益状況 | W132: 確認済 | X132: 百万円単位開示×1000で収録(下3桁は概数)。各科目は百万円未満切捨てのため内訳チェック欄に最大数百万円、賃貸事業損益(F-I)と掲載損益に最大1百万円の差が系統的に発生(JRE-ALL行参照) | Y132: ○（通期保有） | Z132: 年換算可 | AA132: 百万円単位（下3桁は概数）
A133: JRE-060 | B133: JRE | C133: 2026年3月期（第49期） | D133: 6 | E133: 開示（物件別・費用内訳含む・百万円単位） | F133: 736000 | I133: 384000 | J133: 107000 | K133: 65000 | L133: 75000 | M133: 0 | N133: 0 | O133: 134000 | P133: 0 | Q133: =IF($A1232="","",IF(OR(F1232="",I1232=""),"",F1232-I1232)) -> 352000 | R133: =IF($A1232="","",IF(Q1232="","",Q1232+IF(O1232="",0,O1232))) | S133: 0 | T133: =IF($A1232="","",IF(R1232="","",R1232-IF(S1232="",0,S1232))) | U133: =IF($A1232="","",IF(I1232="","",I1232-SUM(J1232:P1232))) -> 3000 | V133: JRE 2026年3月期(第49期)決算短信(2026/5/15公表) ②不動産等関連資産の損益状況 | W133: 確認済 | X133: 百万円単位開示×1000で収録(下3桁は概数)。各科目は百万円未満切捨てのため内訳チェック欄に最大数百万円、賃貸事業損益(F-I)と掲載損益に最大1百万円の差が系統的に発生(JRE-ALL行参照) | Y133: ○（通期保有） | Z133: 年換算可 | AA133: 百万円単位（下3桁は概数）
A134: JRE-061 | B134: JRE | C134: 2026年3月期（第49期） | D134: 6 | E134: 開示（物件別・費用内訳含む・百万円単位） | F134: 71000 | I134: 62000 | J134: 12000 | K134: 7000 | L134: 6000 | M134: 0 | N134: 5000 | O134: 30000 | P134: 0 | Q134: =IF($A1233="","",IF(OR(F1233="",I1233=""),"",F1233-I1233)) -> 9000 | R134: =IF($A1233="","",IF(Q1233="","",Q1233+IF(O1233="",0,O1233))) | S134: 27000 | T134: =IF($A1233="","",IF(R1233="","",R1233-IF(S1233="",0,S1233))) | U134: =IF($A1233="","",IF(I1233="","",I1233-SUM(J1233:P1233))) -> 2000 | V134: JRE 2026年3月期(第49期)決算短信(2026/5/15公表) ②不動産等関連資産の損益状況 | W134: 確認済 | X134: 百万円単位開示×1000で収録(下3桁は概数)。各科目は百万円未満切捨てのため内訳チェック欄に最大数百万円、賃貸事業損益(F-I)と掲載損益に最大1百万円の差が系統的に発生(JRE-ALL行参照) | Y134: ○（通期保有） | Z134: 年換算可 | AA134: 百万円単位（下3桁は概数）
A135: JRE-062 | B135: JRE | C135: 2026年3月期（第49期） | D135: 6 | E135: 開示（物件別・費用内訳含む・百万円単位） | F135: 559000 | I135: 342000 | J135: 99000 | K135: 47000 | L135: 71000 | M135: 1000 | N135: 17000 | O135: 104000 | P135: 0 | Q135: =IF($A1234="","",IF(OR(F1234="",I1234=""),"",F1234-I1234)) -> 217000 | R135: =IF($A1234="","",IF(Q1234="","",Q1234+IF(O1234="",0,O1234))) | S135: 490000 | T135: =IF($A1234="","",IF(R1234="","",R1234-IF(S1234="",0,S1234))) | U135: =IF($A1234="","",IF(I1234="","",I1234-SUM(J1234:P1234))) -> 3000 | V135: JRE 2026年3月期(第49期)決算短信(2026/5/15公表) ②不動産等関連資産の損益状況 | W135: 確認済 | X135: 百万円単位開示×1000で収録(下3桁は概数)。各科目は百万円未満切捨てのため内訳チェック欄に最大数百万円、賃貸事業損益(F-I)と掲載損益に最大1百万円の差が系統的に発生(JRE-ALL行参照) | Y135: ○（通期保有） | Z135: 年換算可 | AA135: 百万円単位（下3桁は概数）
A136: JRE-063 | B136: JRE | C136: 2026年3月期（第49期） | D136: 6 | E136: 開示（物件別・費用内訳含む・百万円単位） | F136: 134000 | I136: 80000 | J136: 18000 | K136: 12000 | L136: 10000 | M136: 0 | N136: 10000 | O136: 27000 | P136: 0 | Q136: =IF($A1235="","",IF(OR(F1235="",I1235=""),"",F1235-I1235)) -> 54000 | R136: =IF($A1235="","",IF(Q1235="","",Q1235+IF(O1235="",0,O1235))) | S136: 2000 | T136: =IF($A1235="","",IF(R1235="","",R1235-IF(S1235="",0,S1235))) | U136: =IF($A1235="","",IF(I1235="","",I1235-SUM(J1235:P1235))) -> 3000 | V136: JRE 2026年3月期(第49期)決算短信(2026/5/15公表) ②不動産等関連資産の損益状況 | W136: 確認済 | X136: 百万円単位開示×1000で収録(下3桁は概数)。各科目は百万円未満切捨てのため内訳チェック欄に最大数百万円、賃貸事業損益(F-I)と掲載損益に最大1百万円の差が系統的に発生(JRE-ALL行参照) | Y136: ○（通期保有） | Z136: 年換算可 | AA136: 百万円単位（下3桁は概数）
...

Sheet 環境認証
A1: 物件ID | B1: 法人ID | C1: 認証種別 | D1: 認証名称 | E1: 対象区分 | F1: ランク | G1: 取得年月 | H1: 出典物件名 | I1: 備考
A2: NBF-01 | B2: NBF | C2: CASBEE | D2: CASBEE-不動産 | F2: S | H2: 新宿三井ビルディング
A3: NBF-02 | B3: NBF | C3: CASBEE | D3: CASBEE-不動産 | F3: S | H3: 飯田橋グラン・ブルーム
A4: NBF-03 | B4: NBF | C4: CASBEE | D4: CASBEE-不動産 | F4: S | H4: 六本木ティーキューブ
A5: NBF-04 | B5: NBF | C5: CASBEE | D5: CASBEE-不動産 | F5: S | H5: 西新宿三井ビルディング
A6: NBF-05 | B6: NBF | C6: CASBEE | D6: CASBEE-不動産 | F6: S | H6: セレスティン芝三井ビルディング
A7: NBF-06 | B7: NBF | C7: CASBEE | D7: CASBEE-不動産 | F7: S | H7: NBF品川タワー
A8: NBF-07 | B8: NBF | C8: CASBEE | D8: CASBEE-不動産 | F8: S | H8: NBFプラチナタワー
A9: NBF-08 | B9: NBF | C9: CASBEE | D9: CASBEE-不動産 | F9: S | H9: NBFコモディオ汐留
A10: NBF-09 | B10: NBF | C10: CASBEE | D10: CASBEE-不動産 | F10: S | H10: G-BASE田町
A11: NBF-10 | B11: NBF | C11: CASBEE | D11: CASBEE-不動産 | F11: S | H11: 虎ノ門琴平タワー
A12: NBF-11 | B12: NBF | C12: CASBEE | D12: CASBEE-不動産 | F12: S | H12: NBF渋谷ガーデンフロント
A13: NBF-12 | B13: NBF | C13: CASBEE | D13: CASBEE-不動産 | F13: A | H13: NBF銀座通りビル
... A34: NBF-34 | B34: NBF | C34: CASBEE | D34: CASBEE-不動産 | F34: S | H34: ゲートシティ大崎
A35: NBF-34 | B35: NBF | C35: CASBEE | D35: CASBEE-建築 | H35: ゲートシティ大崎
A36: NBF-35 | B36: NBF | C36: CASBEE | D36: CASBEE-不動産 | F36: S | H36: NBF豊洲キャナルフロント
A37: NBF-36 | B37: NBF | C37: CASBEE | D37: CASBEE-不動産 | F37: S | H37: 上野イーストタワー
A38: NBF-37 | B38: NBF | C38: CASBEE | D38: CASBEE-不動産 | F38: A | H38: NBF豊洲ガーデンフロント
A39: NBF-38 | B39: NBF | C39: CASBEE | D39: CASBEE-不動産 | F39: S | H39: 大崎ブライトコア（ブライトプラザ）
A40: NBF-39 | B40: NBF | C40: CASBEE | D40: CASBEE-不動産 | F40: S | H40: 中目黒GTタワー
A41: NBF-40 | B41: NBF | C41: CASBEE | D41: CASBEE-不動産 | F41: S | H41: 大崎ブライトタワー
A42: NBF-41 | B42: NBF | C42: CASBEE | D42: CASBEE-不動産 | F42: S | H42: NBF池袋イースト
A43: NBF-42 | B43: NBF | C43: CASBEE | D43: CASBEE-不動産 | F43: S | H43: 東五反田スクエア
A44: NBF-43 | B44: NBF | C44: CASBEE | D44: CASBEE-不動産 | F44: A | H44: NBF池袋タワー
A45: NBF-44 | B45: NBF | C45: CASBEE | D45: CASBEE-不動産 | F45: A | H45: NBF池袋シティビル
A46: NBF-45 | B46: NBF | C46: CASBEE | D46: CASBEE-不動産 | F46: S | H46: 調布サウスゲートビル
A47: NBF-46 | B47: NBF | C47: DBJ | D47: DBJ Green Building認証 | H47: 横浜三井ビルディング | I47: ランク非開示（出典に物件別の星数記載なし）
A48: NBF-46 | B48: NBF | C48: CASBEE | D48: CASBEE-不動産 | F48: S | H48: 横浜三井ビルディング
A49: NBF-47 | B49: NBF | C49: CASBEE | D49: CASBEE-不動産 | F49: S | H49: フロンティア武蔵小杉N棟・S棟
A50: NBF-48 | B50: NBF | C50: CASBEE | D50: CASBEE-不動産 | F50: S | H50: 横浜STビル
A51: NBF-49 | B51: NBF | C51: CASBEE | D51: CASBEE-不動産 | F51: S | H51: パレール三井ビルディング
A52: NBF-50 | B52: NBF | C52: CASBEE | D52: CASBEE-不動産 | F52: S | H52: シーノ大宮ノースウィング
A53: NBF-51 | B53: NBF | C53: CASBEE | D53: CASBEE-不動産 | F53: A | H53: NBF浦和ビル
A54: NBF-52 | B54: NBF | C54: CASBEE | D54: CASBEE-不動産 | F54: A | H54: NBF松戸ビル
A55: NBF-54 | B55: NBF | C55: CASBEE | D55: CASBEE-不動産 | F55: S | H55: 札幌エルプラザ
A56: NBF-55 | B56: NBF | C56: CASBEE | D56: CASBEE-不動産 | F56: A | H56: NBF札幌南二条ビル
A57: NBF-56 | B57: NBF | C57: ZEB | D57: BELS | H57: Dタワー富山 | I57: 星数非開示（出典に物件別の星数記載なし）
A58: NBF-56 | B58: NBF | C58: CASBEE | D58: CASBEE-不動産 | F58: S | H58: Dタワー富山
A59: NBF-57 | B59: NBF | C59: CASBEE | D59: CASBEE-不動産 | F59: S | H59: 三井住友銀行名古屋ビル
A60: NBF-58 | B60: NBF | C60: CASBEE | D60: CASBEE-不動産 | F60: S | H60: 名古屋三井ビルディング新館
A61: NBF-59 | B61: NBF | C61: CASBEE | D61: CASBEE-不動産 | F61: S | H61: 名古屋三井ビルディング本館
A62: NBF-60 | B62: NBF | C62: CASBEE | D62: CASBEE-不動産 | F62: S | H62: NBF名古屋広小路ビル
A63: NBF-61 | B63: NBF | C63: CASBEE | D63: CASBEE-不動産 | F63: S | H63: 中之島三井ビルディング
A64: NBF-62 | B64: NBF | C64: CASBEE | D64: CASBEE-不動産 | F64: S | H64: アクア堂島NBFタワー
A65: NBF-63 | B65: NBF | C65: CASBEE | D65: CASBEE-不動産 | F65: S | H65: 中之島セントラルタワー
A66: NBF-64 | B66: NBF | C66: CASBEE | D66: CASBEE-不動産 | F66: A | H66: 信濃橋三井ビルディング
A67: NBF-65 | B67: NBF | C67: CASBEE | D67: CASBEE-不動産 | F67: S | H67: 堺筋本町センタービル
A68: NBF-66 | B68: NBF | C68: CASBEE | D68: CASBEE-不動産 | F68: A | H68: 淀屋橋フレックスタワー
A69: NBF-67 | B69: NBF | C69: CASBEE | D69: CASBEE-不動産 | F69: S | H69: 広島袋町ビルディング
... A80: JRE-007 | B80: JRE | C80: DBJ | D80: DBJ Green Building認証 | F80: ★5 | H80: 三菱ＵＦＪ信託銀行本店ビル
A81: JRE-008 | B81: JRE | C81: CASBEE | D81: CASBEE-不動産／建築（区分不明） | F81: A | H81: ビュレックス麹町 | I81: 出典表記が「CASBEE（不動産/建築）」等で評価ツールの区分が特定不能
A82: JRE-009 | B82: JRE | C82: ZEB | D82: BELS | F82: ★5 | H82: CIRCLES平河町
A83: JRE-010 | B83: JRE | C83: DBJ | D83: DBJ Green Building認証 | F83: ★3 | H83: 山王グランドビル
A84: JRE-011 | B84: JRE | C84: DBJ | D84: DBJ Green Building認証 | F84: ★3 | H84: 有楽町電気ビルヂング
A85: JRE-012 | B85: JRE | C85: ZEB | D85: BELS | F85: ★3 | H85: フロントプレイス日本橋
A86: JRE-012 | B86: JRE | C86: CASBEE | D86: CASBEE-不動産 | F86: S | H86: フロントプレイス日本橋
A87: JRE-013 | B87: JRE | C87: ZEB | D87: BELS（ZEB Ready） | H87: ＪＲＥ茅場町二丁目ビル | I87: 星数は物件別に特定不能（ZEB取得8物件の内訳は★6×3・★5×5）
A88: JRE-015 | B88: JRE | C88: ZEB | D88: BELS（ZEB Ready） | H88: ＪＲＥ銀座一丁目イーストビル | I88: 星数は物件別に特定不能（ZEB取得8物件の内訳は★6×3・★5×5）
A89: JRE-015 | B89: JRE | C89: CASBEE | D89: CASBEE-不動産／建築（区分不明） | F89: A | H89: ＪＲＥ銀座一丁目イーストビル | I89: 出典表記が「CASBEE（不動産/建築）」等で評価ツールの区分が特定不能
A90: JRE-016 | B90: JRE | C90: DBJ | D90: DBJ Green Building認証 | F90: ★3 | H90: 銀座三和ビル
A91: JRE-017 | B91: JRE | C91: CASBEE | D91: CASBEE-不動産／建築（区分不明） | F91: A | H91: ＪＲＥ銀座三丁目ビル | I91: 出典表記が「CASBEE（不動産/建築）」等で評価ツールの区分が特定不能
A92: JRE-018 | B92: JRE | C92: DBJ | D92: DBJ Green Building認証 | F92: ★3 | H92: 赤坂パークビル
A93: JRE-019 | B93: JRE | C93: DBJ | D93: DBJ Green Building認証 | F93: ★4 | H93: the ARGYLE aoyama
A94: JRE-020 | B94: JRE | C94: ZEB | D94: BELS | F94: ★3 | H94: 3rd MINAMI AOYAMA
A95: JRE-020 | B95: JRE | C95: DBJ | D95: DBJ Green Building認証 | F95: ★4 | H95: 3rd MINAMI AOYAMA
A96: JRE-021 | B96: JRE | C96: CASBEE | D96: CASBEE-不動産／建築（区分不明） | F96: A | H96: ＪＲＥ青山クリスタルビル | I96: 出典表記が「CASBEE（不動産/建築）」等で評価ツールの区分が特定不能
A97: JRE-022 | B97: JRE | C97: CASBEE | D97: CASBEE-不動産／建築（区分不明） | F97: A | H97: クローバー芝公園 | I97: 出典表記が「CASBEE（不動産/建築）」等で評価ツールの区分が特定不能
A98: JRE-023 | B98: JRE | C98: DBJ | D98: DBJ Green Building認証 | F98: ★5 | H98: 汐留ビルディング
A99: JRE-024 | B99: JRE | C99: CASBEE | D99: CASBEE-不動産 | F99: S | H99: ＪＲＥ芝二丁目大門ビル
A100: JRE-025 | B100: JRE | C100: CASBEE | D100: CASBEE-不動産 | F100: S | H100: ＪＲＥコスモ金杉橋ビル
A101: JRE-026 | B101: JRE | C101: CASBEE | D101: CASBEE-不動産 | F101: S | H101: シーバンスS棟
A102: JRE-027 | B102: JRE | C102: ZEB | D102: BELS | F102: ★1 | H102: 田町フロントビル
A103: JRE-027 | B103: JRE | C103: CASBEE | D103: CASBEE-不動産 | F103: S | H103: 田町フロントビル
A104: JRE-028 | B104: JRE | C104: DBJ | D104: DBJ Green Building認証 | F104: ★5 | H104: 新宿イーストサイドスクエア
A105: JRE-029 | B105: JRE | C105: DBJ | D105: DBJ Green Building認証 | F105: ★4 | H105: 新宿フロントタワー
A106: JRE-031 | B106: JRE | C106: CASBEE | D106: CASBEE-不動産／建築（区分不明） | F106: A | H106: ＪＲＥ西新宿テラス | I106: 出典表記が「CASBEE（不動産/建築）」等で評価ツールの区分が特定不能
A107: JRE-032 | B107: JRE | C107: DBJ | D107: DBJ Green Building認証 | F107: ★4 | H107: 東京オペラシティビル
A108: JRE-033 | B108: JRE | C108: CASBEE | D108: CASBEE-不動産／建築（区分不明） | F108: A | H108: フロントプレイス南新宿 | I108: 出典表記が「CASBEE（不動産/建築）」等で評価ツールの区分が特定不能
A109: JRE-034 | B109: JRE | C109: DBJ | D109: DBJ Green Building認証 | F109: ★4 | H109: リンクスクエア新宿
A110: JRE-035 | B110: JRE | C110: ZEB | D110: BELS（ZEB Oriented） | H110: ＪＲＥ代々木一丁目ビル | I110: 星数は物件別に特定不能（ZEB取得8物件の内訳は★6×3・★5×5）
A111: JRE-035 | B111: JRE | C111: CASBEE | D111: CASBEE-不動産 | F111: S | H111: ＪＲＥ代々木一丁目ビル
A112: JRE-036 | B112: JRE | C112: CASBEE | D112: CASBEE-不動産 | F112: S | H112: ＪＲＥ神宮前テラス
A113: JRE-039 | B113: JRE | C113: DBJ | D113: DBJ Green Building認証 | F113: ★3 | H113: 恵比寿ネオナート
A114: JRE-040 | B114: JRE | C114: ZEB | D114: BELS | F114: ★1 | H114: ＴＩＸＴＯＷＥＲ ＵＥＮＯ
A115: JRE-040 | B115: JRE | C115: DBJ | D115: DBJ Green Building認証 | F115: ★3 | H115: ＴＩＸＴＯＷＥＲ ＵＥＮＯ
A116: JRE-041 | B116: JRE | C116: DBJ | D116: DBJ Green Building認証 | F116: ★5 | H116: 豊洲フォレシア
A117: JRE-042 | B117: JRE | C117: DBJ | D117: DBJ Green Building認証 | F117: ★4 | H117: 豊洲フロント
A118: JRE-043 | B118: JRE | C118: ZEB | D118: BELS（ZEB Ready） | H118: ＪＲＥ東五反田一丁目ビル | I118: 星数は物件別に特定不能（ZEB取得8物件の内訳は★6×3・★5×5）
A119: JRE-044 | B119: JRE | C119: ZEB | D119: BELS | F119: ★1 | H119: 大崎フロントタワー
A120: JRE-044 | B120: JRE | C120: CASBEE | D120: CASBEE-不動産 | F120: S | H120: 大崎フロントタワー
A121: JRE-045 | B121: JRE | C121: CASBEE | D121: CASBEE-不動産 | F121: S | H121: ＪＲＥ大森駅東口ビル
A122: JRE-046 | B122: JRE | C122: DBJ | D122: DBJ Green Building認証 | F122: ★3 | H122: ハーモニータワー
A123: JRE-048 | B123: JRE | C123: CASBEE | D123: CASBEE-不動産／建築（区分不明） | F123: A | H123: ＪＲＥ南池袋ビル | I123: 出典表記が「CASBEE（不動産/建築）」等で評価ツールの区分が特定不能
A124: JRE-049 | B124: JRE | C124: CASBEE | D124: CASBEE-不動産 | F124: S | H124: 八王子ファーストスクエア
A125: JRE-050 | B125: JRE | C125: CASBEE | D125: CASBEE-不動産 | F125: S | H125: ＪＲＥさいたま浦和ビル
A126: JRE-051 | B126: JRE | C126: CASBEE | D126: CASBEE-不動産 | F126: S | H126: ＭＭパークビル
A127: JRE-052 | B127: JRE | C127: DBJ | D127: DBJ Green Building認証 | F127: ★4 | H127: クイーンズタワーＡ
A128: JRE-053 | B128: JRE | C128: CASBEE | D128: CASBEE-不動産／建築（区分不明） | F128: A | H128: 武蔵小杉ＳＴＭビル | I128: 出典表記が「CASBEE（不動産/建築）」等で評価ツールの区分が特定不能
A129: JRE-054 | B129: JRE | C129: ZEB | D129: BELS（ZEB Ready） | H129: サッポロアーチビル | I129: 星数は物件別に特定不能（ZEB取得8物件の内訳は★6×3・★5×5）
A130: JRE-054 | B130: JRE | C130: CASBEE | D130: CASBEE-不動産／建築（区分不明） | F130: A | H130: サッポロアーチビル | I130: 出典表記が「CASBEE（不動産/建築）」等で評価ツールの区分が特定不能
...

Sheet PM会社_物件別
A1: 物件ID | B1: 法人ID | C1: 物件名 | D1: PM会社 | E1: PM会社系列 | F1: スポンサー系判定 | G1: 出典資料 | H1: 決算期 | I1: 記載箇所 | J1: 備考
A2: NBF-01 | B2: NBF | C2: 新宿三井ビルディング | D2: 三井不動産株式会社 | E2: 三井不動産系（自社） | F2: スポンサー系 | G2: 日本ビルファンド投資法人 有価証券報告書 | H2: 2025年12月期 | I2: 個別物件表「建物管理会社」欄 | J2: 有報上「建物管理会社」として記載
A3: NBF-02 | B3: NBF | C3: 飯田橋グラン・ブルーム | D3: 三井不動産株式会社 | E3: 三井不動産系（自社） | F3: スポンサー系 | G3: 日本ビルファンド投資法人 有価証券報告書 | H3: 2025年12月期 | I3: 個別物件表「建物管理会社」欄 | J3: 有報上「建物管理会社」として記載
A4: NBF-03 | B4: NBF | C4: 六本木ティーキューブ | D4: 三井不動産株式会社 | E4: 三井不動産系（自社） | F4: スポンサー系 | G4: 日本ビルファンド投資法人 有価証券報告書 | H4: 2025年12月期 | I4: 個別物件表「建物管理会社」欄 | J4: 有報上「建物管理会社」として記載
A5: NBF-04 | B5: NBF | C5: 西新宿三井ビルディング | D5: 三井不動産株式会社 | E5: 三井不動産系（自社） | F5: スポンサー系 | G5: 日本ビルファンド投資法人 有価証券報告書 | H5: 2025年12月期 | I5: 個別物件表「建物管理会社」欄 | J5: 有報上「建物管理会社」として記載
A6: NBF-05 | B6: NBF | C6: セレスティン芝三井ビルディング | D6: 三井不動産株式会社 | E6: 三井不動産系（自社） | F6: スポンサー系 | G6: 日本ビルファンド投資法人 有価証券報告書 | H6: 2025年12月期 | I6: 個別物件表「建物管理会社」欄 | J6: 有報上「建物管理会社」として記載
A7: NBF-06 | B7: NBF | C7: ＮＢＦ品川タワー | D7: 三井不動産ビルマネジメント株式会社 | E7: 三井不動産系 | F7: スポンサー系 | G7: 日本ビルファンド投資法人 有価証券報告書 | H7: 2025年12月期 | I7: 個別物件表「建物管理会社」欄 | J7: 有報上「建物管理会社」として記載
A8: NBF-07 | B8: NBF | C8: ＮＢＦプラチナタワー | D8: 三井不動産ファシリティーズ株式会社 | E8: 三井不動産系 | F8: スポンサー系 | G8: 日本ビルファンド投資法人 有価証券報告書 | H8: 2025年12月期 | I8: 個別物件表「建物管理会社」欄 | J8: 有報上「建物管理会社」として記載
A9: NBF-08 | B9: NBF | C9: ＮＢＦコモディオ汐留 | D9: 三井不動産ファシリティーズ株式会社 | E9: 三井不動産系 | F9: スポンサー系 | G9: 日本ビルファンド投資法人 有価証券報告書 | H9: 2025年12月期 | I9: 個別物件表「建物管理会社」欄 | J9: 有報上「建物管理会社」として記載
A10: NBF-09 | B10: NBF | C10: Ｇ－ＢＡＳＥ田町 | D10: グローブシップ株式会社 | E10: 独立系 | F10: 第三者 | G10: 日本ビルファンド投資法人 有価証券報告書 | H10: 2025年12月期 | I10: 個別物件表「建物管理会社」欄 | J10: 有報上「建物管理会社」として記載
A11: NBF-10 | B11: NBF | C11: 虎ノ門琴平タワー | D11: 三井不動産株式会社 | E11: 三井不動産系（自社） | F11: スポンサー系 | G11: 日本ビルファンド投資法人 有価証券報告書 | H11: 2025年12月期 | I11: 個別物件表「建物管理会社」欄 | J11: 有報上「建物管理会社」として記載
A12: NBF-11 | B12: NBF | C12: ＮＢＦ渋谷ガーデンフロント | D12: 三井不動産ビルマネジメント株式会社 | E12: 三井不動産系 | F12: スポンサー系 | G12: 日本ビルファンド投資法人 有価証券報告書 | H12: 2025年12月期 | I12: 個別物件表「建物管理会社」欄 | J12: 有報上「建物管理会社」として記載
... A70: NBF-70 | B70: NBF | C70: ＮＢＦ熊本ビル | D70: 太平ビルサービス株式会社 | E70: 独立系 | F70: 第三者 | G70: 日本ビルファンド投資法人 有価証券報告書 | H70: 2025年12月期 | I70: 個別物件表「建物管理会社」欄 | J70: 有報上「建物管理会社」として記載
A71: JRE-001 | B71: JRE | C71: 北の丸スクエア | D71: 三菱地所プロパティマネジメント株式会社 | E71: 三菱地所系 | F71: スポンサー系 | G71: ジャパンリアルエステイト投資法人 有価証券報告書 | H71: 2026年3月期 | I71: 個別物件表「不動産管理会社」欄
A72: JRE-002 | B72: JRE | C72: ＪＲＥ神田小川町ビル | D72: 三井物産フォーサイト株式会社 | E72: 三井物産系 | F72: 第三者 | G72: ジャパンリアルエステイト投資法人 有価証券報告書 | H72: 2026年3月期 | I72: 個別物件表「不動産管理会社」欄
A73: JRE-003 | B73: JRE | C73: 神田橋パークビルヂング | D73: 三菱地所株式会社 | E73: 三菱地所系（自社） | F73: スポンサー系 | G73: ジャパンリアルエステイト投資法人 有価証券報告書 | H73: 2026年3月期 | I73: 個別物件表「不動産管理会社」欄
A74: JRE-004 | B74: JRE | C74: 大手町フィナンシャルシティノースタワー | D74: 三菱地所株式会社 | E74: 三菱地所系（自社） | F74: スポンサー系 | G74: ジャパンリアルエステイト投資法人 有価証券報告書 | H74: 2026年3月期 | I74: 個別物件表「不動産管理会社」欄
A75: JRE-005 | B75: JRE | C75: 大手町パークビルディング | D75: 三菱地所株式会社 | E75: 三菱地所系（自社） | F75: スポンサー系 | G75: ジャパンリアルエステイト投資法人 有価証券報告書 | H75: 2026年3月期 | I75: 個別物件表「不動産管理会社」欄
A76: JRE-006 | B76: JRE | C76: 二番町ガーデン | D76: 三菱地所株式会社 | E76: 三菱地所系（自社） | F76: スポンサー系 | G76: ジャパンリアルエステイト投資法人 有価証券報告書 | H76: 2026年3月期 | I76: 個別物件表「不動産管理会社」欄
A77: JRE-007 | B77: JRE | C77: 三菱ＵＦＪ信託銀行本店ビル | D77: 三菱地所株式会社 | E77: 三菱地所系（自社） | F77: スポンサー系 | G77: ジャパンリアルエステイト投資法人 有価証券報告書 | H77: 2026年3月期 | I77: 個別物件表「不動産管理会社」欄
A78: JRE-008 | B78: JRE | C78: ビュレックス麹町 | D78: ケネディクス・プロパティ・デザイン株式会社 | E78: ケネディクス系 | F78: 第三者 | G78: ジャパンリアルエステイト投資法人 有価証券報告書 | H78: 2026年3月期 | I78: 個別物件表「不動産管理会社」欄
A79: JRE-009 | B79: JRE | C79: CIRCLES平河町 | D79: 三菱地所リアルエステートサービス株式会社 | E79: 三菱地所系 | F79: スポンサー系 | G79: ジャパンリアルエステイト投資法人 有価証券報告書 | H79: 2026年3月期 | I79: 個別物件表「不動産管理会社」欄
A80: JRE-010 | B80: JRE | C80: 山王グランドビル | D80: 三菱地所株式会社 | E80: 三菱地所系（自社） | F80: スポンサー系 | G80: ジャパンリアルエステイト投資法人 有価証券報告書 | H80: 2026年3月期 | I80: 個別物件表「不動産管理会社」欄
A81: JRE-011 | B81: JRE | C81: 有楽町電気ビルヂング | D81: 三菱地所プロパティマネジメント株式会社 | E81: 三菱地所系 | F81: スポンサー系 | G81: ジャパンリアルエステイト投資法人 有価証券報告書 | H81: 2026年3月期 | I81: 個別物件表「不動産管理会社」欄
A82: JRE-012 | B82: JRE | C82: フロントプレイス日本橋 | D82: 三菱地所株式会社 | E82: 三菱地所系（自社） | F82: スポンサー系 | G82: ジャパンリアルエステイト投資法人 有価証券報告書 | H82: 2026年3月期 | I82: 個別物件表「不動産管理会社」欄
... A94: JRE-024 | B94: JRE | C94: ＪＲＥ芝二丁目大門ビル | D94: 東京海上日動ファシリティーズ株式会社 | E94: 東京海上系 | F94: 第三者 | G94: ジャパンリアルエステイト投資法人 有価証券報告書 | H94: 2026年3月期 | I94: 個別物件表「不動産管理会社」欄
A95: JRE-025 | B95: JRE | C95: ＪＲＥコスモ金杉橋ビル | D95: 株式会社第一ビルディング | E95: 第一ビルディング（独立系） | F95: 第三者 | G95: ジャパンリアルエステイト投資法人 有価証券報告書 | H95: 2026年3月期 | I95: 個別物件表「不動産管理会社」欄 | J95: 有報上「－」と記載（PM会社を置いていない、またはマスターリース会社が兼務）有報上「－」と記載
A96: JRE-026 | B96: JRE | C96: シーバンスＳ棟 | D96: 清水建設株式会社 | E96: 清水建設系 | F96: 第三者 | G96: ジャパンリアルエステイト投資法人 有価証券報告書 | H96: 2026年3月期 | I96: 個別物件表「不動産管理会社」欄
A97: JRE-027 | B97: JRE | C97: 田町フロントビル | D97: 三菱地所株式会社 | E97: 三菱地所系（自社） | F97: スポンサー系 | G97: ジャパンリアルエステイト投資法人 有価証券報告書 | H97: 2026年3月期 | I97: 個別物件表「不動産管理会社」欄
A98: JRE-028 | B98: JRE | C98: 新宿イーストサイドスクエア | D98: 三菱地所株式会社 | E98: 三菱地所系（自社） | F98: スポンサー系 | G98: ジャパンリアルエステイト投資法人 有価証券報告書 | H98: 2026年3月期 | I98: 個別物件表「不動産管理会社」欄
A99: JRE-029 | B99: JRE | C99: 新宿フロントタワー | D99: 三菱地所株式会社 | E99: 三菱地所系（自社） | F99: スポンサー系 | G99: ジャパンリアルエステイト投資法人 有価証券報告書 | H99: 2026年3月期 | I99: 個別物件表「不動産管理会社」欄
A100: JRE-030 | B100: JRE | C100: コモレ四谷 | D100: 三菱地所株式会社 | E100: 三菱地所系（自社） | F100: スポンサー系 | G100: ジャパンリアルエステイト投資法人 有価証券報告書 | H100: 2026年3月期 | I100: 個別物件表「不動産管理会社」欄
A101: JRE-031 | B101: JRE | C101: ＪＲＥ西新宿テラス | D101: 東京海上日動ファシリティーズ株式会社 | E101: 東京海上系 | F101: 第三者 | G101: ジャパンリアルエステイト投資法人 有価証券報告書 | H101: 2026年3月期 | I101: 個別物件表「不動産管理会社」欄
A102: JRE-032 | B102: JRE | C102: 東京オペラシティビル | D102: 東京オペラシティビル株式会社 | E102: 物件専属SPC | F102: 第三者 | G102: ジャパンリアルエステイト投資法人 有価証券報告書 | H102: 2026年3月期 | I102: 個別物件表「不動産管理会社」欄
A103: JRE-033 | B103: JRE | C103: フロントプレイス南新宿 | D103: 三菱地所株式会社 | E103: 三菱地所系（自社） | F103: スポンサー系 | G103: ジャパンリアルエステイト投資法人 有価証券報告書 | H103: 2026年3月期 | I103: 個別物件表「不動産管理会社」欄
A104: JRE-034 | B104: JRE | C104: リンクスクエア新宿 | D104: 三菱地所株式会社 | E104: 三菱地所系（自社） | F104: スポンサー系 | G104: ジャパンリアルエステイト投資法人 有価証券報告書 | H104: 2026年3月期 | I104: 個別物件表「不動産管理会社」欄
A105: JRE-035 | B105: JRE | C105: ＪＲＥ代々木一丁目ビル | D105: 東京海上日動ファシリティーズ株式会社 | E105: 東京海上系 | F105: 第三者 | G105: ジャパンリアルエステイト投資法人 有価証券報告書 | H105: 2026年3月期 | I105: 個別物件表「不動産管理会社」欄
A106: JRE-036 | B106: JRE | C106: ＪＲＥ神宮前テラス | D106: 株式会社ザイマックス | E106: 独立系（ザイマックス） | F106: 第三者 | G106: ジャパンリアルエステイト投資法人 有価証券報告書 | H106: 2026年3月期 | I106: 個別物件表「不動産管理会社」欄
A107: JRE-037 | B107: JRE | C107: ＪＲＥ神宮前メディアスクエアビル | D107: 三菱地所プロパティマネジメント株式会社 | E107: 三菱地所系 | F107: スポンサー系 | G107: ジャパンリアルエステイト投資法人 有価証券報告書 | H107: 2026年3月期 | I107: 個別物件表「不動産管理会社」欄
... A114: JRE-045 | B114: JRE | C114: ＪＲＥ大森駅東口ビル | D114: 東京海上日動ファシリティーズ株式会社 | E114: 東京海上系 | F114: 第三者 | G114: ジャパンリアルエステイト投資法人 有価証券報告書 | H114: 2026年3月期 | I114: 個別物件表「不動産管理会社」欄
A115: JRE-046 | B115: JRE | C115: ハーモニータワー | D115: ト株式会社 / 株式会社ハーモニ | E115: 複数社（共同受託） | F115: 第三者 | G115: ジャパンリアルエステイト投資法人 有価証券報告書 | H115: 2026年3月期 | I115: 個別物件表「不動産管理会社」欄 | J115: ／複数社への委託
A116: JRE-047 | B116: JRE | C116: ＪＲＥ池袋二丁目ビル | D116: 株式会社第一ビルディング | E116: 第一ビルディング（独立系） | F116: 第三者 | G116: ジャパンリアルエステイト投資法人 有価証券報告書 | H116: 2026年3月期 | I116: 個別物件表「不動産管理会社」欄
A117: JRE-048 | B117: JRE | C117: ＪＲＥ南池袋ビル | D117: 株式会社ザイマックス | E117: 独立系（ザイマックス） | F117: 第三者 | G117: ジャパンリアルエステイト投資法人 有価証券報告書 | H117: 2026年3月期 | I117: 個別物件表「不動産管理会社」欄
A118: JRE-049 | B118: JRE | C118: 八王子ファーストスクエア | D118: 相互住宅株式会社 | E118: 独立系 | F118: 第三者 | G118: ジャパンリアルエステイト投資法人 有価証券報告書 | H118: 2026年3月期 | I118: 個別物件表「不動産管理会社」欄
A119: JRE-050 | B119: JRE | C119: ＪＲＥさいたま浦和ビル | D119: 株式会社第一ビルディング | E119: 第一ビルディング（独立系） | F119: 第三者 | G119: ジャパンリアルエステイト投資法人 有価証券報告書 | H119: 2026年3月期 | I119: 個別物件表「不動産管理会社」欄
A120: JRE-051 | B120: JRE | C120: ＭＭパークビル | D120: 三菱地所株式会社 | E120: 三菱地所系（自社） | F120: スポンサー系 | G120: ジャパンリアルエステイト投資法人 有価証券報告書 | H120: 2026年3月期 | I120: 個別物件表「不動産管理会社」欄
A121: JRE-052 | B121: JRE | C121: クイーンズタワーＡ | D121: 三菱地所株式会社 | E121: 三菱地所系（自社） | F121: スポンサー系 | G121: ジャパンリアルエステイト投資法人 有価証券報告書 | H121: 2026年3月期 | I121: 個別物件表「不動産管理会社」欄
A122: JRE-053 | B122: JRE | C122: 武蔵小杉ＳＴＭビル | D122: 相互住宅株式会社 | E122: 独立系 | F122: 第三者 | G122: ジャパンリアルエステイト投資法人 有価証券報告書 | H122: 2026年3月期 | I122: 個別物件表「不動産管理会社」欄
A123: JRE-054 | B123: JRE | C123: サッポロアーチビル | D123: 株式会社ザイマックス | E123: 独立系（ザイマックス） | F123: 第三者 | G123: ジャパンリアルエステイト投資法人 有価証券報告書 | H123: 2026年3月期 | I123: 個別物件表「不動産管理会社」欄
A124: JRE-055 | B124: JRE | C124: ８・３スクエア北ビル | D124: 三菱地所プロパティマネジメント株式会社 | E124: 三菱地所系 | F124: スポンサー系 | G124: ジャパンリアルエステイト投資法人 有価証券報告書 | H124: 2026年3月期 | I124: 個別物件表「不動産管理会社」欄
A125: JRE-056 | B125: JRE | C125: The Link Sapporo | D125: シービーアールイー株式会社 | E125: 外資系（CBRE） | F125: 第三者 | G125: ジャパンリアルエステイト投資法人 有価証券報告書 | H125: 2026年3月期 | I125: 個別物件表「不動産管理会社」欄
A126: JRE-057 | B126: JRE | C126: 定禅寺パークビル | D126: 三菱地所株式会社 | E126: 三菱地所系（自社） | F126: スポンサー系 | G126: ジャパンリアルエステイト投資法人 有価証券報告書 | H126: 2026年3月期 | I126: 個別物件表「不動産管理会社」欄
A127: JRE-058 | B127: JRE | C127: ＪＲＥ東二番丁スクエア | D127: 三菱地所プロパティマネジメント株式会社 | E127: 三菱地所系 | F127: スポンサー系 | G127: ジャパンリアルエステイト投資法人 有価証券報告書 | H127: 2026年3月期 | I127: 個別物件表「不動産管理会社」欄
... A306: JEI-01 | B306: JEI | C306: 大森ベルポートD館 | D306: 株式会社第一ビルディング | E306: 第一ビルディング（独立系） | F306: 第三者 | G306: ジャパンエクセレント投資法人 有価証券報告書 | H306: 2025年12月期 | I306: 個別物件表「PM会社」欄
A307: JEI-02 | B307: JEI | C307: 芝二丁目ビルディング | D307: 株式会社第一ビルディング | E307: 第一ビルディング（独立系） | F307: 第三者 | G307: ジャパンエクセレント投資法人 有価証券報告書 | H307: 2025年12月期 | I307: 個別物件表「PM会社」欄 | J307: 用途別に複数社へ委託 原文「事務所：株式会社第一ビルディング 住宅：相互住宅株式会社」（用途別に複数社へ委託） ／複数社への委託
A308: JEI-03 | B308: JEI | C308: JEI浜松町ビル | D308: 株式会社第一ビルディング | E308: 第一ビルディング（独立系） | F308: 第三者 | G308: ジャパンエクセレント投資法人 有価証券報告書 | H308: 2025年12月期 | I308: 個別物件表「PM会社」欄
A309: JEI-04 | B309: JEI | C309: 赤坂インターシティ | D309: 日鉄興和不動産株式会社 | E309: 日鉄興和系（自社） | F309: スポンサー系 | G309: ジャパンエクセレント投資法人 有価証券報告書 | H309: 2025年12月期 | I309: 個別物件表「PM会社」欄
A310: JEI-05 | B310: JEI | C310: 台場ガーデンシティビル | D310: 株式会社第一ビルディング | E310: 第一ビルディング（独立系） | F310: 第三者 | G310: ジャパンエクセレント投資法人 有価証券報告書 | H310: 2025年12月期 | I310: 個別物件表「PM会社」欄
A311: JEI-06 | B311: JEI | C311: 浜離宮インターシティ | D311: 日鉄興和不動産株式会社 | E311: 日鉄興和系（自社） | F311: スポンサー系 | G311: ジャパンエクセレント投資法人 有価証券報告書 | H311: 2025年12月期 | I311: 個別物件表「PM会社」欄
A312: JEI-07 | B312: JEI | C312: 興和西新橋ビル | D312: 日鉄興和不動産株式会社 | E312: 日鉄興和系（自社） | F312: スポンサー系 | G312: ジャパンエクセレント投資法人 有価証券報告書 | H312: 2025年12月期 | I312: 個別物件表「PM会社」欄
A313: JEI-08 | B313: JEI | C313: マンサード代官山 | D313: 日鉄興和不動産株式会社 | E313: 日鉄興和系（自社） | F313: スポンサー系 | G313: ジャパンエクセレント投資法人 有価証券報告書 | H313: 2025年12月期 | I313: 個別物件表「PM会社」欄
A314: JEI-09 | B314: JEI | C314: 赤坂インターシティAIR | D314: 赤坂インターシティマネジメント株式会社 | E314: 物件専属SPC | F314: 第三者 | G314: ジャパンエクセレント投資法人 有価証券報告書 | H314: 2025年12月期 | I314: 個別物件表「PM会社」欄
A315: JEI-10 | B315: JEI | C315: BIZCORE赤坂見附 | D315: 日鉄興和不動産株式会社 | E315: 日鉄興和系（自社） | F315: スポンサー系 | G315: ジャパンエクセレント投資法人 有価証券報告書 | H315: 2025年12月期 | I315: 個別物件表「PM会社」欄
A316: JEI-11 | B316: JEI | C316: BIZCORE神保町 | D316: 日鉄興和不動産株式会社 | E316: 日鉄興和系（自社） | F316: スポンサー系 | G316: ジャパンエクセレント投資法人 有価証券報告書 | H316: 2025年12月期 | I316: 個別物件表「PM会社」欄
A317: JEI-12 | B317: JEI | C317: BIZCORE渋谷 | D317: 日鉄興和不動産株式会社 | E317: 日鉄興和系（自社） | F317: スポンサー系 | G317: ジャパンエクセレント投資法人 有価証券報告書 | H317: 2025年12月期 | I317: 個別物件表「PM会社」欄
A318: JEI-13 | B318: JEI | C318: BIZCORE築地 | D318: 日鉄興和不動産株式会社 | E318: 日鉄興和系（自社） | F318: スポンサー系 | G318: ジャパンエクセレント投資法人 有価証券報告書 | H318: 2025年12月期 | I318: 個別物件表「PM会社」欄
A319: JEI-14 | B319: JEI | C319: 大崎ブライトタワー・大崎ブライトプラザ | D319: 三井不動産株式会社 | E319: 三井不動産系（自社） | F319: 第三者 | G319: ジャパンエクセレント投資法人 有価証券報告書 | H319: 2025年12月期 | I319: 個別物件表「PM会社」欄
A320: JEI-15 | B320: JEI | C320: アークヒルズフロントタワー | D320: 日鉄興和不動産株式会社 | E320: 日鉄興和系（自社） | F320: スポンサー系 | G320: ジャパンエクセレント投資法人 有価証券報告書 | H320: 2025年12月期 | I320: 個別物件表「PM会社」欄 | J320: 原文「日鉄興和不動産株式会社、他」（複数社が共同受託） ／複数社への委託
A321: JEI-16 | B321: JEI | C321: NHK名古屋放送センタービル | D321: 星光ビル管理株式会社 | E321: 独立系 | F321: 第三者 | G321: ジャパンエクセレント投資法人 有価証券報告書 | H321: 2025年12月期 | I321: 個別物件表「PM会社」欄
A322: JEI-18 | B322: JEI | C322: グランフロント大阪（北館） | D322: 非開示 | E322: 記載なし・非開示 | F322: 非開示 | G322: ジャパンエクセレント投資法人 有価証券報告書 | H322: 2025年12月期 | I322: 個別物件表「PM会社」欄 | J322: 有報上「非開示」と記載
A323: JEI-19 | B323: JEI | C323: 武蔵小杉タワープレイス | D323: 相互住宅株式会社 | E323: 独立系 | F323: 第三者 | G323: ジャパンエクセレント投資法人 有価証券報告書 | H323: 2025年12月期 | I323: 個別物件表「PM会社」欄
A324: JEI-20 | B324: JEI | C324: 川崎日進町ビルディング | D324: 株式会社第一ビルディング | E324: 第一ビルディング（独立系） | F324: 第三者 | G324: ジャパンエクセレント投資法人 有価証券報告書 | H324: 2025年12月期 | I324: 個別物件表「PM会社」欄
A325: JEI-21 | B325: JEI | C325: JEI両国ビル | D325: 株式会社第一ビルディング | E325: 第一ビルディング（独立系） | F325: 第三者 | G325: ジャパンエクセレント投資法人 有価証券報告書 | H325: 2025年12月期 | I325: 個別物件表「PM会社」欄
A326: JEI-22 | B326: JEI | C326: コアシティ立川 | D326: 株式会社第一ビルディング | E326: 第一ビルディング（独立系） | F326: 第三者 | G326: ジャパンエクセレント投資法人 有価証券報告書 | H326: 2025年12月期 | I326: 個別物件表「PM会社」欄
A327: JEI-23 | B327: JEI | C327: 日石横浜ビル | D327: 株式会社第一ビルディング | E327: 第一ビルディング（独立系） | F327: 第三者 | G327: ジャパンエクセレント投資法人 有価証券報告書 | H327: 2025年12月期 | I327: 個別物件表「PM会社」欄
A328: JEI-24 | B328: JEI | C328: 横浜弁天通第一生命ビルディング | D328: 株式会社第一ビルディング | E328: 第一ビルディング（独立系） | F328: 第三者 | G328: ジャパンエクセレント投資法人 有価証券報告書 | H328: 2025年12月期 | I328: 個別物件表「PM会社」欄
A329: JEI-25 | B329: JEI | C329: 新横浜アリーナ通りビル | D329: 丸紅リアルエステートマネジメント株式会社 | E329: 丸紅系 | F329: 第三者 | G329: ジャパンエクセレント投資法人 有価証券報告書 | H329: 2025年12月期 | I329: 個別物件表「PM会社」欄
A330: JEI-26 | B330: JEI | C330: 浦和SHビル | D330: 積水ハウス株式会社 | E330: 積水ハウス系（自社） | F330: 第三者 | G330: ジャパンエクセレント投資法人 有価証券報告書 | H330: 2025年12月期 | I330: 個別物件表「PM会社」欄
A331: JEI-27 | B331: JEI | C331: JEI広島八丁堀ビル | D331: 株式会社第一ビルディング | E331: 第一ビルディング（独立系） | F331: 第三者 | G331: ジャパンエクセレント投資法人 有価証券報告書 | H331: 2025年12月期 | I331: 個別物件表「PM会社」欄
A332: JEI-28 | B332: JEI | C332: SE札幌ビル | D332: 株式会社第一ビルディング | E332: 第一ビルディング（独立系） | F332: 第三者 | G332: ジャパンエクセレント投資法人 有価証券報告書 | H332: 2025年12月期 | I332: 個別物件表「PM会社」欄
A333: JEI-29 | B333: JEI | C333: 青葉通プラザ | D333: 株式会社第一ビルディング | E333: 第一ビルディング（独立系） | F333: 第三者 | G333: ジャパンエクセレント投資法人 有価証券報告書 | H333: 2025年12月期 | I333: 個別物件表「PM会社」欄
A334: JEI-30 | B334: JEI | C334: 大和南森町ビル | D334: 株式会社第一ビルディング | E334: 第一ビルディング（独立系） | F334: 第三者 | G334: ジャパンエクセレント投資法人 有価証券報告書 | H334: 2025年12月期 | I334: 個別物件表「PM会社」欄
... A337: JEI-33 | B337: JEI | C337: 札幌大手町ビル | D337: 株式会社ザイマックス北海道 | E337: 独立系（ザイマックス） | F337: 第三者 | G337: ジャパンエクセレント投資法人 有価証券報告書 | H337: 2025年12月期 | I337: 個別物件表「PM会社」欄
A338: MHR-01 | B338: MHR | C338: 六本木ヒルズ森タワー | D338: 森ビル株式会社 | E338: 森ビル系（自社） | F338: スポンサー系 | G338: 森ヒルズリート投資法人 有価証券報告書 | H338: 2026年1月期 | I338: 個別物件表「PM会社」欄 | J338: 用途別に複数社へ委託 原文「事務所：株式会社第一ビルディング 住宅：相互住宅株式会社」（用途別に複数社へ委託） ／複数社への委託
A339: MHR-02 | B339: MHR | C339: アーク森ビル | D339: 森ビル株式会社 | E339: 森ビル系（自社） | F339: スポンサー系 | G339: 森ヒルズリート投資法人 有価証券報告書 | H339: 2026年1月期 | I339: 個別物件表「PM会社」欄
A340: MHR-03 | B340: MHR | C340: 後楽森ビル | D340: 森ビル株式会社 | E340: 森ビル系（自社） | F340: スポンサー系 | G340: 森ヒルズリート投資法人 有価証券報告書 | H340: 2026年1月期 | I340: 個別物件表「PM会社」欄
A341: MHR-04 | B341: MHR | C341: 赤坂溜池タワー | D341: 森ビル株式会社 | E341: 森ビル系（自社） | F341: スポンサー系 | G341: 森ヒルズリート投資法人 有価証券報告書 | H341: 2026年1月期 | I341: 個別物件表「PM会社」欄
A342: MHR-05 | B342: MHR | C342: 愛宕グリーンヒルズ | D342: 森ビル株式会社 | E342: 森ビル系（自社） | F342: スポンサー系 | G342: 森ヒルズリート投資法人 有価証券報告書 | H342: 2026年1月期 | I342: 個別物件表「PM会社」欄
A343: MHR-06 | B343: MHR | C343: アークヒルズ サウスタワー | D343: 森ビル株式会社 | E343: 森ビル系（自社） | F343: スポンサー系 | G343: 森ヒルズリート投資法人 有価証券報告書 | H343: 2026年1月期 | I343: 個別物件表「PM会社」欄
A344: MHR-07 | B344: MHR | C344: 虎ノ門ヒルズ 森タワー | D344: 森ビル株式会社 | E344: 森ビル系（自社） | F344: スポンサー系 | G344: 森ヒルズリート投資法人 有価証券報告書 | H344: 2026年1月期 | I344: 個別物件表「PM会社」欄
A345: MHR-08 | B345: MHR | C345: オランダヒルズ森タワー | D345: 森ビル株式会社 | E345: 森ビル系（自社） | F345: スポンサー系 | G345: 森ヒルズリート投資法人 有価証券報告書 | H345: 2026年1月期 | I345: 個別物件表「PM会社」欄
A346: MHR-09 | B346: MHR | C346: 六本木ファーストプラザ | D346: 森ビル株式会社 | E346: 森ビル系（自社） | F346: スポンサー系 | G346: 森ヒルズリート投資法人 有価証券報告書 | H346: 2026年1月期 | I346: 個別物件表「PM会社」欄
A347: MHR-10 | B347: MHR | C347: 六本木ビュータワー | D347: 森ビル株式会社 | E347: 森ビル系（自社） | F347: スポンサー系 | G347: 森ヒルズリート投資法人 有価証券報告書 | H347: 2026年1月期 | I347: 個別物件表「PM会社」欄
A348: MHR-11 | B348: MHR | C348: ラフォーレ原宿（底地） | D348: － | E348: 記載なし・非開示 | F348: 非開示 | G348: 森ヒルズリート投資法人 有価証券報告書 | H348: 2026年1月期 | I348: 個別物件表「PM会社」欄
A349: JPR-01 | B349: JPR | C349: 兼松ビル | D349: 東京建物株式会社 | E349: 東京建物系（自社） | F349: スポンサー系 | G349: 日本プライムリアルティ投資法人 第48期有価証券報告書 | H349: 2025年12月期 | I349: 個別物件表「不動産管理会社」欄
A350: JPR-02 | B350: JPR | C350: 兼松ビル別館 | D350: 東京建物株式会社 | E350: 東京建物系（自社） | F350: スポンサー系 | G350: 日本プライムリアルティ投資法人 第48期有価証券報告書 | H350: 2025年12月期 | I350: 個別物件表「不動産管理会社」欄
A351: JPR-03 | B351: JPR | C351: ＪＰＲ人形町ビル | D351: 東京建物株式会社 | E351: 東京建物系（自社） | F351: スポンサー系 | G351: 日本プライムリアルティ投資法人 第48期有価証券報告書 | H351: 2025年12月期 | I351: 個別物件表「不動産管理会社」欄 | J351: 原文「日鉄興和不動産株式会社、他」（複数社が共同受託） ／複数社への委託
A352: JPR-04 | B352: JPR | C352: 新麹町ビル | D352: 東京建物株式会社 | E352: 東京建物系（自社） | F352: スポンサー系 | G352: 日本プライムリアルティ投資法人 第48期有価証券報告書 | H352: 2025年12月期 | I352: 個別物件表「不動産管理会社」欄
A353: JPR-05 | B353: JPR | C353: ＭＳ芝浦ビル | D353: 東京建物株式会社 | E353: 東京建物系（自社） | F353: スポンサー系 | G353: 日本プライムリアルティ投資法人 第48期有価証券報告書 | H353: 2025年12月期 | I353: 個別物件表「不動産管理会社」欄 | J353: 有報上「非開示」と記載
A354: JPR-06 | B354: JPR | C354: ＪＰＲ市ヶ谷ビル | D354: 東京建物株式会社 | E354: 東京建物系（自社） | F354: スポンサー系 | G354: 日本プライムリアルティ投資法人 第48期有価証券報告書 | H354: 2025年12月期 | I354: 個別物件表「不動産管理会社」欄
...

Sheet PM会社_集計
A1: 法人ID | B1: 投資法人名 | C1: 保有物件数 | D1: PM会社が判明した物件数 | E1: カバー率(%) | F1: PM会社数 | G1: 最多PM会社 | H1: 最多社のシェア(%) | I1: スポンサー系PMの比率(%) | J1: 出典資料 | K1: 取得日
A2: NBF | B2: 日本ビルファンド投資法人 | C2: 70 | D2: 69 | E2: 98.6 | F2: 24 | G2: 三井不動産株式会社 | H2: 29 | I2: 58.8 | J2: 日本ビルファンド投資法人 有価証券報告書 | K2: 2026-08-16
A3: JRE | B3: ジャパンリアルエステイト投資法人 | C3: 79 | D3: 76 | E3: 96.2 | F3: 13 | G3: 三菱地所株式会社 | H3: 32.9 | I3: 61.8 | J3: ジャパンリアルエステイト投資法人 有価証券報告書 | K3: 2026-08-16
A4: GOR | B4: グローバル・ワン不動産投資法人 | C4: 18 | D4: 16 | E4: 88.9 | F4: 9 | G4: 株式会社ザイマックス | H4: 25 | I4: 12.5 | J4: グローバル・ワン不動産投資法人 第45期有価証券報告書 | K4: 2026-08-16
A5: DOI | B5: 大和証券オフィス投資法人 | C5: 60 | D5: 58 | E5: 96.7 | F5: 6 | G5: 株式会社ベスト・プロパティ | H5: 37.9 | I5: 0 | J5: 大和証券オフィス投資法人 第40期有価証券報告書 | K5: 2026-08-16
A6: ICG | B6: いちごオフィスリート投資法人 | C6: 88 | D6: 85 | E6: 96.6 | F6: 18 | G6: 株式会社第一ビルデイング | H6: 34.1 | I6: 34.1 | J6: いちごオフィスリート投資法人 有価証券報告書 | K6: 2026-08-16
A7: JEI | B7: ジャパンエクセレント投資法人 | C7: 34 | D7: 32 | E7: 94.1 | F7: 10 | G7: 株式会社第一ビルディング | H7: 46.9 | I7: 29 | J7: ジャパンエクセレント投資法人 有価証券報告書 | K7: 2026-08-16
A8: MHR | B8: 森ヒルズリート投資法人 | C8: 11 | D8: 11 | E8: 100 | F8: 2 | G8: 森ビル株式会社 | H8: 90.9 | I8: 100 | J8: 森ヒルズリート投資法人 有価証券報告書 | K8: 2026-08-16
A9: JPR | B9: 日本プライムリアルティ投資法人 | C9: 68 | D9: 63 | E9: 92.6 | F9: 12 | G9: 東京建物株式会社 | H9: 54 | I9: 54.8 | J9: 日本プライムリアルティ投資法人 第48期有価証券報告書 | K9: 2026-08-16
A10: TRE | B10: 東急リアル・エステート投資法人 | C10: 28 | D10: 28 | E10: 100 | F10: 5 | G10: 東急プロパティマネジメント株式会社 | H10: 71.4 | I10: 96.4 | J10: 東急リアル・エステート投資法人 有価証券報告書 | K10: 2026-08-16
A11: HLC | B11: ヒューリックリート投資法人 | C11: 69 | D11: 62 | E11: 89.9 | F11: 2 | G11: ヒューリック株式会社 | H11: 98.4 | I11: 98.4 | J11: ヒューリックリート投資法人 有価証券報告書 | K11: 2026-08-16
A12: NUD | B12: NTT都市開発リート投資法人 | C12: 63 | D12: 60 | E12: 95.2 | F12: 10 | G12: アール・エー・アセット・マネジメント株式会社 | H12: 38.3 | I12: 81.7 | J12: NTT都市開発リート投資法人 有価証券報告書 | K12: 2026-08-16
A13: HFR | B13: 平和不動産リート投資法人 | C13: 138 | D13: 96 | E13: 69.6 | F13: 9 | G13: 株式会社長谷工ライブネット | H13: 38.5 | I13: 1.1 | J13: 平和不動産リート投資法人 有価証券報告書 | K13: 2026-08-16
A14: SHR | B14: 積水ハウス・リート投資法人 | C14: 150 | D14: 120 | E14: 80 | F14: 15 | G14: 積水ハウスシャーメゾンPM東京株式会社 | H14: 50 | I14: 66.7 | J14: 積水ハウス・リート投資法人 有価証券報告書 | K14: 2026-08-16
A15: MTR | B15: 森トラストリート投資法人 | C15: 20 | D15: 0 | E15: 0 | F15: 0 | G15: — | K15: 2026-08-16
A16: SKR | B16: サンケイリアルエステート投資法人 | C16: 16 | D16: 13 | E16: 81.2 | F16: 3 | G16: 株式会社サンケイビルマネジメント | H16: 76.9 | I16: 76.9 | J16: サンケイリアルエステート投資法人 有価証券報告書 | K16: 2026-08-16
A17: KDX | B17: ＫＤＸ不動産投資法人 | C17: 345 | D17: 339 | E17: 98.3 | F17: 16 | G17: ケネディクス・プロパティ・デザイン株式会社 | H17: 46.9 | I17: 47 | J17: ケネディクス・オフィス投資法人 有価証券報告書 | K17: 2026-08-16
A18: CTR | B18: セントラル・リート投資法人（旧ザイマックス・リート投資法人） | C18: 20 | D18: 18 | E18: 90 | F18: 5 | G18: 株式会社ザイマックス | H18: 72.2 | I18: 88.9 | J18: セントラル・リート投資法人 第16期有価証券報告書 | K18: 2026-08-16
A19: ORI | B19: Oneリート投資法人 | C19: 34 | D19: 28 | E19: 82.4 | F19: 9 | G19: 東洋不動産プロパティマネジメント株式会社 | H19: 35.7 | I19: 0 | J19: Oneリート投資法人 第25期有価証券報告書 | K19: 2026-08-16

Sheet GRESB評価
A1: 法人ID | B1: 投資法人名 | C1: GRESB星数（2025） | D1: グリーンスター | E1: 開示評価 | F1: 評価年 | G1: 主要用途 | H1: 情報源 | I1: 備考
A2: NBF | B2: 日本ビルファンド投資法人 | C2: 5 | D2: あり | E2: A（8年連続） | F2: 2025 | G2: オフィス | H2: 適時開示2025/10/2
A3: JRE | B3: ジャパンリアルエステイト投資法人 | C3: 5 | D3: 10年連続 | E3: — | F3: 2025 | G3: オフィス | H3: ESGサイト
A4: GOR | B4: グローバル・ワン不動産投資法人 | C4: 5 | D4: — | E4: — | F4: 2025 | G4: オフィス | H4: ユーザー提供（2026/8/16）
A5: DOI | B5: 大和証券オフィス投資法人 | C5: 4 | D5: 14年連続 | E5: — | F5: 2025 | G5: オフィス | H5: 公式サイト
A6: ICG | B6: いちごオフィスリート投資法人 | C6: 3 | D6: 継続取得 | E6: — | F6: 2025 | G6: オフィス | H6: ユーザー提供
A7: JEI | B7: ジャパンエクセレント投資法人 | C7: 4 | D7: 11年連続 | E7: — | F7: 2025 | G7: オフィス | H7: 適時開示2025/10/2
A8: MHR | B8: 森ヒルズリート投資法人 | C8: 4 | D8: 14年連続 | E8: — | F8: 2025 | G8: オフィス | H8: 公式サイト
A9: JPR | B9: 日本プライムリアルティ投資法人 | C9: 5 | D9: — | E9: — | F9: 2025 | G9: 総合 | H9: 資産運用報告
A10: TRE | B10: 東急リアル・エステート投資法人 | C10: 4 | D10: — | E10: — | F10: 2025 | G10: 総合 | H10: ユーザー提供（2026/8/16）
A11: HLC | B11: ヒューリックリート投資法人 | C11: 4 | D11: 9年連続 | E11: A（7年連続） | F11: 2025 | G11: 総合 | H11: 公式サイト
A12: NUD | B12: NTT都市開発リート投資法人 | C12: 4 | D12: — | E12: A（6年連続） | F12: 2025 | G12: 総合 | H12: 公式サイト
A13: HFR | B13: 平和不動産リート投資法人 | C13: 4 | D13: — | E13: — | F13: 2025 | G13: 総合 | H13: ユーザー提供
A14: SHR | B14: 積水ハウス・リート投資法人 | C14: 3 | D14: — | E14: A（6年連続） | F14: 2025 | G14: 総合 | H14: ユーザー提供（2024は4スター＝降格） | I14: 2024年は4スター。2025年に3スターへ降格
A15: MTR | B15: 森トラストリート投資法人 | C15: 4 | D15: — | E15: — | F15: 2025 | G15: オフィス | H15: ユーザー提供
A16: SKR | B16: サンケイリアルエステート投資法人 | C16: 2 | D16: — | E16: — | F16: 2025 | G16: オフィス | H16: ユーザー提供（2026/8/16）
A17: KDX | B17: ＫＤＸ不動産投資法人 | C17: 5 | D17: あり | E17: — | F17: 2025 | G17: 総合 | H17: IR見出し（本文要再確認）
A18: CTR | B18: セントラル・リート投資法人（旧ザイマックス・リート投資法人） | C18: 4 | D18: — | E18: — | F18: 2025 | G18: 総合 | H18: ユーザー提供 | I18: 2025年11月にセントラル・リート投資法人へ商号変更。評価はザイマックス・リート投資法人として受審
A19: ORI | B19: Oneリート投資法人 | C19: 4 | D19: — | E19: — | F19: 2025 | G19: オフィス | H19: ユーザー提供（2026/8/16）

Sheet GRESB_MC30点
A1: マネジメント・コンポーネント 30点 ─ 指標別の配点と要求水準
A2: 全指標が静的採点（絶対評価）。自助努力で満点到達が可能な領域。E:0% / S:34% / G:66%
A4: アスペクト | B4: 指標 | C4: 指標名 | D4: 配点 | E4: 次元 | F4: 満点を取るための要求水準・要件 | G4: 乗数・減点機構 | H4: 2026年変更
A5: リーダーシップ | B5: LE1 | C5: ESGリーダーシップ・コミットメント | D5: 0 | E5: G | F5: PRI・SBTi・TCFD・UNGC等への公的コミットメント、およびネットゼロ・コミットメント（SBTiネットゼロ基準、WorldGBC等）を選択 | G5: ―（非採点・報告目的のみ） | H5: 変更なし
A6: リーダーシップ | B6: LE2 | C6: ESG目標 | D6: 1 | E6: G | F6: 一般目標(環境/社会/ガバナンスの3分野=各1/3)を全て設定し「公開されている」を選択(公開2/4・非公開0/4)。課題別目標(人的資本・健康)も加点 | G6: ― | H6: 変更なし
A7: リーダーシップ | B7: LE3 | C7: ESG責任者 | D7: 2 | E7: G | F7: ESG(3/5)・気候関連(1/5)・人的資本(1/5)の3領域それぞれで「ESGが中核責務の専任従業員」を配置(5/5)。兼務は3/5、外部コンサルは2/5に減点 | G7: ― | H7: ★指標廃止(▲2点)
A8: リーダーシップ | B8: LE4 | C8: ESGタスクフォース/委員会 | D8: 1 | E8: G | F8: 取締役会・Cスイート・投資委員会・ファンド/ポートフォリオマネージャー(各3/8)から3者以上を委員に含める。実務担当者層は各2/8 | G8: 「その他」は手動検証(受理1/1・不受理0) | H8: 変更なし
A9: リーダーシップ | B9: LE5 | C9: 上級意思決定者 | D9: 1 | E9: G | F9: ESG(3/5)・気候(1/5)・人的資本(1/5)それぞれで、取締役会/Cスイート/投資委員会のいずれかに属する最上位意思決定者を指名 | G9: 「その他」は手動検証 | H9: 変更なし
A10: リーダーシップ | B10: LE6 | C10: 従業員ESG業績目標 | D10: 2 | E10: G | F10: ★前提条件: ESG目標に「あらかじめ定められた財務的帰結がある」こと。その上で取締役会・Cスイート・投資委員会・ファンドマネージャー(各3/8)を対象に含める。単なる目標設定では0点 | G10: エビデンス必須。手動検証で受理2/2・部分受理1/2・不受理0 | H10: 変更なし
A11: 方針 | B11: PO1 | C11: 環境方針 | D11: 1.5 | E11: G | F11: 環境課題13項目(生物多様性・気候変動適応・エネルギー・GHG・室内環境品質・資材調達・汚染防止・再エネ・災害レジリエンス・持続可能な調達・廃棄物・水・その他)を網羅=2/3。加えてネットゼロ方針の保有=1/3 | G11: エビデンス必須。受理2/2・部分受理1/2・不受理0 | H11: 変更なし
A12: 方針 | B12: PO2 | C12: 社会方針 | D12: 1.5 | E12: G | F12: 社会課題17項目(児童労働・地域開発・顧客満足・従業員エンゲージメント・健康福祉・報酬・強制労働・結社の自由・安全衛生4分類・人権・人的資本・労働基準・社会的企業連携・ステークホルダー関係)を網羅 | G12: エビデンス必須。同上 | H12: 変更なし
A13: 方針 | B13: PO3 | C13: ガバナンス方針 | D13: 1.5 | E13: G | F13: ガバナンス課題8項目(贈収賄・サイバーセキュリティ・データ保護・役員報酬・受託者責任・不正・政治献金・株主の権利)を網羅 | G13: エビデンス必須。同上 | H13: 変更なし
A14: 報告 | B14: RP1 | C14: ESG報告 | D14: 3.5 | E14: G | F14: ★MC最大配点。統合報告書(3/6・IIRCフレームワーク準拠必須)＋単独サステナビリティ報告書(2/6)＋年次報告書内のセクション(2/6)＋自社サイト専用ページ(2/3)を組合せ。各々で(a)報告レベルは「エンティティ」を選択(2/2、投資顧問/グループは1/2)、(b)GRI・EPRA・ISSB等のガイドライン準拠(1/6)、(c)第三者レビューは「外部保証(assured)」または「外部検証(verified)」で3/3(「外部チェック(checked)」のみは1/3) | G14: エビデンス必須。受理2/2・部分受理1/2・不受理0 | H14: 変更なし
A15: 報告 | B15: RP2.1 | C15: インシデント監視 | D15: 0.25 | E15: G | F15: 不祥事・違反等の監視プロセスを保有し、顧客・従業員・投資家(各1/4)への外部コミュニケーションを含める。全選択肢を選ばなくても満点可 | G15: 「その他」は自動検証。※セクターリーダー選定の判断材料に使用される | H15: 変更なし
A16: 報告 | B16: RP2.2 | C16: ESGインシデント発生状況 | D16: 0 | E16: G | F16: 報告年度中の罰金・制裁を伴うESG関連違反の件数・金額・係属中調査件数を報告 | G16: ―（非採点）※セクターリーダー選定の判断材料 | H16: 変更なし
... A39: ステークホルダー | B39: SE8 | C39: ステークホルダー苦情処理プロセス | D39: 0.5 | E39: S | F39: 正式な苦情処理プロセス。(1)特性9項目(アクセス容易・匿名・対話型・公平・改善志向・正当安全・予測可能・報復禁止・透明、各1/4)から4つ以上=2/3、(2)適用対象9者(各1/3)から3者以上=1/3 | G39: 「その他」は手動検証 | H39: 変更なし
A40: MC 合計 | D40: 30

Sheet GRESB_PC70点
A1: パフォーマンス・コンポーネント 70点 ─ 指標別の配点と要求水準（既存物件運用）
A2: 静的採点27.5点＋相対採点42.5点。E:89% / S:11% / G:0%。オレンジ=相対採点（他社比較で決定）、緑=静的採点（自助努力で満点可能）
A4: アスペクト | B4: 指標 | C4: 指標名 | D4: 配点 | E4: 採点方式 | F4: 次元 | G4: 内訳（サブ配点） | H4: 満点を取るための要求水準・要件 | I4: 乗数・減点機構 | J4: 2026年変更
A5: 報告特性 | B5: R1 | C5: スタンディング投資ポートフォリオ | D5: 0 | E5: ― | F5: ― | G5: ― | H5: アセットポータルの資産レベルデータから自動生成。%GAVと国のみ修正可能。★%GAVはエンティティ分類とピアグループ判定に使われるため、正確な入力が必須 | I5: ―（非採点） | J5: 変更なし
A6: リスク評価 | B6: RA1 | C6: ポートフォリオのリスク評価 | D6: 3 | E6: 静的 | F6: E | G6: ― | H6: 過去3年以内に資産レベルの環境・社会リスク評価を実施。18項目(生物多様性・建物安全性と資材・気候変動適応・土壌汚染・省エネ・エネルギー供給・洪水・GHG・健康福祉・室内環境品質・自然災害・規制・レジリエンス・社会経済・交通・廃棄物・水効率・水供給、各1/6)を選択し、★各項目ごとにポートフォリオカバー率100%を確保。ISO31000等の第三者標準への準拠も報告 | I6: ポートフォリオカバー率(%)が乗数 | J6: 変更なし
A7: リスク評価 | B7: RA2 | C7: 技術的建物診断 | D7: 3 | E7: 静的 | F7: E | G7: エネルギー1.5 / 水1.0 / 廃棄物0.5 | H7: 過去3年以内に実施した技術的建物診断(テクニカル・ビルディング・アセスメント)。★エネルギー診断が1.5点と最大。資産レベルデータから自動集計され、カバー率が乗数として作用するため全物件での実施が必要 | I7: カバー率(%)が乗数(ポートフォリオレベルに集計) | J7: ★▲1点(2点へ)
A8: リスク評価 | B8: RA3 | C8: 省エネ施策 | D8: 1.5 | E8: 静的 | F8: E | G8: 0.25点×6施策 | H8: 過去3年以内に実施した省エネ施策を資産ポータルで報告。★報告した施策1件につき0.25点。6種類の施策を報告すれば満点 | I8: ―（施策数がそのまま点数） | J8: ★▲1点(0.5点へ)
A9: リスク評価 | B9: RA4 | C9: 節水施策 | D9: 1 | E9: 静的 | F9: E | G9: 0.25点×4施策 | H9: 過去3年以内に実施した節水施策。1件につき0.25点、4種類で満点 | I9: ― | J9: ★▲0.75点(0.25点へ)
A10: リスク評価 | B10: RA5 | C10: 廃棄物管理施策 | D10: 0.5 | E10: 静的 | F10: E | G10: 0.25点×2施策 | H10: 過去3年以内に実施した廃棄物管理施策。1件につき0.25点、2種類で満点 | I10: ― | J10: ★▲0.25点(0.25点へ)
A11: 目標 | B11: T1.1 | C11: ポートフォリオ改善目標 | D11: 1 | E11: 静的 | F11: E | G11: 2/9×目標＋1/9(外部公表) | H11: 長期の性能改善目標を設定。★目標1件につき最大点の2/9、さらにその目標を外部公表していれば1/9が加算。3件の目標を設定し全て外部公表すれば満点(2/9×3＋1/9×3=1) | I11: 「その他」は手動検証 | J11: 変更なし
A12: 目標 | B12: T1.2 | C12: ネットゼロ目標 | D12: 1 | E12: 静的 | F12: E | G12: ― | H12: ネットゼロに整合したGHG削減目標の存在。★2025年からエビデンス提出が必須化(2025年は手動検証の対象外だが将来の検証基準策定に使用)。達成方法(省エネ・再エネ・オフセット・脱炭素予算・取得売却方針)の説明も記載 | I12: エビデンス提出必須 | J12: ★+1点(2点へ)
A13: テナント＆コミュニティ | B13: TC1 | C13: テナント・エンゲージメント・プログラム | D13: 1 | E13: 静的 | F13: S | G13: ― | H13: ESG課題を含むテナント engagement。手法9種(建物コミュニケーション・個別FBセッション・エネルギー/水/廃棄物消費のFB提供・SNS/オンライン・エンゲージメント会議・テナントESGガイド・テナントESG研修・ESG啓発イベント、各1/4)から4つ以上 | I13: ★カバー率はドロップダウン選択で乗数化: 0-25%=0.25 / 25-50%=0.5 / 50-75%=0.75 / 75-100%=1.00 | J13: 変更なし
A14: テナント＆コミュニティ | B14: TC2.1 | C14: テナント満足度調査 | D14: 1 | E14: 静的 | F14: S | G14: 調査種別2/3＋定量指標1/3 | H14: 過去3年以内に実施。★独立第三者による調査=3/3(社内実施は2/3)。テナントカバー率が乗数。定量指標(1/3)ではNPS採用=3/3(その他指標は2/3) | I14: テナントカバー率(%)が乗数。エビデンス手動検証。回答率は採点対象外 | J14: 変更なし
A15: テナント＆コミュニティ | B15: TC2.2 | C15: テナント満足度改善プログラム | D15: 1 | E15: 静的 | F15: S | G15: ― | H15: TC2.1の結果に基づく改善プログラム。資産別アクションプラン策定・PM/AMとのFBセッション・個別テナントとのFBセッション(各1/2)から2つ以上 | I15: ★TC2.1で0点の場合、本指標も0点(連動制約) | J15: 変更なし
A16: テナント＆コミュニティ | B16: TC3 | C16: テナント内装・改修プログラム | D16: 1.5 | E16: 静的 | F16: E | G16: ― | H16: ESG課題を含む内装・改修プログラム。最低内装基準の達成支援・テナント内装ガイド・最低内装基準の規定・調達支援(各1/3)から3つ以上。2025年新設の非採点セクションでESGトピック(アップフロントカーボン・省エネ・廃棄物・節水・空気質・生物多様性)を報告 | I16: カバー率ドロップダウンが乗数(0.25/0.5/0.75/1.00) | J16: ★+1点(2.5点へ)。追加1点はESGトピック(内包炭素含む)に配分
... A31: 建物認証 | B31: BC2 | C31: 省エネ格付(エネルギー・レーティング) | D31: 2 | E31: 相対 | F31: E | G31: ― | H31: BELS、EPC等の省エネルギー格付を取得した延床面積の割合。★BC1とは別枠のため、CASBEE/DBJ Green Building(BC1.2)とBELS(BC2)の併用が両方の点を取る定石 | I31: ベンチマーク比較 | J31: 変更なし
A32: PC 合計 | D32: 70
A33: うち相対採点 | D33: 42.5
A34: うち静的採点 | D34: 27.5
